Workbook

Sheet Graph
A3: Month | B3: Net | C3: Checking | D3: Savings | E3: Investment | F3: Change % MoM | G3: Change % YoY | I3: Category | J3: 2014 | K3: 2015 | L3: 2016 | M3: 2017 | N3: 2018 | O3: 2019 | P3: 2020 | Q3: 2021 | R3: 2022 | S3: 2023 | T3: 2024 | U3: 2025 | V3: 2026
A4: 41640 | B4: 21649.025 | C4: 1271.79 | D4: 10006.255 | E4: 10370.98 | F4: 0 | I4: Cable | J4: 851.91 | K4: 987.32 | L4: 1197.49 | M4: 1543.82 | N4: 2034.95 | O4: 1970.25 | P4: 3356.2 | Q4: 3292.78 | R4: 3440.28 | S4: 2037.2 | T4: 3993.94 | U4: 4846.57 | V4: =ABS(Summary!F21) -> 1782.99
A5: 41671 | B5: 22401.335 | C5: 1297.42 | D5: 9951.605 | E5: 11152.31 | F5: =(B5-B4)/B4 -> 0.034750295 | I5: Car Insurance | J5: 927.31 | K5: 495.81 | L5: 664 | M5: 725.62 | N5: 806.4 | O5: 862.29 | P5: 812.38 | Q5: 1736.44 | R5: 1845.05 | S5: 2349.59 | T5: 4515 | U5: 4026.47 | V5: =ABS(Summary!F22) -> 1726.67
A6: 41699 | B6: 23723.73 | C6: 1345.88 | D6: 10747.5 | E6: 11630.35 | F6: =(B6-B5)/B5 -> 0.059031973 | I6: Cleaners | J6: 96.56 | K6: 91 | L6: 20 | M6: 0 | N6: 0 | O6: 0 | P6: 0 | Q6: 0 | R6: 0 | S6: 0 | T6: 0 | U6: 0 | V6: =ABS(Summary!F23) -> 0
A7: 41730 | B7: 23432.04 | C7: 1400 | D7: 10273.68 | E7: 11758.36 | F7: =(B7-B6)/B6 -> -0.012295284 | I7: Clothes | J7: 1332.7 | K7: 116.71 | L7: 258.73 | M7: 819.96 | N7: 557.72 | O7: 317 | P7: 322 | Q7: 709 | R7: 883 | S7: 1865.7 | T7: 3446.48 | U7: 3322.58 | V7: =ABS(Summary!F24) -> 1827.19
A8: 41760 | B8: 24523.49 | C8: 1450.97 | D8: 10694.02 | E8: 12378.5 | F8: =(B8-B7)/B7 -> 0.046579384 | I8: Utilities | J8: 0 | K8: 0 | L8: 0 | M8: 0 | N8: 0 | O8: 0 | P8: 0 | Q8: 277.75 | R8: 4044.92 | S8: 7082.98 | T8: 8422.68 | U8: 8054.25 | V8: =ABS(Summary!F25) -> 3543.06
A9: 41791 | B9: 24628.91 | C9: 1500.93 | D9: 10109.97 | E9: 13018.01 | F9: =(B9-B8)/B8 -> 0.0042987356 | I9: Dining | J9: 7007.295 | K9: 4867.59 | L9: 7576.94 | M9: 9145.189 | N9: 7811.36 | O9: 9042.62 | P9: 7226.48 | Q9: 6448.99 | R9: 10189.09 | S9: 15350.63 | T9: 16817.09 | U9: 18139.49 | V9: =ABS(Summary!F26) -> 8682.83
A10: 41821 | B10: 25890.34 | C10: 1550.26 | D10: 11063.67 | E10: 13276.41 | F10: =(B10-B9)/B9 -> 0.051217451 | I10: Entertainment | J10: 589.01 | K10: 1280.43 | L10: 2038.2 | M10: 3337.86 | N10: 2322 | O10: 3807.97 | P10: 2895.82 | Q10: 2035.44 | R10: 3210.96 | S10: 2512 | T10: 4405 | U10: 4789.02 | V10: =ABS(Summary!F27) -> 2548.38
A11: 41852 | B11: 26583.16 | C11: 1600.44 | D11: 11204.09 | E11: 13778.63 | F11: =(B11-B10)/B10 -> 0.026759788 | I11: Gas | J11: 2440.2405 | K11: 1967.55 | L11: 2032.52 | M11: 2661.15 | N11: 2767.39 | O11: 2393.93 | P11: 1819.54 | Q11: 3552.42 | R11: 5292.16 | S11: 2735.74 | T11: 2230.68 | U11: 2605.1 | V11: =ABS(Summary!F28) -> 1491.94
A12: 41883 | B12: 27276.63 | C12: 1650 | D12: 10319.13 | E12: 15307.5 | F12: =(B12-B11)/B11 -> 0.026086816 | I12: Gifts | J12: 431.16 | K12: 1026.8 | L12: 320 | M12: 1446.25 | N12: 1912 | O12: 2816.02 | P12: 4201.05 | Q12: 2303.89 | R12: 4561.3 | S12: 4085.81 | T12: 7078.06 | U12: 3429 | V12: =ABS(Summary!F29) -> 2699.84
A13: 41913 | B13: 27004.21 | C13: 1650.49 | D13: 9804.71 | E13: 15549.01 | F13: =(B13-B12)/B12 -> -0.0099873042 | I13: Grocery | J13: 622.87 | K13: 844.37 | L13: 1296.999 | M13: 2195.06 | N13: 1338.21 | O13: 4714.05 | P13: 4736.63 | Q13: 5762.05 | R13: 9675.2 | S13: 11091.32 | T13: 14672.91 | U13: 13428.26 | V13: =ABS(Summary!F30) -> 4870.26
A14: 41944 | B14: 26880.92 | C14: 1700 | D14: 9288.45 | E14: 15892.47 | F14: =(B14-B13)/B13 -> -0.0045655844 | I14: Gym | J14: 275.93 | K14: 0 | L14: 525.21 | M14: 1035.99 | N14: 1092 | O14: 1135.78 | P14: 585.66 | Q14: 1449.76 | R14: 2210.21 | S14: 1559 | T14: 2664.8 | U14: 1858 | V14: =ABS(Summary!F31) -> 359
A15: 41974 | B15: 27223.75 | C15: 1750 | D15: 9370.99 | E15: 16102.76 | F15: =(B15-B14)/B14 -> 0.012753656 | G15: =(B15-B4)/B4 -> 0.25750467 | I15: Loan | J15: 10860.31 | K15: 8088.87 | L15: 3286.78 | M15: 0 | N15: 0 | O15: 0 | P15: 0 | Q15: 0 | R15: 0 | S15: 3042 | T15: 0 | U15: 0 | V15: =ABS(Summary!F32) -> 0
A16: 42005 | B16: 28593.49 | C16: 1800.15 | D16: 9866.77 | E16: 16426.57 | F16: =(B16-B15)/B15 -> 0.050314156 | I16: Misc | J16: 2230.39 | K16: 2452.72 | L16: 1760.55 | M16: 2736.42 | N16: 5846.81 | O16: 7540.08 | P16: 3321.9 | Q16: 5192.64 | R16: 10567.66 | S16: 15194.14 | T16: 8684.53 | U16: 8066.38 | V16: =ABS(Summary!F33) -> 2080
A17: 42036 | B17: 28220.99 | C17: 1850.06 | D17: 8868.08 | E17: 17002.85 | F17: =(B17-B16)/B16 -> -0.013027441 | I17: Offering | J17: 785.92 | K17: =481.36+456 -> 937.36 | L17: 878.05 | M17: 1666.15 | N17: 1440 | O17: 1552.64 | P17: 1817 | Q17: 1402.21 | R17: 2129 | S17: 4066 | T17: 5273 | U17: 8410 | V17: =ABS(Summary!F34) -> 4955.54
A18: 42064 | B18: 28589.92 | C18: 1900 | D18: 8800.08 | E18: 17584.84 | F18: =(B18-B17)/B17 -> 0.013072894 | I18: Rent | J18: 6436.94 | K18: 10040.33 | L18: 8503.97 | M18: 8283.08 | N18: 11107.76 | O18: 9917.18 | P18: 16928.247 | Q18: 10437.13 | R18: 33954.52 | S18: 36146.49 | T18: 50666 | U18: 48773 | V18: =ABS(Summary!F35) -> 25304
A19: 42095 | B19: 29266.99 | C19: 1900 | D19: 9110.4 | E19: 17951.05 | F19: =(B19-B18)/B18 -> 0.023682123 | I19: Travel | J19: 472.98 | K19: 345.32 | L19: 1280.54 | M19: 1057.97 | N19: 5707.71 | O19: 6035.42 | P19: 816 | Q19: 10424.68 | R19: 10431 | S19: 11718.75 | T19: 13939 | U19: 4603.3 | V19: =ABS(Summary!F36) -> 5677
A20: 42125 | B20: 30007.84 | C20: 1950 | D20: 9359.4 | E20: 18342.9 | F20: =(B20-B19)/B19 -> 0.025313502 | I20: Parents | J20: 0 | K20: 0 | L20: 1153.27 | M20: 1769.96 | N20: 3186.91 | O20: 2725.69 | P20: 2409.61 | Q20: 4132.62 | R20: 1959 | S20: 4032 | T20: 8401 | U20: 9116 | V20: =ABS(Summary!F37) -> 3045
A21: 42156 | B21: 30396.9 | C21: 1969.8 | D21: 9478.2 | E21: 18668.9 | F21: =(B21-B20)/B20 -> 0.012965278 | I21: Car | J21: 37.82 | K21: 267.82 | L21: 537.04 | M21: 262 | N21: 612 | O21: 266.51 | P21: 10393 | Q21: 4361.26 | R21: 3532 | S21: 3311 | T21: 1793 | U21: 2322 | V21: =ABS(Summary!F38) -> 830
A22: 42186 | B22: 31336.35 | C22: 2000.73 | D22: 9699.62 | E22: 19256 | F22: =(B22-B21)/B21 -> 0.030906112 | I22: House | J22: 0 | K22: 0 | L22: 0 | M22: 0 | N22: 0 | O22: 0 | P22: 0 | Q22: 3437.57 | R22: 3080.19 | S22: 5129.57 | T22: 14326.18 | U22: 3911.1 | V22: =ABS(Summary!F39) -> 1439.3
A23: 42217 | B23: 31108.32 | C23: 2000.45 | D23: 9537.07 | E23: 19570.8 | F23: =(B23-B22)/B22 -> -0.0072768526 | I23: School | J23: 0 | K23: 0 | L23: 0 | M23: 3657 | N23: 85.86 | O23: 2217 | P23: 0 | Q23: 0 | R23: 0 | S23: 0 | T23: 2421.8 | U23: 3036 | V23: =ABS(Summary!F40) -> 11681
A24: 42248 | B24: 31657.56 | C24: 2049.7 | D24: 9702.61 | E24: 19905.25 | F24: =(B24-B23)/B23 -> 0.017655727 | I24: Baby Sitter | J24: 0 | K24: 0 | L24: 0 | M24: 0 | N24: 0 | O24: 0 | P24: 0 | Q24: 0 | R24: 0 | S24: 0 | T24: 4334 | U24: 7446 | V24: =ABS(Summary!F41) -> 4801
A25: 42278 | B25: 33152.22 | C25: 2100.06 | D25: 10049.27 | E25: 20502.89 | F25: =(B25-B24)/B24 -> 0.047213367 | I25: Total | J25: =SUM(J4:J24) -> 35399.346 | K25: =SUM(K4:K23) -> 33810 | L25: =SUM(L4:L23) -> 33330.289 | M25: =SUM(M4:M23) -> 42343.479 | N25: =SUM(N4:N23) -> 48629.08 | O25: =SUM(O4:O23) -> 57314.43 | P25: =SUM(P4:P23) -> 61641.517 | Q25: =SUM(Q4:Q23) -> 66956.63 | R25: =SUM(R4:R23) -> 111005.54 | S25: =SUM(S4:S23) -> 133309.92 | T25: =SUM(T4:T24) -> 178085.15 | U25: =SUM(U4:U24) -> 160182.52 | V25: =SUM(V4:V23) -> 84544
A26: 42309 | B26: 34074.55 | C26: 2150.06 | D26: 10675.1 | E26: 21049.39 | F26: =(B26-B25)/B25 -> 0.027821063
A27: 42339 | B27: 34719.28 | C27: 2200.12 | D27: 10888.1 | E27: 21418.65 | F27: =(B27-B26)/B26 -> 0.01892116 | G27: =(B27-B16)/B16 -> 0.21423723 | I27: Category | J27: Total
A28: 42370 | B28: 35458.24 | C28: 2250.81 | D28: 11403.8 | E28: 21803.63 | F28: =(B28-B27)/B27 -> 0.021283852
A29: 42401 | B29: 35923.871 | C29: 2300.67 | D29: 11442.381 | E29: 22180.82 | F29: =(B29-B28)/B28 -> 0.013131814 | I29: Sum of 2014 | J29: Sum of 2015 | K29: Sum of 2016 | L29: Sum of 2017 | M29: Sum of 2018 | N29: Sum of 2019 | O29: Sum of 2020 | P29: Sum of 2021 | Q29: Sum of 2022 | R29: Sum of 2023 | S29: Sum of 2024 | T29: Sum of 2025 | U29: Sum of 2026
A30: 42430 | B30: 35940.411 | C30: 2350.87 | D30: 11029.601 | E30: 22559.94 | F30: =(B30-B29)/B29 -> 0.00046041809 | I30: 35399.346 | J30: 33810 | K30: 33330.289 | L30: 42343.479 | M30: 48629.08 | N30: 57314.43 | O30: 61641.517 | P30: 66956.63 | Q30: 111005.54 | R30: 133309.92 | S30: 178085.15 | T30: 160182.52 | U30: 5867
A31: 42461 | B31: 38992.73 | C31: 2400.64 | D31: 11581.9 | E31: 25010.19 | F31: =(B31-B30)/B30 -> 0.084927214
A32: 42491 | B32: 38568.28 | C32: 2450.66 | D32: 10608.47 | E32: 25509.15 | F32: =(B32-B31)/B31 -> -0.010885362
A33: 42522 | B33: 40042.39 | C33: 2500.3 | D33: 11550.75 | E33: 25991.34 | F33: =(B33-B32)/B32 -> 0.038220787
A34: 42552 | B34: 41991.17 | C34: 2550 | D34: 12479.63 | E34: 26961.54 | F34: =(B34-B33)/B33 -> 0.048667924
A35: 42583 | B35: 43010.93 | C35: 2600.99 | D35: 12659.63 | E35: 27750.31 | F35: =(B35-B34)/B34 -> 0.024285106
A36: 42614 | B36: 52337.87 | C36: 2650 | D36: 13404.63 | E36: 36283.24 | F36: =(B36-B35)/B35 -> 0.21685046
A37: 42644 | B37: 54547.5 | C37: 2700 | D37: 14589.63 | E37: 37257.87 | F37: =(B37-B36)/B36 -> 0.042218569
A38: 42675 | B38: 56251.08 | C38: 2750.96 | D38: 15614.63 | E38: 37885.49 | F38: =(B38-B37)/B37 -> 0.031231129
A39: 42705 | B39: 57734.43 | C39: 2800 | D39: 15801.63 | E39: 39132.8 | F39: =(B39-B38)/B38 -> 0.02637016 | G39: =(B39-B28)/B28 -> 0.62823733
A40: 42736 | B40: 59381.57 | C40: 2850.38 | D40: 16889.63 | E40: 39641.56 | F40: =(B40-B39)/B39 -> 0.028529597
A41: 42767 | B41: 63826.23 | C41: 2900.83 | D41: 16027.63 | E41: 44897.77 | F41: =(B41-B40)/B40 -> 0.074849149
A42: 42795 | B42: 67300.78 | C42: 2950.76 | D42: 18499.63 | E42: 45850.39 | F42: =(B42-B41)/B41 -> 0.05443765
A43: 42826 | B43: 69374.7 | C43: 3000 | D43: 19744.63 | E43: 46630.07 | F43: =(B43-B42)/B42 -> 0.03081569
A44: 42856 | B44: 70547.82 | C44: 3050 | D44: 19884.63 | E44: 47613.19 | F44: =(B44-B43)/B43 -> 0.016909911
A45: 42887 | B45: 72552.12 | C45: 3100 | D45: 20709.63 | E45: 48742.49 | F45: =(B45-B44)/B44 -> 0.028410516
A46: 42917 | B46: 74761.81 | C46: 3150 | D46: 21708.75 | E46: 49903.06 | F46: =(B46-B45)/B45 -> 0.030456588
A47: 42948 | B47: 75832.99 | C47: 3200.05 | D47: 20184 | E47: 52448.94 | F47: =(B47-B46)/B46 -> 0.014327904
A48: 42979 | B48: 77967.44 | C48: 3250 | D48: 20815 | E48: 53902.44 | F48: =(B48-B47)/B47 -> 0.028146721
A49: 43009 | B49: 82843.96 | C49: 3300 | D49: 24552.19 | E49: 54991.77 | F49: =(B49-B48)/B48 -> 0.062545596
A50: 43040 | B50: 84258.73 | C50: 3350.93 | D50: 24672.29 | E50: 56235.51 | F50: =(B50-B49)/B49 -> 0.017077527
A51: 43070 | B51: 83360.54 | C51: 3400.21 | D51: 23016.29 | E51: 56944.04 | F51: =(B51-B50)/B50 -> -0.010659904 | G51: =(B51-B40)/B40 -> 0.40381165
A52: 43101 | B52: 88002.01 | C52: 3450.72 | D52: 24254.29 | E52: 60297 | F52: =(B52-B51)/B51 -> 0.055679462
A53: 43132 | B53: 89676.12 | C53: 3500.66 | D53: 24985.29 | E53: 61190.17 | F53: =(B53-B52)/B52 -> 0.019023543
A54: 43160 | B54: 91419.65 | C54: 3550.66 | D54: 27085.29 | E54: 60783.7 | F54: =(B54-B53)/B53 -> 0.019442523
A55: 43191 | B55: 93461.5 | C55: 3600.66 | D55: 28235.29 | E55: 61625.55 | F55: =(B55-B54)/B54 -> 0.022334914
A56: 43221 | B56: 94707.96 | C56: 3650.73 | D56: 28310.29 | E56: 62746.94 | F56: =(B56-B55)/B55 -> 0.013336615
A57: 43252 | B57: 95737.19 | C57: 3700 | D57: 28185.29 | E57: 63851.9 | F57: =(B57-B56)/B56 -> 0.010867408
A58: 43282 | B58: 97583.59 | C58: 3750.41 | D58: 28895.29 | E58: 64937.89 | F58: =(B58-B57)/B57 -> 0.019286131
A59: 43313 | B59: 99555.4 | C59: 3800.42 | D59: 29470.29 | E59: 66284.69 | F59: =(B59-B58)/B58 -> 0.020206369
A60: 43344 | B60: 100370.47 | C60: 3850 | D60: 28947.29 | E60: 67573.18 | F60: =(B60-B59)/B59 -> 0.0081870998
A61: 43374 | B61: 101868.64 | C61: 3900 | D61: 30085.29 | E61: 67883.35 | F61: =(B61-B60)/B60 -> 0.014926402
A62: 43405 | B62: 102746.66 | C62: 3950 | D62: 30735.29 | E62: 68061.37 | F62: =(B62-B61)/B61 -> 0.0086191393
A63: 43435 | B63: 103815.63 | C63: 4000 | D63: 31410.29 | E63: 68405.34 | F63: =(B63-B62)/B62 -> 0.010403939 | G63: =(B63-B52)/B52 -> 0.17969612
A64: 43466 | B64: 103701.28 | C64: 4050 | D64: 32036.29 | E64: 67614.99 | F64: =(B64-B63)/B63 -> -0.0011014719
A65: 43497 | B65: 111548.5 | C65: 4100 | D65: 31526.29 | E65: 75922.21 | F65: =(B65-B64)/B64 -> 0.07567139
A66: 43525 | B66: 115410.87 | C66: 4150 | D66: 33652.04 | E66: 77608.83 | F66: =(B66-B65)/B65 -> 0.034625029
A67: 43556 | B67: 117380.3 | C67: 4200 | D67: 34977.06 | E67: 78203.24 | F67: =(B67-B66)/B66 -> 0.01706451
A68: 43586 | B68: 122448.72 | C68: 4250 | D68: 41052.75 | E68: 77145.97 | F68: =(B68-B67)/B67 -> 0.043179477
A69: 43617 | B69: 126326.14 | C69: 4300.29 | D69: 42377.75 | E69: 79648.1 | F69: =(B69-B68)/B68 -> 0.031665664
A70: 43647 | B70: 127607.85 | C70: 4350.29 | D70: 39068.75 | E70: 84188.81 | F70: =(B70-B69)/B69 -> 0.010146039
A71: 43678 | B71: 125854.18 | C71: 4400.58 | D71: 40156.75 | E71: 81296.85 | F71: =(B71-B70)/B70 -> -0.01374265
A72: 43709 | B72: 128779.55 | C72: 4450.58 | D72: 41081.75 | E72: 83247.22 | F72: =(B72-B71)/B71 -> 0.023244123
A73: 43739 | B73: 134475.75 | C73: 4500 | D73: 43865.9 | E73: 86109.85 | F73: =(B73-B72)/B72 -> 0.044232178
A74: 43770 | B74: 136040.93 | C74: 4550 | D74: 44645.08 | E74: 86845.85 | F74: =(B74-B73)/B73 -> 0.011639125
A75: 43800 | B75: 136087.78 | C75: 4600 | D75: 43453.9 | E75: 88033.88 | F75: =(B75-B74)/B74 -> 0.00034438165 | G75: =(B75-B64)/B64 -> 0.31230569
A76: 43831 | B76: 143371.09 | C76: 4650.0033 | D76: 43623.9 | E76: 95097.19 | F76: =(B76-B75)/B75 -> 0.053519231
A77: 43862 | B77: 145478.28 | C77: 4700.0033 | D77: 45745.9 | E77: 95032.38 | F77: =(B77-B76)/B76 -> 0.014697454
A78: 43891 | B78: 148894.11 | C78: 4750.0033 | D78: 46820.08 | E78: 97324.03 | F78: =(B78-B77)/B77 -> 0.023479999
A79: 43922 | B79: 151665.39 | C79: 4800.6433 | D79: 49594 | E79: 97270.75 | F79: =(B79-B78)/B78 -> 0.018612422
A80: 43952 | B80: 166271.39 | C80: 4850 | D80: 57238 | E80: 104183.39 | F80: =(B80-B79)/B79 -> 0.096304083
A81: 43983 | B81: 170080.15 | C81: 4900 | D81: 58963 | E81: 106217.15 | F81: =(B81-B80)/B80 -> 0.022906887
A82: 44013 | B82: 177535.14 | C82: 4950 | D82: 60634.77 | E82: 111950.37 | F82: =(B82-B81)/B81 -> 0.043832217
A83: 44044 | B83: 182809.5 | C83: 5000 | D83: 60676.58 | E83: 117132.92 | F83: =(B83-B82)/B82 -> 0.029708823
A84: 44075 | B84: 185072.62 | C84: 5050 | D84: 61577.58 | E84: 118445.04 | F84: =(B84-B83)/B83 -> 0.012379663
A85: 44105 | B85: 189313 | C85: 5100 | D85: 63123.36 | E85: 121089.64 | F85: =(B85-B84)/B84 -> 0.022911979
A86: 44136 | B86: 189702 | C86: 5150 | D86: 53932.22 | E86: 130619.78 | F86: =(B86-B85)/B85 -> 0.0020547981
A87: 44166 | B87: 182996.97 | C87: 5200 | D87: 42043.91 | E87: 135753.06 | F87: =(B87-B86)/B86 -> -0.035345068 | G87: =(B87-B76)/B76 -> 0.27638679
A88: 44217 | B88: 202970.41 | C88: 5250 | D88: 42924.91 | E88: 154795.5 | F88: =(B88-B87)/B87 -> 0.10914629
A89: 44248 | B89: 209736.35 | C89: 5300 | D89: 42164.91 | E89: 162271.44 | F89: =(B89-B88)/B88 -> 0.033334613
A90: 44276 | B90: 217852.64 | C90: 5350 | D90: 46891.73 | E90: 165610.91 | F90: =(B90-B89)/B89 -> 0.038697584
A91: 44307 | B91: 228506.33 | C91: 5400 | D91: 42824 | E91: 180282.33 | F91: =(B91-B90)/B90 -> 0.048903194
A92: 44337 | B92: 235452.42 | C92: 5450 | D92: 42932.22 | E92: 187070.2 | F92: =(B92-B91)/B91 -> 0.030397801
A93: 44368 | B93: 238023.39 | C93: 5500 | D93: 43957.22 | E93: 188566.17 | F93: =(B93-B92)/B92 -> 0.010919276
A94: 44398 | B94: 241929.56 | C94: 5550 | D94: 44469.98 | E94: 191909.58 | F94: =(B94-B93)/B93 -> 0.016410866
A95: 44429 | B95: 339896.92 | C95: 5600 | D95: 135439.03 | E95: 198857.89 | F95: =(B95-B94)/B94 -> 0.40494167
A96: 44460 | B96: 327743.53 | C96: 5906.61 | D96: 124810.03 | E96: 197026.89 | F96: =(B96-B95)/B95 -> -0.035756105
A97: 44490 | B97: 339672.39 | C97: 6024.77 | D97: 119636.41 | E97: 214011.21 | F97: =(B97-B96)/B96 -> 0.036396935
A98: 44521 | B98: 360809.39 | C98: 6509.77 | D98: 133361.41 | E98: 220938.21 | F98: =(B98-B97)/B97 -> 0.062227607
A99: 44551 | B99: 361300.74 | C99: 6609 | D99: 130315.36 | E99: 224376.38 | F99: =(B99-B98)/B98 -> 0.0013617994 | G99: =(B99-B88)/B88 -> 0.78006607
A100: 44562 | B100: 374494.79 | C100: 8071 | D100: 134313.16 | E100: 232110.63 | F100: =(B100-B99)/B99 -> 0.036518193
A101: 44593 | B101: 382192.76 | C101: 8509 | D101: 139417.36 | E101: 234266.4 | F101: =(B101-B100)/B100 -> 0.020555613
A102: 44621 | B102: 389681.92 | C102: 8759 | D102: 144893.29 | E102: 236029.63 | F102: =(B102-B101)/B101 -> 0.019595243
...

Sheet Investment
B2: Investment*
C3: 2026 | D3: Invest | E3: Gain/ (Loss) | F3: FMV | G3: % Increase | H3: % Gained
B4: Etrade | C4: =Summary!Y4 -> 206508 | D4: =Summary!Z4 -> 0 | E4: =Summary!AA4 -> 7081 | F4: =Summary!AB4 -> 213589 | G4: =Summary!AC4 -> 0.034289229 | H4: =Summary!AD4 -> 0.034289229
B5: BC | C5: =Summary!Y5 -> 127109 | D5: =Summary!Z5 -> 5000 | E5: =Summary!AA5 -> 0 | F5: =Summary!AB5 -> 132109 | G5: =Summary!AC5 -> 0.039336318 | H5: =Summary!AD5 -> 0
B6: Roth IRA | C6: =Summary!Y6 -> 62955 | D6: =Summary!Z6 -> 1500 | E6: =Summary!AA6 -> 7439 | F6: =Summary!AB6 -> 71894 | G6: =Summary!AC6 -> 0.14199031 | H6: =Summary!AD6 -> 0.11541385
B7: TSP | C7: =Summary!Y7 -> 27298 | D7: =Summary!Z7 -> 0 | E7: =Summary!AA7 -> 0 | F7: =Summary!AB7 -> 27298 | G7: =Summary!AC7 -> 0 | H7: =Summary!AD7 -> 0
B8: UTMA | C8: =Summary!Y8 -> 3879 | D8: =Summary!Z8 -> 2600 | E8: =Summary!AA8 -> 641 | F8: =Summary!AB8 -> 7120 | G8: =Summary!AC8 -> 0.83552462 | H8: =Summary!AD8 -> 0.098935021
B9: 401K / Pension | C9: =Summary!Y9 -> 247061 | D9: =Summary!Z9 -> 0 | E9: =Summary!AA9 -> 42617 | F9: =Summary!AB9 -> 289678 | G9: =Summary!AC9 -> 0.17249586 | H9: =Summary!AD9 -> 0.17249586
B10: Chase/AMEX | C10: =Summary!Y10 -> 2944.3 | D10: =Summary!Z10 -> 0 | E10: =Summary!AA10 -> 1084.62 | F10: =Summary!AB10 -> 4028.92 | G10: =Summary!AC10 -> 0.36837958 | H10: =Summary!AD10 -> 0.36837958
B11: TOTAL | C11: =Summary!Y11 -> 677754.3 | D11: =Summary!Z11 -> 9100 | E11: =Summary!AA11 -> 58862.62 | F11: =Summary!AB11 -> 745716.92 | G11: =Summary!AC11 -> 0.10027619 | H11: =Summary!AD11 -> 0.085698845
C12: 2025 | D12: Invest | E12: Gain/ (Loss) | F12: FMV | G12: % Increase | H12: % Gained
B13: Etrade | C13: 88708 | D13: 38181 | E13: 79619 | F13: 206508 | G13: =(F13-C13)/C13 -> 1.3279524 | H13: =E13/(C13+D13) -> 0.62746968
B14: BC | C14: 104164 | D14: 14000 | E14: 8945 | F14: 127109 | G14: =(F14-C14)/C14 -> 0.22027764 | H14: =E14/(C14+D14) -> 0.075699875
B15: Roth IRA | C15: 48142 | D15: 7000 | E15: 7813 | F15: 62955 | G15: =(F15-C15)/C15 -> 0.30769391 | H15: =E15/(C15+D15) -> 0.14168873
B16: UTMA | C16: 3014 | D16: 400 | E16: 465 | F16: 3879 | G16: =(F16-C16)/C16 -> 0.28699403 | H16: =E16/(C16+D16) -> 0.13620387
B17: KPMG Pension | C17: 31601 | E17: 1580 | F17: 33181 | G17: =(F17-C17)/C17 -> 0.049998418 | H17: =E17/(C17+D17) -> 0.049998418
B18: 401K / Pension | C18: 191318 | E18: 49860 | F18: 241178 | G18: =(F18-C18)/C18 -> 0.26061322 | H18: =E18/(C18+D18) -> 0.26061322
B19: Chase/AMEX | C19: 1225.01 | E19: 1719.29 | F19: 2944.3 | G19: =(F19-C19)/C19 -> 1.4034906 | H19: =E19/(C19+D19) -> 1.4034906
B20: TOTAL | C20: 468172.01 | D20: 59581 | E20: 150001.29 | F20: 677754.3 | G20: =(F20-C20)/C20 -> 0.44766087 | H20: =E20/(C20+D20) -> 0.28422631
C21: 2024 | D21: Invest | E21: Gain/ (Loss) | F21: FMV | G21: % Increase | H21: % Gained
B22: Etrade | C22: 39026 | D22: 39211.76 | E22: 10471 | F22: 88708.76 | G22: =(F22-C22)/C22 -> 1.2730682 | H22: =E22/(C22+D22) -> 0.13383563
B23: BC | C23: 68968 | D23: 18212 | E23: 16984 | F23: 104164 | G23: =(F23-C23)/C23 -> 0.51032363 | H23: =E23/(C23+D23) -> 0.19481532
B24: Lending Club | C24: 35.5 | E24: -35.5 | F24: 0 | G24: =(F24-C24)/C24 -> -1 | H24: =E24/(C24+D24) -> -1
B25: Roth IRA | C25: 29214 | D25: 10100 | E25: 8828 | F25: 48142 | G25: =(F25-C25)/C25 -> 0.64790854 | H25: =E25/(C25+D25) -> 0.22455105
B26: TSP | C26: 27298 | F26: 27298 | G26: =(F26-C26)/C26 -> 0 | H26: =E26/(C26+D26) -> 0
B27: Card | C27: 5554.14 | E27: -5554.14 | F27: 0 | G27: =(F27-C27)/C27 -> -1 | H27: =E27/(C27+D27) -> -1
B28: UTMA | C28: 0 | D28: 3000 | E28: 14 | F28: 3014 | G28: =(F28-C28)/C28 -> #DIV/0! | H28: =E28/(C28+D28) -> 0.0046666667
B29: 401K / Pension | C29: 173715 | D29: -23895 | E29: 45801 | F29: 195621 | G29: =(F29-C29)/C29 -> 0.1261031 | H29: =E29/(C29+D29) -> 0.30570685
B30: Chase/AMEX | C30: 1119.06 | E30: 105.19 | F30: 1224.25 | G30: =(F30-C30)/C30 -> 0.093998534 | H30: =E30/(C30+D30) -> 0.093998534
B31: TOTAL | C31: 344929.7 | D31: 46628.76 | E31: 76613.55 | F31: 468172.01 | G31: =(F31-C31)/C31 -> 0.35729689 | H31: =E31/(C31+D31) -> 0.19566312
C32: 2023 | D32: Invest | E32: Gain/ (Loss) | F32: FMV | G32: % Increase | H32: % Gained
B33: Etrade | C33: 36511 | D33: 2000 | E33: 515 | F33: 39026 | G33: =(F33-C33)/C33 -> 0.06888335 | H33: =E33/(C33+D33) -> 0.013372803
B34: BC | C34: 65668 | D34: 3300 | F34: 68968 | G34: =(F34-C34)/C34 -> 0.050252787 | H34: =E34/(C34+D34) -> 0
B35: Lending Club | C35: 150.26 | D35: -24.07 | E35: -90.69 | F35: 35.5 | G35: =(F35-C35)/C35 -> -0.76374285 | H35: =E35/(C35+D35) -> -0.71867818
B36: Roth IRA | C36: 23787 | D36: 3600 | E36: 1827 | F36: 29214 | G36: =(F36-C36)/C36 -> 0.22814983 | H36: =E36/(C36+D36) -> 0.066710483
B37: TSP | C37: 27298 | F37: 27298 | G37: =(F37-C37)/C37 -> 0 | H37: =E37/(C37+D37) -> 0
B38: Card | C38: 5554.14 | F38: 5554.14 | G38: =(F38-C38)/C38 -> 0 | H38: =E38/(C38+D38) -> 0
B39: 401K / Pension | C39: 147725 | D39: 3876 | E39: 22114 | F39: 173715 | G39: =(F39-C39)/C39 -> 0.17593501 | H39: =E39/(C39+D39) -> 0.14586975
B40: Chase/AMEX | C40: 1752.18 | E40: -665.76 | F40: 1086.42 | G40: =(F40-C40)/C40 -> -0.37996096 | H40: =E40/(C40+D40) -> -0.37996096
B41: TOTAL | C41: 308445.58 | D41: 12751.93 | E41: 23699.55 | F41: 344897.06 | G41: =(F41-C41)/C41 -> 0.11817799 | H41: =E41/(C41+D41) -> 0.073784974
C42: 2022 | D42: Invest | E42: Gain/ (Loss) | F42: FMV | G42: % Increase | H42: % Gained
B43: Etrade | C43: 36511 | D43: 0 | E43: 0 | F43: =SUM(C43:E43) -> 36511 | G43: =(F43-C43)/C43 -> 0 | H43: =E43/(C43+D43) -> 0
B44: BC | C44: 51621 | D44: 14047 | F44: =SUM(C44:E44) -> 65668 | G44: =(F44-C44)/C44 -> 0.27211794 | H44: =E44/(C44+D44) -> 0
B45: Lending Club | C45: 683 | D45: -532.74 | E45: 0 | F45: =SUM(C45:E45) -> 150.26 | G45: =(F45-C45)/C45 -> -0.78 | H45: =E45/(C45+D45) -> 0
B46: Roth IRA | C46: 20187 | D46: 0 | E46: 3600 | F46: =SUM(C46:E46) -> 23787 | G46: =(F46-C46)/C46 -> 0.17833259 | H46: =E46/(C46+D46) -> 0.17833259
B47: TSP | C47: 27298 | F47: =SUM(C47:E47) -> 27298 | G47: =(F47-C47)/C47 -> 0 | H47: =E47/(C47+D47) -> 0
B48: Card | C48: 5554.14 | F48: =SUM(C48:E48) -> 5554.14 | G48: =(F48-C48)/C48 -> 0 | H48: =E48/(C48+D48) -> 0
B49: 401K / Pension | C49: 109005 | D49: 0 | E49: 38720 | F49: =SUM(C49:E49) -> 147725 | G49: =(F49-C49)/C49 -> 0.35521306 | H49: =E49/(C49+D49) -> 0.35521306
B50: Chase/AMEX | C50: 815.24 | E50: 936.76 | F50: =SUM(C50:E50) -> 1752 | G50: =(F50-C50)/C50 -> 1.1490604 | H50: =E50/(C50+D50) -> 1.1490604
B51: TOTAL | C51: =SUM(C43:C50) -> 251674.38 | D51: =SUM(D43:D50) -> 13514.26 | E51: =SUM(E43:E50) -> 43256.76 | F51: =SUM(F43:F50) -> 308445.4 | G51: =(F51-C51)/C51 -> 0.2255733 | H51: =E51/(C51+D51) -> 0.16311694
C52: 2021 | D52: Invest | E52: Gain/ (Loss) | F52: FMV | G52: % Increase | H52: % Gained
B53: Etrade | C53: 28193.28 | D53: 812 | E53: 7505.72 | F53: =SUM(C53:E53) -> 36511 | G53: =(F53-C53)/C53 -> 0.29502491 | H53: =E53/(C53+D53) -> 0.25877082
B54: BC | C54: 9619.46 | D54: 24499 | E54: 17502.54 | F54: =SUM(C54:E54) -> 51621 | G54: =(F54-C54)/C54 -> 4.3663095 | H54: =E54/(C54+D54) -> 0.51299326
B55: Lending Club | C55: 915 | D55: -235 | E55: 3 | F55: =SUM(C55:E55) -> 683 | G55: =(F55-C55)/C55 -> -0.25355191 | H55: =E55/(C55+D55) -> 0.0044117647
B56: Roth IRA | C56: 12451 | D56: 3500.4 | E56: 4235.6 | F56: =SUM(C56:E56) -> 20187 | G56: =(F56-C56)/C56 -> 0.62131556 | H56: =E56/(C56+D56) -> 0.26553155
B57: TSP | C57: 0 | D57: 27298 | F57: =SUM(C57:E57) -> 27298 | G57: =(F57-C57)/C57 -> #DIV/0! | H57: =E57/(C57+D57) -> 0
B58: Card | C58: 0 | D58: 5554.14 | F58: =SUM(C58:E58) -> 5554.14 | G58: =(F58-C58)/C58 -> #DIV/0! | H58: =E58/(C58+D58) -> 0
B59: 401K / Pension | C59: 83073.67 | D59: 6612 | E59: 19319.93 | F59: =SUM(C59:E59) -> 109005.6 | G59: =(F59-C59)/C59 -> 0.31215583 | H59: =E59/(C59+D59) -> 0.21541825
B60: Chase/AMEX | C60: 1500.65 | E60: -685.41 | F60: =SUM(C60:E60) -> 815.24 | G60: =(F60-C60)/C60 -> -0.45674208 | H60: =E60/(C60+D60) -> -0.45674208
B61: TOTAL | C61: =SUM(C53:C60) -> 135753.06 | D61: =SUM(D53:D60) -> 68040.54 | E61: =SUM(E53:E60) -> 47881.38 | F61: =SUM(F53:F60) -> 251674.98 | G61: =(F61-C61)/C61 -> 0.85391755 | H61: =E61/(C61+D61) -> 0.23495036
C62: 2020 | D62: Invest | E62: Gain/ (Loss) | F62: FMV | G62: % Increase | H62: % Gained
B63: Etrade | C63: 16216.54 | D63: 8773 | E63: 3203.74 | F63: =SUM(C63:E63) -> 28193.28 | G63: =(F63-C63)/C63 -> 0.73855089 | H63: =E63/(C63+D63) -> 0.12820324
B64: BC | C64: 2288.46 | D64: 1100 | E64: 6231 | F64: =SUM(C64:E64) -> 9619.46 | G64: =(F64-C64)/C64 -> 3.2034643 | H64: =E64/(C64+D64) -> 1.8388885
B65: Lending Club | C65: 1421 | D65: -583 | E65: 77 | F65: =SUM(C65:E65) -> 915 | G65: =(F65-C65)/C65 -> -0.35608726 | H65: =E65/(C65+D65) -> 0.091885442
B66: Roth IRA | C66: 8709 | D66: 1950 | E66: 1792 | F66: =SUM(C66:E66) -> 12451 | G66: =(F66-C66)/C66 -> 0.42967046 | H66: =E66/(C66+D66) -> 0.16812084
B67: 401K / Pension | C67: 60554.67 | D67: 6433 | E67: 16086 | F67: =SUM(C67:E67) -> 83073.67 | G67: =(F67-C67)/C67 -> 0.37187883 | H67: =E67/(C67+D67) -> 0.24013374
B68: Chase/AMEX | C68: 2018 | E68: -517.41 | F68: =SUM(C68:E68) -> 1500.59 | G68: =(F68-C68)/C68 -> -0.25639742 | H68: =E68/(C68+D68) -> -0.25639742
B69: TOTAL | C69: =SUM(C63:C68) -> 91207.67 | D69: =SUM(D63:D68) -> 17673 | E69: =SUM(E63:E68) -> 26872.33 | F69: =SUM(F63:F68) -> 135753 | G69: =(F69-C69)/C69 -> 0.48839456 | H69: =E69/(C69+D69) -> 0.24680533
C70: 2019 | D70: Invest | E70: Gain/ (Loss) | F70: FMV | G70: % Increase | H70: % Gained
B71: Etrade | C71: 12070.03 | D71: 1769.54 | E71: 2377 | F71: =SUM(C71:E71) -> 16216.57 | G71: =(F71-C71)/C71 -> 0.34354016 | H71: =E71/(C71+D71) -> 0.17175389
B72: BC | C72: 0 | D72: 4770.46 | E72: -2482 | F72: =SUM(C72:E72) -> 2288.46 | G72: =(F72-C72)/C72 -> #DIV/0! | H72: =E72/(C72+D72) -> -0.52028526
B73: Lending Club | C73: 1799 | D73: -112 | E73: -266 | F73: =SUM(C73:E73) -> 1421 | G73: =(F73-C73)/C73 -> -0.21011673 | H73: =E73/(C73+D73) -> -0.15767635
B74: Roth IRA | C74: 6901 | D74: 312 | E74: 1496 | F74: =SUM(C74:E74) -> 8709 | G74: =(F74-C74)/C74 -> 0.26199102 | H74: =E74/(C74+D74) -> 0.2074033
B75: 401K / Pension | C75: 44223.67 | D75: 6396.74 | E75: 9934.26 | F75: =SUM(C75:E75) -> 60554.67 | G75: =(F75-C75)/C75 -> 0.36928188 | H75: =E75/(C75+D75) -> 0.19625009
B76: Chase/AMEX | C76: 3411.64 | D76: 0 | E76: -1393.58 | F76: =SUM(C76:E76) -> 2018.06 | G76: =(F76-C76)/C76 -> -0.40847803 | H76: =E76/(C76+D76) -> -0.40847803
B77: TOTAL | C77: =SUM(C71:C76) -> 68405.34 | D77: =SUM(D71:D76) -> 13136.74 | E77: =SUM(E71:E76) -> 9665.68 | F77: =SUM(F71:F76) -> 91207.76 | G77: =(F77-C77)/C77 -> 0.33334269 | H77: =E77/(C77+D77) -> 0.1185361
C78: 2018 | D78: Invest | E78: Gain/ (Loss) | F78: FMV | G78: % Increase | H78: % Gained
B79: Etrade | C79: 9683 | D79: 1827 | E79: 560.03 | F79: =SUM(C79:E79) -> 12070.03 | G79: =(F79-C79)/C79 -> 0.24651761 | H79: =E79/(C79+D79) -> 0.048655951
B80: Lending Club | C80: 1622 | D80: 125 | E80: 52 | F80: =SUM(C80:E80) -> 1799 | G80: =(F80-C80)/C80 -> 0.10912454 | H80: =E80/(C80+D80) -> 0.029765312
B81: Roth IRA | C81: 6446 | D81: 75 | E81: 380 | F81: =SUM(C81:E81) -> 6901 | G81: =(F81-C81)/C81 -> 0.07058641 | H81: =E81/(C81+D81) -> 0.058273271
B82: 401K / Pension | C82: 36319.14 | D82: 5220 | E82: 2684.53 | F82: =SUM(C82:E82) -> 44223.67 | G82: =(F82-C82)/C82 -> 0.21764089 | H82: =E82/(C82+D82) -> 0.064626519
B83: Chase/AMEX | C83: 2876.44 | D83: 0 | E83: 535.2 | F83: =SUM(C83:E83) -> 3411.64 | G83: =(F83-C83)/C83 -> 0.18606333 | H83: =E83/(C83+D83) -> 0.18606333
B84: TOTAL | C84: =SUM(C79:C83) -> 56946.58 | D84: =SUM(D79:D83) -> 7247 | E84: =SUM(E79:E83) -> 4211.76 | F84: =SUM(F79:F83) -> 68405.34 | G84: =(F84-C84)/C84 -> 0.20121946 | H84: =E84/(C84+D84) -> 0.065610299
C85: 2017 | D85: Invest | E85: Gain/ (Loss) | F85: FMV | G85: % Increase | H85: % Gained
B86: Etrade | C86: 6430 | D86: 2380 | E86: 873 | F86: =SUM(C86:E86) -> 9683 | G86: =(F86-C86)/C86 -> 0.5059098 | H86: =E86/(C86+D86) -> 0.099091941
B87: Lending Club | C87: 1632 | D87: 0 | E87: -10 | F87: =SUM(C87:E87) -> 1622 | G87: =(F87-C87)/C87 -> -0.006127451 | H87: =E87/(C87+D87) -> -0.006127451
B88: Roth IRA | C88: 4997 | D88: 300 | E88: 1149 | F88: =SUM(C88:E88) -> 6446 | G88: =(F88-C88)/C88 -> 0.28997398 | H88: =E88/(C88+D88) -> 0.21691524
B89: 401K / Pension | C89: 23286.53 | D89: 4474.76 | E89: =8557+1 -> 8558 | F89: =SUM(C89:E89) -> 36319.29 | G89: =(F89-C89)/C89 -> 0.55966947 | H89: =E89/(C89+D89) -> 0.30827098
B90: Chase/AMEX | C90: 2788.27 | D90: 0 | E90: =84.92+3 -> 87.92 | F90: =SUM(C90:E90) -> 2876.19 | G90: =(F90-C90)/C90 -> 0.031532097 | H90: =E90/(C90+D90) -> 0.031532097
B91: TOTAL | C91: =SUM(C86:C90) -> 39133.8 | D91: =SUM(D86:D90) -> 7154.76 | E91: =SUM(E86:E90) -> 10657.92 | F91: =SUM(F86:F90) -> 56946.48 | G91: =(F91-C91)/C91 -> 0.45517379 | H91: =E91/(C91+D91) -> 0.23024955
C92: 2016 | D92: Invest | E92: Gain/ (Loss) | F92: FMV | G92: % Increase | H92: % Gained
B93: Etrade | C93: 6030 | D93: 350 | E93: =4+16+30 -> 50 | F93: =SUM(C93:E93) -> 6430 | G93: =(F93-C93)/C93 -> 0.066334992 | H93: =E93/(C93+D93) -> 0.0078369906
B94: Lending Club | C94: 1601 | D94: 0 | E94: =37-6 -> 31 | F94: =SUM(C94:E94) -> 1632 | G94: =(F94-C94)/C94 -> 0.019362898 | H94: =E94/(C94+D94) -> 0.019362898
B95: Roth IRA | C95: 4176 | D95: 400 | E95: 421 | F95: =SUM(C95:E95) -> 4997 | G95: =(F95-C95)/C95 -> 0.19659962 | H95: =E95/(C95+D95) -> 0.092001748
B96: 401K / Pension | C96: 7806.07 | D96: 3605 | E96: 11875.46 | F96: =SUM(C96:E96) -> 23286.53 | G96: =(F96-C96)/C96 -> 1.9831311 | H96: =E96/(C96+D96) -> 1.0406964
B97: Chase/AMEX | C97: 1807.35 | E97: =948.35+33 -> 981.35 | F97: =SUM(C97:E97) -> 2788.7 | G97: =(F97-C97)/C97 -> 0.54297729 | H97: =E97/(C97+D97) -> 0.54297729
B98: TOTAL | C98: =SUM(C93:C97) -> 21420.42 | D98: =SUM(D93:D97) -> 4355 | E98: =SUM(E93:E97) -> 13358.81 | F98: =SUM(F93:F97) -> 39134.23 | G98: =(F98-C98)/C98 -> 0.82695904 | H98: =E98/(C98+D98) -> 0.5182771

Sheet Summary
B2: 2026 | L2: Savings | X2: Investment*
B3: Month | C3: Net | D3: Budget | E3: Actual | F3: Variance | G3: Change | H3: Investment Earning | J3: Month | K3: Checkings | L3: School | M3: Buy | N3: House | O3: Car | P3: Travel | Q3: Kids | R3: Gifts | S3: Emergency | T3: Savings | U3: Investment* | V3: Total | W3: check | Y3: 2025 | Z3: Invest | AA3: Gain/ (Loss) | AB3: FMV | AC3: % Increase | AD3: % Gained
B4: 46023 | C4: =Jan!W73 -> 1083924.3 | D4: =K42 -> 13325 | E4: =L42 -> -13407 | F4: =D4+E4 -> -82 | G4: =C4-SUM(Jan!D3:W3) -> 32376.96 | H4: =Jan!AE21 -> 21346.6 | J4: =B4 -> 46023 | K4: =Jan!W72 -> 11100 | L4: =Jan!H65 -> 14645.08 | M4: =Jan!I65 -> 55015 | N4: =Jan!J65 -> 152796 | O4: =Jan!K65 -> 67208.71 | P4: =Jan!L65 -> 20985.75 | Q4: =Jan!M65 -> 30000.37 | R4: =Jan!N65 -> 4000 | S4: =Jan!O65 -> 25572.5 | T4: =SUM(L4:S4) -> 370223.41 | U4: =Jan!W71 -> 702600.9 | V4: =K4+T4+U4 -> 1083924.3 | W4: =C4-V4 -> 0 | X4: Etrade | Y4: =Jan!P3 -> 206508 | AA4: =Jan!AE15+Feb!AE15 -> 7081 | AB4: =SUM(Y4:AA4) -> 213589 | AC4: =(AB4-Y4)/Y4 -> 0.034289229 | AD4: =AA4/(Y4+Z4) -> 0.034289229
B5: 46054 | C5: =Feb!W61 -> 1098715.2 | D5: =N42 -> 11985 | E5: =O42 -> -12830.68 | F5: =D5+E5 -> -845.68 | G5: =C5-C4 -> 14790.93 | H5: =Feb!AE21 -> 5861.96 | J5: =B5 -> 46054 | K5: =Feb!W60 -> 11200 | L5: =Feb!H53 -> 14645.08 | M5: =Feb!I53 -> 57040 | N5: =Feb!J53 -> 153796 | O5: =Feb!K53 -> 69712.68 | P5: =Feb!L53 -> 20985.75 | Q5: =Feb!M53 -> 32000.37 | R5: =Feb!N53 -> 4000 | S5: =Feb!O53 -> 26572.5 | T5: =SUM(L5:S5) -> 378752.38 | U5: =Feb!W59 -> 708762.86 | V5: =K5+T5+U5 -> 1098715.2 | W5: =C5-V5 -> 0 | X5: BC | Y5: =Jan!Q3 -> 127109 | Z5: =Jan!AE7+'Apr '!AE7 -> 5000 | AB5: =SUM(Y5:AA5) -> 132109 | AC5: =(AB5-Y5)/Y5 -> 0.039336318 | AD5: =AA5/(Y5+Z5) -> 0
B6: 46082 | C6: =Mar!W77 -> 1081075.1 | D6: =Q42 -> 13555 | E6: =R42 -> -17117.97 | F6: =D6+E6 -> -3562.97 | G6: =C6-C5 -> -17640.12 | H6: =Mar!AE21 -> 474.72 | J6: =B6 -> 46082 | K6: =Mar!W76 -> 11300 | L6: =Mar!H69 -> 14845.08 | M6: =Mar!I69 -> 47065 | N6: =Mar!J69 -> 154796 | O6: =Mar!K69 -> 59712.68 | P6: =Mar!L69 -> 21245.91 | Q6: =Mar!M69 -> 32000.37 | R6: =Mar!N69 -> 4000 | S6: =Mar!O69 -> 26572.5 | T6: =SUM(L6:S6) -> 360237.54 | U6: =Mar!W75 -> 709537.58 | V6: =K6+T6+U6 -> 1081075.1 | W6: =C6-V6 -> 0 | X6: Roth IRA | Y6: =Jan!R3 -> 62955 | Z6: =Jan!AE9+Feb!AE8+Mar!AE8+'Apr '!AE8+'May '!AE8 -> 1500 | AA6: =Jan!AE18+'Apr '!AE17+'May '!AE17 -> 7439 | AB6: =SUM(Y6:AA6) -> 71894 | AC6: =(AB6-Y6)/Y6 -> 0.14199031 | AD6: =AA6/(Y6+Z6) -> 0.11541385
B7: 46113 | C7: ='Apr '!W68 -> 1106484 | D7: =T42 -> 21825 | E7: =U42 -> -25755.07 | F7: =D7+E7 -> -3930.07 | G7: =C7-C6 -> 25408.9 | H7: ='Apr '!AE20 -> 16551.9 | J7: =B7 -> 46113 | K7: ='Apr '!W67 -> 11400 | L7: ='Apr '!H60 -> 7939.08 | M7: ='Apr '!I60 -> 49090 | N7: ='Apr '!J60 -> 152868 | O7: ='Apr '!K60 -> 60578.68 | P7: ='Apr '!L60 -> 24245.91 | Q7: ='Apr '!M60 -> 32000.37 | R7: ='Apr '!N60 -> 4000 | S7: ='Apr '!O60 -> 33572.5 | T7: =SUM(L7:S7) -> 364294.54 | U7: ='Apr '!W66 -> 730789.48 | V7: =K7+T7+U7 -> 1106484 | W7: =C7-V7 -> 0 | X7: TSP | Y7: =Jan!U3 -> 27298 | AB7: =SUM(Y7:AA7) -> 27298 | AC7: =(AB7-Y7)/Y7 -> 0 | AD7: =AA7/(Y7+Z7) -> 0
B8: 46143 | C8: ='May '!W70 -> 1128693.4 | D8: =W42 -> 12855 | E8: =X42 -> -13700.14 | F8: =D8+E8 -> -845.14 | G8: =C8-C7 -> 22209.35 | H8: ='May '!AE21 -> 14627.44 | J8: =B8 -> 46143 | K8: ='May '!W69 -> 11500 | L8: ='May '!H62 -> 8939.08 | M8: ='May '!I62 -> 52071.91 | N8: ='May '!J62 -> 153868 | O8: ='May '!K62 -> 60778.68 | P8: ='May '!L62 -> 26245.91 | Q8: ='May '!M62 -> 32000.37 | R8: ='May '!N62 -> 4000 | S8: ='May '!O62 -> 33572.5 | T8: =SUM(L8:S8) -> 371476.45 | U8: ='May '!W68 -> 745716.92 | V8: =K8+T8+U8 -> 1128693.4 | W8: =C8-V8 -> 0 | X8: Riley (UTMA) | Y8: =Jan!S3 -> 3879 | Z8: =Jan!AE8+'Apr '!AE9 -> 2600 | AA8: =Jan!AE17+'May '!AE18 -> 641 | AB8: =SUM(Y8:AA8) -> 7120 | AC8: =(AB8-Y8)/Y8 -> 0.83552462 | AD8: =AA8/(Y8+Z8) -> 0.098935021
B9: 46174 | C9: ='Jun '!W53 -> 1122652.8 | D9: =Z42 -> 12775 | E9: =AA42 -> -6534.14 | F9: =D9+E9 -> 6240.86 | G9: =C9-C8 -> -6040.62 | H9: ='Jun '!AE18 -> 0 | J9: =B9 -> 46174 | K9: ='Jun '!W52 -> 11600 | L9: ='Jun '!H45 -> 8939.08 | M9: ='Jun '!I45 -> 44931.29 | N9: ='Jun '!J45 -> 154868 | O9: ='Jun '!K45 -> 60778.68 | P9: ='Jun '!L45 -> 26245.91 | Q9: ='Jun '!M45 -> 32000.37 | R9: ='Jun '!N45 -> 4000 | S9: ='Jun '!O45 -> 33572.5 | T9: =SUM(L9:S9) -> 365335.83 | U9: ='Jun '!W51 -> 745716.92 | V9: =K9+T9+U9 -> 1122652.8 | W9: =C9-V9 -> 0 | X9: 401K / Pension | Y9: =Jan!V3+Jan!T3 -> 247061 | AA9: =Jan!AE19+Feb!AE19+'Apr '!AE18+'May '!AE19 -> 42617 | AB9: =SUM(Y9:AA9) -> 289678 | AC9: =(AB9-Y9)/Y9 -> 0.17249586 | AD9: =AA9/(Y9+Z9) -> 0.17249586
B10: 46204 | C10: =Jul!W52 -> 0 | D10: =AC42 -> 14675 | E10: =AD42 -> 0 | F10: =D10+E10 -> 14675 | G10: =C10-C9 -> -1122652.8 | H10: =Jul!AE20 -> 0 | J10: =B10 -> 46204 | K10: =Jul!W51 -> 0 | L10: =Jul!H44 -> 0 | M10: =Jul!I44 -> 0 | N10: =Jul!J44 -> 0 | O10: =Jul!K44 -> 0 | P10: =Jul!L44 -> 0 | Q10: =Jul!M44 -> 0 | R10: =Jul!N44 -> 0 | S10: =Jul!O44 -> 0 | T10: =SUM(L10:S10) -> 0 | U10: =Jul!W50 -> 0 | V10: =K10+T10+U10 -> 0 | W10: =C10-V10 -> 0 | X10: Chase/AMEX | Y10: =Jan!W3 -> 2944.3 | AA10: =Jan!AE20+Feb!AE20+Mar!AE20+'Apr '!AE19+'May '!AE20 -> 1084.62 | AB10: =SUM(Y10:AA10) -> 4028.92 | AC10: =(AB10-Y10)/Y10 -> 0.36837958 | AD10: =AA10/(Y10+Z10) -> 0.36837958
B11: 46235 | C11: =Aug!W45 -> 0 | D11: =AF42 -> 12024.2 | E11: =AG42 -> 0 | F11: =D11+E11 -> 12024.2 | G11: =C11-C10 -> 0 | H11: =Aug!AE22 -> 0 | J11: =B11 -> 46235 | K11: =Aug!W44 -> 0 | L11: =Aug!H37 -> 0 | M11: =Aug!I37 -> 0 | N11: =Aug!J37 -> 0 | O11: =Aug!K37 -> 0 | P11: =Aug!L37 -> 0 | Q11: =Aug!M37 -> 0 | R11: =Aug!N37 -> 0 | S11: =Aug!O37 -> 0 | T11: =SUM(L11:S11) -> 0 | U11: =Aug!W43 -> 0 | V11: =K11+T11+U11 -> 0 | W11: =C11-V11 -> 0 | X11: TOTAL | Y11: =SUM(Y4:Y10) -> 677754.3 | Z11: =SUM(Z4:Z10) -> 9100 | AA11: =SUM(AA4:AA10) -> 58862.62 | AB11: =SUM(AB4:AB10) -> 745716.92 | AC11: =(AB11-Y11)/Y11 -> 0.10027619 | AD11: =AA11/(Y11+Z11) -> 0.085698845
B12: 46266 | C12: =Sep!W55 -> 0 | D12: =AI42 -> 11881.2 | E12: =AJ42 -> 0 | F12: =D12+E12 -> 11881.2 | G12: =C12-C11 -> 0 | H12: =Sep!AE22 -> 0 | J12: =B12 -> 46266 | K12: =Sep!W54 -> 0 | L12: =Sep!H44 -> 0 | M12: =Sep!I44 -> 0 | N12: =Sep!J44 -> 0 | O12: =Sep!K44 -> 0 | P12: =Sep!L44 -> 0 | Q12: =Sep!M44 -> 0 | R12: =Sep!N44 -> 0 | S12: =Sep!O44 -> 0 | T12: =SUM(L12:S12) -> 0 | U12: =Sep!W53 -> 0 | V12: =K12+T12+U12 -> 0 | W12: =C12-V12 -> 0 | AB12: =AB11-U9 -> 0
B13: 46296 | C13: =Oct!W59 -> 0 | D13: =AL42 -> 11381.2 | E13: =AM42 -> 0 | F13: =D13+E13 -> 11381.2 | G13: =C13-C12 -> 0 | H13: =Oct!AE22 -> 0 | J13: =B13 -> 46296 | K13: =Oct!W58 -> 0 | L13: =Oct!H48 -> 0 | M13: =Oct!I48 -> 0 | N13: =Oct!J48 -> 0 | O13: =Oct!K48 -> 0 | P13: =Oct!L48 -> 0 | Q13: =Oct!M48 -> 0 | R13: =Oct!N48 -> 0 | S13: =Oct!O48 -> 0 | T13: =SUM(L13:S13) -> 0 | U13: =Oct!W57 -> 0 | V13: =K13+T13+U13 -> 0 | W13: =C13-V13 -> 0
B14: 46327 | C14: =Nov!W47 -> 0 | D14: =AO42 -> 12031.2 | E14: =AP42 -> 0 | F14: =D14+E14 -> 12031.2 | G14: =C14-C13 -> 0 | H14: =Nov!AE22 -> 0 | J14: =B14 -> 46327 | K14: =Nov!W46 -> 0 | L14: =Nov!H36 -> 0 | M14: =Nov!I36 -> 0 | N14: =Nov!J36 -> 0 | O14: =Nov!K36 -> 0 | P14: =Nov!L36 -> 0 | Q14: =Nov!M36 -> 0 | R14: =Nov!N36 -> 0 | S14: =Nov!O36 -> 0 | T14: =SUM(L14:S14) -> 0 | U14: =Nov!W45 -> 0 | V14: =K14+T14+U14 -> 0 | W14: =C14-V14 -> 0
B15: 46357 | C15: =Dec!W50 -> 0 | D15: =AR42 -> 12631.2 | E15: =AS42 -> 0 | F15: =D15+E15 -> 12631.2 | G15: =C15-C14 -> 0 | H15: =Dec!AE18 -> 0 | J15: =B15 -> 46357 | K15: =Dec!W49 -> 0 | L15: =Dec!H39 -> 0 | M15: =Dec!I39 -> 0 | N15: =Dec!J39 -> 0 | O15: =Dec!K39 -> 0 | P15: =Dec!L39 -> 0 | Q15: =Dec!M39 -> 0 | R15: =Dec!N39 -> 0 | S15: =Dec!O39 -> 0 | T15: =SUM(L15:S15) -> 0 | U15: =Dec!W48 -> 0 | V15: =K15+T15+U15 -> 0 | W15: =C15-V15 -> 0
C16: TOTAL | D16: =SUM(D4:D15) -> 160944 | E16: =SUM(E4:E15) -> -89345 | F16: =SUM(F4:F15) -> 71599 | G16: =SUM(G4:G15) -> -1051547.4 | H16: =SUM(H4:H15) -> 58862.62
F17: Average | G17: =AVERAGE(G4:G15) -> -87628.946 | H17: =AVERAGE(H4:H15) -> 4905.2183
E19: 2026 | J19: 2026 | K19: =B4 -> 46023 | N19: =J5 -> 46054 | Q19: =J6 -> 46082 | T19: =J7 -> 46113 | W19: =J8 -> 46143 | Z19: =J9 -> 46174 | AC19: =J10 -> 46204 | AF19: =J11 -> 46235 | AI19: =J12 -> 46266 | AL19: =J13 -> 46296 | AO19: =J14 -> 46327 | AR19: =J15 -> 46357
D20: Category | E20: Budget | F20: Actual | G20: Variance | H20: % of Total | J20: Category | K20: Budget | L20: Actual | M20: Variance | N20: Budget | O20: Actual | P20: Variance | Q20: Budget | R20: Actual | S20: Variance | T20: Budget | U20: Actual | V20: Variance | W20: Budget | X20: Actual | Y20: Variance | Z20: Budget | AA20: Actual | AB20: Variance | AC20: Budget | AD20: Actual | AE20: Variance | AF20: Budget | AG20: Actual | AH20: Variance | AI20: Budget | AJ20: Actual | AK20: Variance | AL20: Budget | AM20: Actual | AN20: Variance | AO20: Budget | AP20: Actual | AQ20: Variance | AR20: Budget | AS20: Actual | AT20: Variance
D21: Cable | E21: =K21+N21+Q21+T21+W21+Z21+AC21+AF21+AI21+AL21+AO21+AR21 -> 4460 | F21: =L21+O21+R21+U21+X21+AA21+AD21+AG21+AJ21+AM21+AP21+AS21 -> -1782.99 | G21: =E21+F21 -> 2677.01 | H21: =ABS(F21)/E21 -> 0.39977354 | J21: Cable | K21: 350 | L21: =Jan!AA4 -> -326 | M21: =K21+L21 -> 24 | N21: 480 | O21: =Feb!AA4 -> -271 | P21: =N21+O21 -> 209 | Q21: 480 | R21: =Mar!AA4 -> -452 | S21: =Q21+R21 -> 28 | T21: 350 | U21: ='Apr '!AA4 -> -277 | V21: =T21+U21 -> 73 | W21: 350 | X21: ='May '!AA4 -> -381.99 | Y21: =W21+X21 -> -31.99 | Z21: 350 | AA21: ='Jun '!AA4 -> -75 | AB21: =Z21+AA21 -> 275 | AC21: 350 | AD21: =Jul!AA4 -> 0 | AE21: =AC21+AD21 -> 350 | AF21: 350 | AG21: =Aug!AA4 -> 0 | AH21: =AF21+AG21 -> 350 | AI21: 350 | AJ21: =Sep!AA4 -> 0 | AK21: =AI21+AJ21 -> 350 | AL21: 350 | AM21: =Oct!AA4 -> 0 | AN21: =AL21+AM21 -> 350 | AO21: 350 | AP21: =Nov!AA4 -> 0 | AQ21: =AO21+AP21 -> 350 | AR21: 350 | AS21: =Dec!AA5 -> 0 | AT21: =AR21+AS21 -> 350
D22: Car Insurance | E22: =K22+N22+Q22+T22+W22+Z22+AC22+AF22+AI22+AL22+AO22+AR22 -> 4020 | F22: =L22+O22+R22+U22+X22+AA22+AD22+AG22+AJ22+AM22+AP22+AS22 -> -1726.67 | G22: =E22+F22 -> 2293.33 | H22: =ABS(F22)/E22 -> 0.4295199 | J22: Car Insurance | K22: 335 | L22: =Jan!AA5 -> -342 | M22: =K22+L22 -> -7 | N22: 335 | O22: =Feb!AA5 -> -342 | P22: =N22+O22 -> -7 | Q22: 335 | R22: =Mar!AA5 -> -342 | S22: =Q22+R22 -> -7 | T22: 335 | U22: ='Apr '!AA5 -> -342 | V22: =T22+U22 -> -7 | W22: 335 | X22: ='May '!AA5 -> -358.67 | Y22: =W22+X22 -> -23.67 | Z22: 335 | AA22: ='Jun '!AA5 -> 0 | AB22: =Z22+AA22 -> 335 | AC22: 335 | AD22: =Jul!AA5 -> 0 | AE22: =AC22+AD22 -> 335 | AF22: 335 | AG22: =Aug!AA5 -> 0 | AH22: =AF22+AG22 -> 335 | AI22: 335 | AJ22: =Sep!AA5 -> 0 | AK22: =AI22+AJ22 -> 335 | AL22: 335 | AM22: =Oct!AA5 -> 0 | AN22: =AL22+AM22 -> 335 | AO22: 335 | AP22: =Nov!AA5 -> 0 | AQ22: =AO22+AP22 -> 335 | AR22: 335 | AS22: =Dec!AA6 -> 0 | AT22: =AR22+AS22 -> 335
D23: Cleaners | E23: =K23+N23+Q23+T23+W23+Z23+AC23+AF23+AI23+AL23+AO23+AR23 -> 160 | F23: =L23+O23+R23+U23+X23+AA23+AD23+AG23+AJ23+AM23+AP23+AS23 -> 0 | G23: =E23+F23 -> 160 | H23: =ABS(F23)/E23 -> 0 | J23: Cleaners | K23: 20 | L23: =Jan!AA6 -> 0 | M23: =K23+L23 -> 20 | N23: 20 | O23: =Feb!AA6 -> 0 | P23: =N23+O23 -> 20 | Q23: 20 | R23: =Mar!AA6 -> 0 | S23: =Q23+R23 -> 20 | T23: 20 | U23: ='Apr '!AA6 -> 0 | V23: =T23+U23 -> 20 | W23: 20 | X23: ='May '!AA6 -> 0 | Y23: =W23+X23 -> 20 | Z23: 20 | AA23: ='Jun '!AA6 -> 0 | AB23: =Z23+AA23 -> 20 | AC23: 20 | AD23: =Jul!AA6 -> 0 | AE23: =AC23+AD23 -> 20 | AF23: 20 | AG23: =Aug!AA6 -> 0 | AH23: =AF23+AG23 -> 20 | AI23: 0 | AJ23: =Sep!AA6 -> 0 | AK23: =AI23+AJ23 -> 0 | AL23: 0 | AM23: =Oct!AA6 -> 0 | AN23: =AL23+AM23 -> 0 | AO23: 0 | AP23: =Nov!AA6 -> 0 | AQ23: =AO23+AP23 -> 0 | AR23: 0 | AS23: =Dec!AA7 -> 0 | AT23: =AR23+AS23 -> 0
D24: Clothes | E24: =K24+N24+Q24+T24+W24+Z24+AC24+AF24+AI24+AL24+AO24+AR24 -> 1080 | F24: =L24+O24+R24+U24+X24+AA24+AD24+AG24+AJ24+AM24+AP24+AS24 -> -1827.19 | G24: =E24+F24 -> -747.19 | H24: =ABS(F24)/E24 -> 1.6918426 | J24: Clothes | K24: 300 | L24: =Jan!AA7 -> -353 | M24: =K24+L24 -> -53 | N24: 300 | O24: =Feb!AA7 -> -150 | P24: =N24+O24 -> 150 | Q24: 20 | R24: =Mar!AA7 -> -450 | S24: =Q24+R24 -> -430 | T24: 20 | U24: ='Apr '!AA7 -> -539 | V24: =T24+U24 -> -519 | W24: 300 | X24: ='May '!AA7 -> -262 | Y24: =W24+X24 -> 38 | Z24: 20 | AA24: ='Jun '!AA7 -> -73.19 | AB24: =Z24+AA24 -> -53.19 | AC24: 20 | AD24: =Jul!AA7 -> 0 | AE24: =AC24+AD24 -> 20 | AF24: 20 | AG24: =Aug!AA7 -> 0 | AH24: =AF24+AG24 -> 20 | AI24: 20 | AJ24: =Sep!AA7 -> 0 | AK24: =AI24+AJ24 -> 20 | AL24: 20 | AM24: =Oct!AA7 -> 0 | AN24: =AL24+AM24 -> 20 | AO24: 20 | AP24: =Nov!AA7 -> 0 | AQ24: =AO24+AP24 -> 20 | AR24: 20 | AS24: =Dec!AA8 -> 0 | AT24: =AR24+AS24 -> 20
D25: Utilities | E25: =K25+N25+Q25+T25+W25+Z25+AC25+AF25+AI25+AL25+AO25+AR25 -> 8400 | F25: =L25+O25+R25+U25+X25+AA25+AD25+AG25+AJ25+AM25+AP25+AS25 -> -3543.06 | G25: =E25+F25 -> 4856.94 | H25: =ABS(F25)/E25 -> 0.42179286 | J25: Utilities | K25: 700 | L25: =Jan!AA8 -> -492 | M25: =K25+L25 -> 208 | N25: 700 | O25: =Feb!AA8 -> -687.74 | P25: =N25+O25 -> 12.26 | Q25: 700 | R25: =Mar!AA8 -> -694.97 | S25: =Q25+R25 -> 5.03 | T25: 700 | U25: ='Apr '!AA8 -> -751.29 | V25: =T25+U25 -> -51.29 | W25: 700 | X25: ='May '!AA8 -> -642.06 | Y25: =W25+X25 -> 57.94 | Z25: 700 | AA25: ='Jun '!AA8 -> -275 | AB25: =Z25+AA25 -> 425 | AC25: 700 | AD25: =Jul!AA8 -> 0 | AE25: 650 | AF25: 700 | AG25: =Aug!AA8 -> 0 | AH25: =AF25+AG25 -> 700 | AI25: 700 | AJ25: =Sep!AA8 -> 0 | AK25: =AI25+AJ25 -> 700 | AL25: 700 | AM25: =Oct!AA8 -> 0 | AN25: =AL25+AM25 -> 700 | AO25: 700 | AP25: =Nov!AA8 -> 0 | AQ25: =AO25+AP25 -> 700 | AR25: 700 | AS25: =Dec!AA9 -> 0 | AT25: =AR25+AS25 -> 700
D26: Dining | E26: =K26+N26+Q26+T26+W26+Z26+AC26+AF26+AI26+AL26+AO26+AR26 -> 15600 | F26: =L26+O26+R26+U26+X26+AA26+AD26+AG26+AJ26+AM26+AP26+AS26 -> -8682.83 | G26: =E26+F26 -> 6917.17 | H26: =ABS(F26)/E26 -> 0.55659167 | J26: Dining | K26: 1300 | L26: =Jan!AA9 -> -1652 | M26: =K26+L26 -> -352 | N26: 1300 | O26: =Feb!AA9 -> -1495 | P26: =N26+O26 -> -195 | Q26: 1300 | R26: =Mar!AA9 -> -1959 | S26: =Q26+R26 -> -659 | T26: 1300 | U26: ='Apr '!AA9 -> -1631.13 | V26: =T26+U26 -> -331.13 | W26: 1300 | X26: ='May '!AA9 -> -1470.7 | Y26: =W26+X26 -> -170.7 | Z26: 1300 | AA26: ='Jun '!AA9 -> -475 | AB26: =Z26+AA26 -> 825 | AC26: 1300 | AD26: =Jul!AA9 -> 0 | AE26: =AC26+AD26 -> 1300 | AF26: 1300 | AG26: =Aug!AA9 -> 0 | AH26: =AF26+AG26 -> 1300 | AI26: 1300 | AJ26: =Sep!AA9 -> 0 | AK26: =AI26+AJ26 -> 1300 | AL26: 1300 | AM26: =Oct!AA9 -> 0 | AN26: =AL26+AM26 -> 1300 | AO26: 1300 | AP26: =Nov!AA9 -> 0 | AQ26: =AO26+AP26 -> 1300 | AR26: 1300 | AS26: =Dec!AA10 -> 0 | AT26: =AR26+AS26 -> 1300
D27: Entertainment | E27: =K27+N27+Q27+T27+W27+Z27+AC27+AF27+AI27+AL27+AO27+AR27 -> 1800 | F27: =L27+O27+R27+U27+X27+AA27+AD27+AG27+AJ27+AM27+AP27+AS27 -> -2548.38 | G27: =E27+F27 -> -748.38 | H27: =ABS(F27)/E27 -> 1.4157667 | J27: Entertainment | K27: 150 | L27: =Jan!AA10 -> -733 | M27: =K27+L27 -> -583 | N27: 150 | O27: =Feb!AA10 -> -435 | P27: =N27+O27 -> -285 | Q27: 150 | R27: =Mar!AA10 -> -853 | S27: =Q27+R27 -> -703 | T27: 150 | U27: ='Apr '!AA10 -> -347.38 | V27: =T27+U27 -> -197.38 | W27: 150 | X27: ='May '!AA10 -> -180 | Y27: =W27+X27 -> -30 | Z27: 150 | AA27: ='Jun '!AA10 -> 0 | AB27: =Z27+AA27 -> 150 | AC27: 150 | AD27: =Jul!AA10 -> 0 | AE27: =AC27+AD27 -> 150 | AF27: 150 | AG27: =Aug!AA10 -> 0 | AH27: =AF27+AG27 -> 150 | AI27: 150 | AJ27: =Sep!AA10 -> 0 | AK27: =AI27+AJ27 -> 150 | AL27: 150 | AM27: =Oct!AA10 -> 0 | AN27: =AL27+AM27 -> 150 | AO27: 150 | AP27: =Nov!AA10 -> 0 | AQ27: =AO27+AP27 -> 150 | AR27: 150 | AS27: =Dec!AA11 -> 0 | AT27: =AR27+AS27 -> 150
D28: Gas | E28: =K28+N28+Q28+T28+W28+Z28+AC28+AF28+AI28+AL28+AO28+AR28 -> 2400 | F28: =L28+O28+R28+U28+X28+AA28+AD28+AG28+AJ28+AM28+AP28+AS28 -> -1491.94 | G28: =E28+F28 -> 908.06 | H28: =ABS(F28)/E28 -> 0.62164167 | J28: Gas | K28: 200 | L28: =Jan!AA11 -> -160 | M28: =K28+L28 -> 40 | N28: 200 | O28: =Feb!AA11 -> -197.94 | P28: =N28+O28 -> 2.06 | Q28: 200 | R28: =Mar!AA11 -> -247 | S28: =Q28+R28 -> -47 | T28: 200 | U28: ='Apr '!AA11 -> -293 | V28: =T28+U28 -> -93 | W28: 200 | X28: ='May '!AA11 -> -481 | Y28: =W28+X28 -> -281 | Z28: 200 | AA28: ='Jun '!AA11 -> -113 | AB28: =Z28+AA28 -> 87 | AC28: 200 | AD28: =Jul!AA11 -> 0 | AE28: =AC28+AD28 -> 200 | AF28: 200 | AG28: =Aug!AA11 -> 0 | AH28: =AF28+AG28 -> 200 | AI28: 200 | AJ28: =Sep!AA11 -> 0 | AK28: =AI28+AJ28 -> 200 | AL28: 200 | AM28: =Oct!AA11 -> 0 | AN28: =AL28+AM28 -> 200 | AO28: 200 | AP28: =Nov!AA11 -> 0 | AQ28: =AO28+AP28 -> 200 | AR28: 200 | AS28: =Dec!AA12 -> 0 | AT28: =AR28+AS28 -> 200
D29: Gifts | E29: =K29+N29+Q29+T29+W29+Z29+AC29+AF29+AI29+AL29+AO29+AR29 -> 3650 | F29: =L29+O29+R29+U29+X29+AA29+AD29+AG29+AJ29+AM29+AP29+AS29 -> -2699.84 | G29: =E29+F29 -> 950.16 | H29: =ABS(F29)/E29 -> 0.73968219 | J29: Gifts | K29: 200 | L29: =Jan!AA12 -> -275 | M29: =K29+L29 -> -75 | N29: 200 | O29: =Feb!AA12 -> -423 | P29: =N29+O29 -> -223 | Q29: 200 | R29: =Mar!AA12 -> -915 | S29: =Q29+R29 -> -715 | T29: 200 | U29: ='Apr '!AA12 -> -496 | V29: =T29+U29 -> -296 | W29: 500 | X29: ='May '!AA12 -> -590.84 | Y29: =W29+X29 -> -90.84 | Z29: 500 | AA29: ='Jun '!AA12 -> 0 | AB29: =Z29+AA29 -> 500 | AC29: 200 | AD29: =Jul!AA12 -> 0 | AE29: =AC29+AD29 -> 200 | AF29: 50 | AG29: =Aug!AA12 -> 0 | AH29: =AF29+AG29 -> 50 | AI29: 50 | AJ29: =Sep!AA12 -> 0 | AK29: =AI29+AJ29 -> 50 | AL29: 50 | AM29: =Oct!AA12 -> 0 | AN29: =AL29+AM29 -> 50 | AO29: 500 | AP29: =Nov!AA12 -> 0 | AQ29: =AO29+AP29 -> 500 | AR29: 1000 | AS29: =Dec!AA13 -> 0 | AT29: =AR29+AS29 -> 1000
D30: Grocery | E30: =K30+N30+Q30+T30+W30+Z30+AC30+AF30+AI30+AL30+AO30+AR30 -> 12000 | F30: =L30+O30+R30+U30+X30+AA30+AD30+AG30+AJ30+AM30+AP30+AS30 -> -4870.26 | G30: =E30+F30 -> 7129.74 | H30: =ABS(F30)/E30 -> 0.405855 | J30: Grocery | K30: 1000 | L30: =Jan!AA13 -> -1314 | M30: =K30+L30 -> -314 | N30: 1000 | O30: =Feb!AA13 -> -777 | P30: =N30+O30 -> 223 | Q30: 1000 | R30: =Mar!AA13 -> -700 | S30: =Q30+R30 -> 300 | T30: 1000 | U30: ='Apr '!AA13 -> -630 | V30: =T30+U30 -> 370 | W30: 1000 | X30: ='May '!AA13 -> -1171.31 | Y30: =W30+X30 -> -171.31 | Z30: 1000 | AA30: ='Jun '!AA13 -> -277.95 | AB30: =Z30+AA30 -> 722.05 | AC30: 1000 | AD30: =Jul!AA13 -> 0 | AE30: =AC30+AD30 -> 1000 | AF30: 1000 | AG30: =Aug!AA13 -> 0 | AH30: =AF30+AG30 -> 1000 | AI30: 1000 | AJ30: =Sep!AA13 -> 0 | AK30: =AI30+AJ30 -> 1000 | AL30: 1000 | AM30: =Oct!AA13 -> 0 | AN30: =AL30+AM30 -> 1000 | AO30: 1000 | AP30: =Nov!AA13 -> 0 | AQ30: =AO30+AP30 -> 1000 | AR30: 1000 | AS30: =Dec!AA14 -> 0 | AT30: =AR30+AS30 -> 1000
D31: Gym | E31: =K31+N31+Q31+T31+W31+Z31+AC31+AF31+AI31+AL31+AO31+AR31 -> 2000 | F31: =L31+O31+R31+U31+X31+AA31+AD31+AG31+AJ31+AM31+AP31+AS31 -> -359 | G31: =E31+F31 -> 1641 | H31: =ABS(F31)/E31 -> 0.1795 | J31: Gym | K31: 100 | L31: =Jan!AA14 -> 0 | M31: =K31+L31 -> 100 | N31: 100 | O31: =Feb!AA14 -> 0 | P31: =N31+O31 -> 100 | Q31: 100 | R31: =Mar!AA14 -> 0 | S31: =Q31+R31 -> 100 | T31: 100 | U31: ='Apr '!AA14 -> -100 | V31: =T31+U31 -> 0 | W31: 200 | X31: ='May '!AA14 -> -259 | Y31: =W31+X31 -> -59 | Z31: 200 | AA31: ='Jun '!AA14 -> 0 | AB31: =Z31+AA31 -> 200 | AC31: 200 | AD31: =Jul!AA14 -> 0 | AE31: =AC31+AD31 -> 200 | AF31: 200 | AG31: =Aug!AA14 -> 0 | AH31: =AF31+AG31 -> 200 | AI31: 200 | AJ31: =Sep!AA14 -> 0 | AK31: =AI31+AJ31 -> 200 | AL31: 200 | AM31: =Oct!AA14 -> 0 | AN31: =AL31+AM31 -> 200 | AO31: 200 | AP31: =Nov!AA14 -> 0 | AQ31: =AO31+AP31 -> 200 | AR31: 200 | AS31: =Dec!AA15 -> 0 | AT31: =AR31+AS31 -> 200
D32: Loan | E32: =K32+N32+Q32+T32+W32+Z32+AC32+AF32+AI32+AL32+AO32+AR32 -> 0 | F32: =L32+O32+R32+U32+X32+AA32+AD32+AG32+AJ32+AM32+AP32+AS32 -> 0 | G32: =E32+F32 -> 0 | H32: 0 | J32: Loan | K32: 0 | L32: =Jan!AA15 -> 0 | M32: =K32+L32 -> 0 | N32: 0 | O32: =Feb!AA15 -> 0 | P32: =N32+O32 -> 0 | Q32: 0 | R32: =Mar!AA15 -> 0 | S32: =Q32+R32 -> 0 | T32: 0 | U32: ='Apr '!AA15 -> 0 | V32: =T32+U32 -> 0 | W32: 0 | X32: ='May '!AA15 -> 0 | Y32: =W32+X32 -> 0 | Z32: 0 | AA32: ='Jun '!AA15 -> 0 | AB32: =Z32+AA32 -> 0 | AC32: 0 | AD32: =Jul!AA15 -> 0 | AE32: =AC32+AD32 -> 0 | AF32: 0 | AG32: =Aug!AA15 -> 0 | AH32: =AF32+AG32 -> 0 | AI32: 0 | AJ32: =Sep!AA15 -> 0 | AK32: =AI32+AJ32 -> 0 | AL32: 0 | AM32: =Oct!AA15 -> 0 | AN32: =AL32+AM32 -> 0 | AO32: 0 | AP32: =Nov!AA15 -> 0 | AQ32: =AO32+AP32 -> 0 | AR32: 0 | AS32: =Dec!AA16 -> 0 | AT32: =AR32+AS32 -> 0
D33: Misc | E33: =K33+N33+Q33+T33+W33+Z33+AC33+AF33+AI33+AL33+AO33+AR33 -> 7600 | F33: =L33+O33+R33+U33+X33+AA33+AD33+AG33+AJ33+AM33+AP33+AS33 -> -2080 | G33: =E33+F33 -> 5520 | H33: =ABS(F33)/E33 -> 0.27368421 | J33: Misc | K33: 2000 | L33: =Jan!AA16 -> -287 | M33: =K33+L33 -> 1713 | N33: 500 | O33: =Feb!AA16 -> -300 | P33: =N33+O33 -> 200 | Q33: 500 | R33: =Mar!AA16 -> -457 | S33: =Q33+R33 -> 43 | T33: 500 | U33: ='Apr '!AA16 -> -906 | V33: =T33+U33 -> -406 | W33: 500 | X33: ='May '!AA16 -> -50 | Y33: =W33+X33 -> 450 | Z33: 500 | AA33: ='Jun '!AA16 -> -80 | AB33: =Z33+AA33 -> 420 | AC33: 500 | AD33: =Jul!AA16 -> 0 | AE33: =AC33+AD33 -> 500 | AF33: 500 | AG33: =Aug!AA16 -> 0 | AH33: =AF33+AG33 -> 500 | AI33: 500 | AJ33: =Sep!AA16 -> 0 | AK33: =AI33+AJ33 -> 500 | AL33: 500 | AM33: =Oct!AA16 -> 0 | AN33: =AL33+AM33 -> 500 | AO33: 500 | AP33: =Nov!AA16 -> 0 | AQ33: =AO33+AP33 -> 500 | AR33: 600 | AS33: =Dec!AA17 -> 0 | AT33: =AR33+AS33 -> 600
D34: Offering | E34: =K34+N34+Q34+T34+W34+Z34+AC34+AF34+AI34+AL34+AO34+AR34 -> 9600 | F34: =L34+O34+R34+U34+X34+AA34+AD34+AG34+AJ34+AM34+AP34+AS34 -> -4955.54 | G34: =E34+F34 -> 4644.46 | H34: =ABS(F34)/E34 -> 0.51620208 | J34: Offering | K34: 800 | L34: =Jan!AA17 -> -1264 | M34: =K34+L34 -> -464 | N34: 800 | O34: =Feb!AA17 -> -499 | P34: =N34+O34 -> 301 | Q34: 800 | R34: =Mar!AA17 -> -917 | S34: =Q34+R34 -> -117 | T34: 800 | U34: ='Apr '!AA17 -> -910.27 | V34: =T34+U34 -> -110.27 | W34: 800 | X34: ='May '!AA17 -> -909.27 | Y34: =W34+X34 -> -109.27 | Z34: 800 | AA34: ='Jun '!AA17 -> -456 | AB34: =Z34+AA34 -> 344 | AC34: 800 | AD34: =Jul!AA17 -> 0 | AE34: =AC34+AD34 -> 800 | AF34: 800 | AG34: =Aug!AA17 -> 0 | AH34: =AF34+AG34 -> 800 | AI34: 800 | AJ34: =Sep!AA17 -> 0 | AK34: =AI34+AJ34 -> 800 | AL34: 800 | AM34: =Oct!AA17 -> 0 | AN34: =AL34+AM34 -> 800 | AO34: 800 | AP34: =Nov!AA17 -> 0 | AQ34: =AO34+AP34 -> 800 | AR34: 800 | AS34: =Dec!AA18 -> 0 | AT34: =AR34+AS34 -> 800
D35: Rent | E35: =K35+N35+Q35+T35+W35+Z35+AC35+AF35+AI35+AL35+AO35+AR35 -> 49200 | F35: =L35+O35+R35+U35+X35+AA35+AD35+AG35+AJ35+AM35+AP35+AS35 -> -25304 | G35: =E35+F35 -> 23896 | H35: =ABS(F35)/E35 -> 0.51430894 | J35: Rent | K35: 4100 | L35: =Jan!AA18 -> -4134 | M35: =K35+L35 -> -34 | N35: 4100 | O35: =Feb!AA18 -> -4138 | P35: =N35+O35 -> -38 | Q35: 4100 | R35: =Mar!AA18 -> -4138 | S35: =Q35+R35 -> -38 | T35: 4100 | U35: ='Apr '!AA18 -> -4618 | V35: =T35+U35 -> -518 | W35: 4100 | X35: ='May '!AA18 -> -4138 | Y35: =W35+X35 -> -38 | Z35: 4100 | AA35: ='Jun '!AA18 -> -4138 | AB35: =Z35+AA35 -> -38 | AC35: 4100 | AD35: =Jul!AA18 -> 0 | AE35: =AC35+AD35 -> 4100 | AF35: 4100 | AG35: =Aug!AA18 -> 0 | AH35: =AF35+AG35 -> 4100 | AI35: 4100 | AJ35: =Sep!AA18 -> 0 | AK35: =AI35+AJ35 -> 4100 | AL35: 4100 | AM35: =Oct!AA18 -> 0 | AN35: =AL35+AM35 -> 4100 | AO35: 4100 | AP35: =Nov!AA18 -> 0 | AQ35: =AO35+AP35 -> 4100 | AR35: 4100 | AS35: =Dec!AA19 -> 0 | AT35: =AR35+AS35 -> 4100
D36: Travel | E36: =K36+N36+Q36+T36+W36+Z36+AC36+AF36+AI36+AL36+AO36+AR36 -> 5831 | F36: =L36+O36+R36+U36+X36+AA36+AD36+AG36+AJ36+AM36+AP36+AS36 -> -5677 | G36: =E36+F36 -> 154 | H36: =ABS(F36)/E36 -> 0.97358944 | J36: Travel | K36: 150 | L36: =Jan!AA19 -> 0 | M36: =K36+L36 -> 150 | N36: 0 | O36: =Feb!AA19 -> -1318 | P36: =N36+O36 -> -1318 | Q36: 1800 | R36: =Mar!AA19 -> -2709 | S36: =Q36+R36 -> -909 | T36: 0 | U36: ='Apr '!AA19 -> -1508 | V36: =T36+U36 -> -1508 | W36: 500 | X36: ='May '!AA19 -> -142 | Y36: =W36+X36 -> 358 | Z36: 500 | AA36: ='Jun '!AA19 -> 0 | AB36: =Z36+AA36 -> 500 | AC36: 2000 | AD36: =Jul!AA19 -> 0 | AE36: =AC36+AD36 -> 2000 | AF36: 176.2 | AG36: =Aug!AA19 -> 0 | AH36: =AF36+AG36 -> 176.2 | AI36: 176.2 | AJ36: =Sep!AA19 -> 0 | AK36: =AI36+AJ36 -> 176.2 | AL36: 176.2 | AM36: =Oct!AA19 -> 0 | AN36: =AL36+AM36 -> 176.2 | AO36: 176.2 | AP36: =Nov!AA19 -> 0 | AQ36: =AO36+AP36 -> 176.2 | AR36: 176.2 | AS36: =Dec!AA20 -> 0 | AT36: =AR36+AS36 -> 176.2
D37: Parents | E37: =K37+N37+Q37+T37+W37+Z37+AC37+AF37+AI37+AL37+AO37+AR37 -> 5700 | F37: =L37+O37+R37+U37+X37+AA37+AD37+AG37+AJ37+AM37+AP37+AS37 -> -3045 | G37: =E37+F37 -> 2655 | H37: =ABS(F37)/E37 -> 0.53421053 | J37: Parents | K37: 200 | L37: =Jan!AA20 -> -200 | M37: =K37+L37 -> 0 | N37: 500 | O37: =Feb!AA20 -> -500 | P37: =N37+O37 -> 0 | Q37: 500 | R37: =Mar!AA20 -> -500 | S37: =Q37+R37 -> 0 | T37: 500 | U37: ='Apr '!AA20 -> -500 | V37: =T37+U37 -> 0 | W37: 500 | X37: ='May '!AA20 -> -845 | Y37: =W37+X37 -> -345 | Z37: 500 | AA37: ='Jun '!AA20 -> -500 | AB37: =Z37+AA37 -> 0 | AC37: 500 | AD37: =Jul!AA20 -> 0 | AE37: =AC37+AD37 -> 500 | AF37: 500 | AG37: =Aug!AA20 -> 0 | AH37: =AF37+AG37 -> 500 | AI37: 500 | AJ37: =Sep!AA20 -> 0 | AK37: =AI37+AJ37 -> 500 | AL37: 500 | AM37: =Oct!AA20 -> 0 | AN37: =AL37+AM37 -> 500 | AO37: 500 | AP37: =Nov!AA20 -> 0 | AQ37: =AO37+AP37 -> 500 | AR37: 500 | AS37: =Dec!AA21 -> 0 | AT37: =AR37+AS37 -> 500
D38: Car | E38: =K38+N38+Q38+T38+W38+Z38+AC38+AF38+AI38+AL38+AO38+AR38 -> 3323 | F38: =L38+O38+R38+U38+X38+AA38+AD38+AG38+AJ38+AM38+AP38+AS38 -> -830 | G38: =E38+F38 -> 2493 | H38: =ABS(F38)/E38 -> 0.2497743 | J38: Car | K38: 200 | L38: =Jan!AA21 -> 0 | M38: =K38+L38 -> 200 | N38: 200 | O38: =Feb!AA21 -> 0 | P38: =N38+O38 -> 200 | Q38: 250 | R38: =Mar!AA21 -> 0 | S38: =Q38+R38 -> 250 | T38: 250 | U38: ='Apr '!AA21 -> -830 | V38: =T38+U38 -> -580 | W38: 0 | X38: ='May '!AA21 -> 0 | Y38: =W38+X38 -> 0 | Z38: 500 | AA38: ='Jun '!AA21 -> 0 | AB38: =Z38+AA38 -> 500 | AC38: 500 | AD38: =Jul!AA21 -> 0 | AE38: =AC38+AD38 -> 500 | AF38: 523 | AG38: =Aug!AA21 -> 0 | AH38: =AF38+AG38 -> 523 | AI38: 500 | AJ38: =Sep!AA21 -> 0 | AK38: =AI38+AJ38 -> 500 | AL38: 0 | AM38: =Oct!AA21 -> 0 | AN38: =AL38+AM38 -> 0 | AO38: 200 | AP38: =Nov!AA21 -> 0 | AQ38: =AO38+AP38 -> 200 | AR38: 200 | AS38: =Dec!AA22 -> 0 | AT38: =AR38+AS38 -> 200
D39: House | E39: =K39+N39+Q39+T39+W39+Z39+AC39+AF39+AI39+AL39+AO39+AR39 -> 3700 | F39: =L39+O39+R39+U39+X39+AA39+AD39+AG39+AJ39+AM39+AP39+AS39 -> -1439.3 | G39: =E39+F39 -> 2260.7 | H39: =ABS(F39)/E39 -> 0.389 | J39: House | K39: 200 | L39: =Jan!AA22 -> -425 | M39: =K39+L39 -> -225 | N39: 200 | O39: =Feb!AA22 -> -157 | P39: =N39+O39 -> 43 | Q39: 200 | R39: =Mar!AA22 -> -24 | S39: =Q39+R39 -> 176 | T39: 400 | U39: ='Apr '!AA22 -> -290 | V39: =T39+U39 -> 110 | W39: 500 | X39: ='May '!AA22 -> -508.3 | Y39: =W39+X39 -> -8.3 | Z39: 200 | AA39: ='Jun '!AA22 -> -35 | AB39: =Z39+AA39 -> 165 | AC39: 1000 | AD39: =Jul!AA22 -> 0 | AE39: =AC39+AD39 -> 1000 | AF39: 200 | AG39: =Aug!AA22 -> 0 | AH39: =AF39+AG39 -> 200 | AI39: 200 | AJ39: =Sep!AA22 -> 0 | AK39: =AI39+AJ39 -> 200 | AL39: 200 | AM39: =Oct!AA22 -> 0 | AN39: =AL39+AM39 -> 200 | AO39: 200 | AP39: =Nov!AA22 -> 0 | AQ39: =AO39+AP39 -> 200 | AR39: 200 | AS39: =Dec!AA23 -> 0 | AT39: =AR39+AS39 -> 200
D40: School | E40: =K40+N40+Q40+T40+W40+Z40+AC40+AF40+AI40+AL40+AO40+AR40 -> 10120 | F40: =L40+O40+R40+U40+X40+AA40+AD40+AG40+AJ40+AM40+AP40+AS40 -> -11681 | G40: =E40+F40 -> -1561 | H40: =ABS(F40)/E40 -> 1.154249 | J40: School | K40: 120 | L40: =Jan!AA23 -> -570 | M40: =K40+L40 -> -450 | N40: 0 | O40: =Feb!AA23 -> -260 | P40: =N40+O40 -> -260 | Q40: 0 | R40: =Mar!AA24 -> -880 | S40: =Q40+R40 -> -880 | T40: 10000 | U40: ='Apr '!AA23 -> -9906 | V40: =T40+U40 -> 94 | W40: 0 | X40: ='May '!AA23 -> -65 | Y40: =W40+X40 -> -65 | Z40: 0 | AA40: ='Jun '!AA23 -> 0 | AB40: =Z40+AA40 -> 0 | AC40: 0 | AD40: =Jul!AA23 -> 0 | AE40: =AC40+AD40 -> 0 | AF40: 0 | AG40: =Aug!AA23 -> 0 | AH40: =AF40+AG40 -> 0 | AI40: 0 | AJ40: =Sep!AA23 -> 0 | AK40: =AI40+AJ40 -> 0 | AL40: 0 | AM40: =Oct!AA23 -> 0 | AN40: =AL40+AM40 -> 0 | AO40: 0 | AP40: =Nov!AA23 -> 0 | AQ40: =AO40+AP40 -> 0 | AR40: 0 | AS40: =Dec!AA24 -> 0 | AT40: =AR40+AS40 -> 0
D41: Baby Sitter | E41: =K41+N41+Q41+T41+W41+Z41+AC41+AF41+AI41+AL41+AO41+AR41 -> 10300 | F41: =L41+O41+R41+U41+X41+AA41+AD41+AG41+AJ41+AM41+AP41+AS41 -> -4801 | G41: =E41+F41 -> 5499 | H41: =ABS(F41)/E41 -> 0.4661165 | J41: =D41 -> Baby Sitter | K41: 900 | L41: =Jan!AA24 -> -880 | M41: =K41+L41 -> 20 | N41: 900 | O41: =Feb!AA24 -> -880 | P41: =N41+O41 -> 20 | Q41: 900 | R41: =Mar!AA24 -> -880 | S41: =Q41+R41 -> 20 | T41: 900 | U41: ='Apr '!AA24 -> -880 | V41: =T41+U41 -> 20 | W41: 900 | X41: ='May '!AA24 -> -1245 | Y41: =W41+X41 -> -345 | Z41: 900 | AA41: ='Jun '!AA24 -> -36 | AB41: =Z41+AA41 -> 864 | AC41: 800 | AD41: =Jul!AA24 -> 0 | AE41: =AC41+AD41 -> 800 | AF41: 900 | AG41: =Aug!AA24 -> 0 | AH41: =AF41+AG41 -> 900 | AI41: 800 | AJ41: =Sep!AA24 -> 0 | AK41: =AI41+AJ41 -> 800 | AL41: 800 | AM41: =Oct!AA24 -> 0 | AN41: =AL41+AM41 -> 800 | AO41: 800 | AP41: =Nov!AA24 -> 0 | AQ41: =AO41+AP41 -> 800 | AR41: 800 | AS41: =Dec!AA25 -> 0 | AT41: =AR41+AS41 -> 800
D42: Total | E42: =SUM(E21:E41) -> 160944 | F42: =SUM(F21:F41) -> -89345 | G42: =SUM(G21:G40) -> 66100 | J42: Total | K42: =SUM(K21:K41) -> 13325 | L42: =SUM(L21:L41) -> -13407 | M42: =SUM(M21:M41) -> -82 | N42: =SUM(N21:N41) -> 11985 | O42: =SUM(O21:O41) -> -12830.68 | P42: =SUM(P21:P41) -> -845.68 | Q42: =SUM(Q21:Q41) -> 13555 | R42: =SUM(R21:R41) -> -17117.97 | ... AT42: =SUM(AT21:AT41) -> 12631.2
E43: 2025 | J43: 2025 | K43: 45658 | N43: 45689 | Q43: 45717 | T43: 45748 | W43: 45778 | Z43: 45809 | AC43: 45839 | AF43: 45870 | AI43: 45901 | AL43: 45931 | AO43: 45962 | AR43: 45992
D44: Category | E44: Budget | F44: Actual | G44: Variance | H44: % of Total | J44: Category | K44: Budget | L44: Actual | M44: Variance | N44: Budget | O44: Actual | P44: Variance | Q44: Budget | R44: Actual | S44: Variance | T44: Budget | U44: Actual | V44: Variance | W44: Budget | X44: Actual | Y44: Variance | Z44: Budget | AA44: Actual | AB44: Variance | AC44: Budget | AD44: Actual | AE44: Variance | AF44: Budget | AG44: Actual | AH44: Variance | AI44: Budget | AJ44: Actual | AK44: Variance | AL44: Budget | AM44: Actual | AN44: Variance | AO44: Budget | AP44: Actual | AQ44: Variance | AR44: Budget | AS44: Actual | AT44: Variance
D45: Cable | E45: =K45+N45+Q45+T45+W45+Z45+AC45+AF45+AI45+AL45+AO45+AR45 -> 5540 | F45: =L45+O45+R45+U45+X45+AA45+AD45+AG45+AJ45+AM45+AP45+AS45 -> -4846.57 | G45: =E45+F45 -> 693.43 | H45: =ABS(F45)/E45 -> 0.87483213 | J45: Cable | K45: 350 | L45: -478.5 | M45: -128.5 | N45: 480 | O45: -471.45 | P45: 8.55 | Q45: 480 | R45: -440.65 | S45: 39.35 | T45: 350 | U45: -207.65 | V45: 142.35 | W45: 350 | X45: -476 | Y45: -126 | Z45: 350 | AA45: -244.46 | AB45: 105.54 | AC45: 350 | AD45: -370.46 | AE45: -20.46 | AF45: 350 | AG45: -264.45 | AH45: 85.55 | AI45: 350 | AJ45: -469 | AK45: -119 | AL45: 680 | AM45: -754.95 | AN45: -74.95 | AO45: 350 | AP45: -453 | AQ45: -103 | AR45: 1100 | AS45: -216 | AT45: 884
D46: Car Insurance | E46: =K46+N46+Q46+T46+W46+Z46+AC46+AF46+AI46+AL46+AO46+AR46 -> 4020 | F46: =L46+O46+R46+U46+X46+AA46+AD46+AG46+AJ46+AM46+AP46+AS46 -> -4026.47 | G46: =E46+F46 -> -6.47 | H46: =ABS(F46)/E46 -> 1.0016095 | J46: Car Insurance | K46: 335 | L46: -336 | M46: -1 | N46: 335 | O46: -336 | P46: -1 | Q46: 335 | R46: -332 | S46: 3 | T46: 335 | U46: -332 | V46: 3 | W46: 335 | X46: -332.47 | Y46: 2.53 | Z46: 335 | AA46: -332 | AB46: 3 | AC46: 335 | AD46: -332 | AE46: 3 | AF46: 335 | AG46: -346 | AH46: -11 | AI46: 335 | AJ46: -342 | AK46: -7 | AL46: 335 | AM46: -322 | AN46: 13 | AO46: 335 | AP46: -342 | AQ46: -7 | AR46: 335 | AS46: -342 | AT46: -7
D47: Cleaners | E47: =K47+N47+Q47+T47+W47+Z47+AC47+AF47+AI47+AL47+AO47+AR47 -> 160 | F47: =L47+O47+R47+U47+X47+AA47+AD47+AG47+AJ47+AM47+AP47+AS47 -> 0 | G47: =E47+F47 -> 160 | H47: =ABS(F47)/E47 -> 0 | J47: Cleaners | K47: 20 | L47: 0 | M47: 20 | N47: 20 | O47: 0 | P47: 20 | Q47: 20 | R47: 0 | S47: 20 | T47: 20 | U47: 0 | V47: 20 | W47: 20 | X47: 0 | Y47: 20 | Z47: 20 | AA47: 0 | AB47: 20 | AC47: 20 | AD47: 0 | AE47: 20 | AF47: 20 | AG47: 0 | AH47: 20 | AI47: 0 | AJ47: 0 | AK47: 0 | AL47: 0 | AM47: 0 | AN47: 0 | AO47: 0 | AP47: 0 | AQ47: 0 | AR47: 0 | AS47: 0 | AT47: 0
D48: Clothes | E48: =K48+N48+Q48+T48+W48+Z48+AC48+AF48+AI48+AL48+AO48+AR48 -> 1611 | F48: =L48+O48+R48+U48+X48+AA48+AD48+AG48+AJ48+AM48+AP48+AS48 -> -3322.58 | G48: =E48+F48 -> -1711.58 | H48: =ABS(F48)/E48 -> 2.0624333 | J48: Clothes | K48: 300 | L48: -177 | M48: 123 | N48: 300 | O48: -219 | P48: 81 | Q48: 20 | R48: -361 | S48: -341 | T48: 20 | U48: -436 | V48: -416 | W48: 300 | X48: -53.76 | Y48: 246.24 | Z48: 20 | AA48: -267.18 | AB48: -247.18 | AC48: 20 | AD48: -457 | AE48: -437 | AF48: 551 | AG48: -601.64 | AH48: -50.64 | AI48: 20 | AJ48: -45 | AK48: -25 | AL48: 20 | AM48: -51 | AN48: -31 | AO48: 20 | AP48: -574 | AQ48: -554 | AR48: 20 | AS48: -80 | AT48: -60
D49: Utilities | E49: =K49+N49+Q49+T49+W49+Z49+AC49+AF49+AI49+AL49+AO49+AR49 -> 8400 | F49: =L49+O49+R49+U49+X49+AA49+AD49+AG49+AJ49+AM49+AP49+AS49 -> -8054.25 | G49: =E49+F49 -> 345.75 | H49: =ABS(F49)/E49 -> 0.95883929 | J49: Utilities | K49: 700 | L49: -724 | M49: -24 | N49: 700 | O49: -721 | P49: -21 | Q49: 700 | R49: -964.97 | S49: -264.97 | T49: 700 | U49: -139.68 | V49: 560.32 | W49: 700 | X49: -605.15 | Y49: 94.85 | Z49: 700 | AA49: -694 | AB49: 6 | AC49: 700 | AD49: -940.68 | AE49: 650 | AF49: 700 | AG49: -592.61 | AH49: 107.39 | AI49: 700 | AJ49: -813.32 | AK49: -113.32 | AL49: 700 | AM49: -579.84 | AN49: 120.16 | AO49: 700 | AP49: -621 | AQ49: 79 | AR49: 700 | AS49: -658 | AT49: 42
D50: Dining | E50: =K50+N50+Q50+T50+W50+Z50+AC50+AF50+AI50+AL50+AO50+AR50 -> 13200 | F50: =L50+O50+R50+U50+X50+AA50+AD50+AG50+AJ50+AM50+AP50+AS50 -> -18139.49 | G50: =E50+F50 -> -4939.49 | H50: =ABS(F50)/E50 -> 1.3742038 | J50: Dining | K50: 1100 | L50: -420.52 | M50: 679.48 | N50: 1100 | O50: -1193.86 | P50: -93.86 | Q50: 1100 | R50: -1637.41 | S50: -537.41 | T50: 1100 | U50: -2071 | V50: -971 | W50: 1100 | X50: -2648 | Y50: -1548 | Z50: 1100 | AA50: -1201.98 | AB50: -101.98 | AC50: 1100 | AD50: -1046 | AE50: 54 | AF50: 1100 | AG50: -2228.34 | AH50: -1128.34 | AI50: 1100 | AJ50: -2053.38 | AK50: -953.38 | AL50: 1100 | AM50: -1182 | AN50: -82 | AO50: 1100 | AP50: -1634 | AQ50: -534 | AR50: 1100 | AS50: -823 | AT50: 277
D51: Entertainment | E51: =K51+N51+Q51+T51+W51+Z51+AC51+AF51+AI51+AL51+AO51+AR51 -> 4916 | F51: =L51+O51+R51+U51+X51+AA51+AD51+AG51+AJ51+AM51+AP51+AS51 -> -4789.02 | G51: =E51+F51 -> 126.98 | H51: =ABS(F51)/E51 -> 0.97417006 | J51: Entertainment | K51: 1000 | L51: -1051.34 | M51: -51.34 | N51: 303 | O51: -303 | P51: 0 | Q51: 150 | R51: -93.19 | S51: 56.81 | T51: 150 | U51: -134.49 | V51: 15.51 | W51: 150 | X51: 0 | Y51: 150 | Z51: 1613 | AA51: -1613 | AB51: 0 | AC51: 800 | AD51: -814 | AE51: -14 | AF51: 150 | AG51: -348 | AH51: -198 | AI51: 150 | AJ51: -77 | AK51: 73 | AL51: 150 | AM51: -80 | AN51: 70 | AO51: 150 | AP51: -75 | AQ51: 75 | AR51: 150 | AS51: -200 | AT51: -50
D52: Gas | E52: =K52+N52+Q52+T52+W52+Z52+AC52+AF52+AI52+AL52+AO52+AR52 -> 2400 | F52: =L52+O52+R52+U52+X52+AA52+AD52+AG52+AJ52+AM52+AP52+AS52 -> -2605.1 | G52: =E52+F52 -> -205.1 | H52: =ABS(F52)/E52 -> 1.0854583 | J52: Gas | K52: 200 | L52: -327 | M52: -127 | N52: 200 | O52: -110 | P52: 90 | Q52: 200 | R52: -289.27 | S52: -89.27 | T52: 200 | U52: -323 | V52: -123 | W52: 200 | X52: -188 | Y52: 12 | Z52: 200 | AA52: -291.83 | AB52: -91.83 | AC52: 200 | AD52: -155 | AE52: 45 | AF52: 200 | AG52: -201 | AH52: -1 | AI52: 200 | AJ52: -230 | AK52: -30 | AL52: 200 | AM52: -255 | AN52: -55 | AO52: 200 | AP52: -100 | AQ52: 100 | AR52: 200 | AS52: -135 | AT52: 65
D53: Gifts | E53: =K53+N53+Q53+T53+W53+Z53+AC53+AF53+AI53+AL53+AO53+AR53 -> 3450 | F53: =L53+O53+R53+U53+X53+AA53+AD53+AG53+AJ53+AM53+AP53+AS53 -> -3429 | G53: =E53+F53 -> 21 | H53: =ABS(F53)/E53 -> 0.99391304 | J53: Gifts | K53: 100 | L53: -118 | M53: -18 | N53: 50 | O53: 0 | P53: 50 | Q53: 50 | R53: -84 | S53: -34 | T53: 200 | U53: 0 | V53: 200 | W53: 300 | X53: -400 | Y53: -100 | Z53: 350 | AA53: -528 | AB53: -178 | AC53: 200 | AD53: -120 | AE53: 80 | AF53: 600 | AG53: -608 | AH53: -8 | AI53: 50 | AJ53: 132 | AK53: 182 | AL53: 50 | AM53: -723 | AN53: -673 | AO53: 500 | AP53: -520 | AQ53: -20 | AR53: 1000 | AS53: -460 | AT53: 540
D54: Grocery | E54: =K54+N54+Q54+T54+W54+Z54+AC54+AF54+AI54+AL54+AO54+AR54 -> 12000 | F54: =L54+O54+R54+U54+X54+AA54+AD54+AG54+AJ54+AM54+AP54+AS54 -> -13428.26 | G54: =E54+F54 -> -1428.26 | H54: =ABS(F54)/E54 -> 1.1190217 | J54: Grocery | K54: 1000 | L54: -2267.44 | M54: -1267.44 | N54: 1000 | O54: -999.86 | P54: 0.14 | Q54: 1000 | R54: -1412 | S54: -412 | T54: 1000 | U54: -833.36 | V54: 166.64 | W54: 1000 | X54: -501 | Y54: 499 | Z54: 1000 | AA54: -1134 | AB54: -134 | AC54: 1000 | AD54: -1135 | AE54: -135 | AF54: 1000 | AG54: -526 | AH54: 474 | AI54: 1000 | AJ54: -1074 | AK54: -74 | AL54: 1000 | AM54: -856 | AN54: 144 | AO54: 1000 | AP54: -1144.6 | AQ54: -144.6 | AR54: 1000 | AS54: -1545 | AT54: -545
D55: Gym | E55: =K55+N55+Q55+T55+W55+Z55+AC55+AF55+AI55+AL55+AO55+AR55 -> 2400 | F55: =L55+O55+R55+U55+X55+AA55+AD55+AG55+AJ55+AM55+AP55+AS55 -> -1858 | G55: =E55+F55 -> 542 | H55: =ABS(F55)/E55 -> 0.77416667 | J55: Gym | K55: 200 | L55: -270 | M55: -70 | N55: 200 | O55: -300 | P55: -100 | Q55: 200 | R55: -269 | S55: -69 | T55: 200 | U55: -180 | V55: 20 | W55: 200 | X55: -170 | Y55: 30 | Z55: 200 | AA55: -168 | AB55: 32 | AC55: 200 | AD55: -160 | AE55: 40 | AF55: 200 | AG55: -160 | AH55: 40 | AI55: 200 | AJ55: 0 | AK55: 200 | AL55: 200 | AM55: 0 | AN55: 200 | AO55: 200 | AP55: -181 | AQ55: 19 | AR55: 200 | AS55: 0 | AT55: 200
D56: Loan | E56: =K56+N56+Q56+T56+W56+Z56+AC56+AF56+AI56+AL56+AO56+AR56 -> 0 | F56: =L56+O56+R56+U56+X56+AA56+AD56+AG56+AJ56+AM56+AP56+AS56 -> 0 | G56: =E56+F56 -> 0 | H56: 0 | J56: Loan | K56: 0 | L56: 0 | M56: 0 | N56: 0 | O56: 0 | P56: 0 | Q56: 0 | R56: 0 | S56: 0 | T56: 0 | U56: 0 | V56: 0 | W56: 0 | X56: 0 | Y56: 0 | Z56: 0 | AA56: 0 | AB56: 0 | AC56: 0 | AD56: 0 | AE56: 0 | AF56: 0 | AG56: 0 | AH56: 0 | AI56: 0 | AJ56: 0 | AK56: 0 | AL56: 0 | AM56: 0 | AN56: 0 | AO56: 0 | AP56: 0 | AQ56: 0 | AR56: 0 | AS56: 0 | AT56: 0
D57: Misc | E57: =K57+N57+Q57+T57+W57+Z57+AC57+AF57+AI57+AL57+AO57+AR57 -> 7300 | F57: =L57+O57+R57+U57+X57+AA57+AD57+AG57+AJ57+AM57+AP57+AS57 -> -8066.38 | G57: =E57+F57 -> -766.38 | H57: =ABS(F57)/E57 -> 1.1049836 | J57: Misc | K57: 2000 | L57: -1718 | M57: 282 | N57: 500 | O57: -169 | P57: 331 | Q57: 500 | R57: -928.79 | S57: -428.79 | T57: 500 | U57: 0 | V57: 500 | W57: 500 | X57: -337 | Y57: 163 | Z57: 500 | AA57: -199 | AB57: 301 | AC57: 500 | AD57: -612 | AE57: -112 | AF57: 500 | AG57: -564.19 | AH57: -64.19 | AI57: 200 | AJ57: -599 | AK57: -399 | AL57: 500 | AM57: -967 | AN57: -467 | AO57: 500 | AP57: -524.4 | AQ57: -24.4 | AR57: 600 | AS57: -1448 | AT57: -848
D58: Offering | E58: =K58+N58+Q58+T58+W58+Z58+AC58+AF58+AI58+AL58+AO58+AR58 -> 6000 | F58: =L58+O58+R58+U58+X58+AA58+AD58+AG58+AJ58+AM58+AP58+AS58 -> -8410 | G58: =E58+F58 -> -2410 | H58: =ABS(F58)/E58 -> 1.4016667 | J58: Offering | K58: 500 | L58: -705 | M58: -205 | N58: 500 | O58: -560 | P58: -60 | Q58: 500 | R58: -700 | S58: -200 | T58: 500 | U58: -657 | V58: -157 | W58: 500 | X58: -507 | Y58: -7 | Z58: 500 | AA58: -607 | AB58: -107 | AC58: 500 | AD58: -607 | AE58: -107 | AF58: 500 | AG58: -1084 | AH58: -584 | AI58: 500 | AJ58: -452 | AK58: 48 | AL58: 500 | AM58: -813 | AN58: -313 | AO58: 500 | AP58: -1169 | AQ58: -669 | AR58: 500 | AS58: -549 | AT58: -49
D59: Rent | E59: =K59+N59+Q59+T59+W59+Z59+AC59+AF59+AI59+AL59+AO59+AR59 -> 49905 | F59: =L59+O59+R59+U59+X59+AA59+AD59+AG59+AJ59+AM59+AP59+AS59 -> -48773 | G59: =E59+F59 -> 1132 | H59: =ABS(F59)/E59 -> 0.9773169 | J59: Rent | K59: 4200 | L59: -4035 | M59: 165 | N59: 4035 | O59: -4035 | P59: 0 | Q59: 4035 | R59: -4035 | S59: 0 | T59: 4035 | U59: -4035 | V59: 0 | W59: 4200 | X59: -4035 | Y59: 165 | Z59: 4200 | AA59: -4035 | AB59: 165 | AC59: 4200 | AD59: -4135 | AE59: 65 | AF59: 4200 | AG59: -4135 | AH59: 65 | AI59: 4200 | AJ59: -3985 | AK59: 215 | AL59: 4200 | AM59: -4085 | AN59: 115 | AO59: 4200 | AP59: -4085 | AQ59: 115 | AR59: 4200 | AS59: -4138 | AT59: 62
D60: Travel | E60: =K60+N60+Q60+T60+W60+Z60+AC60+AF60+AI60+AL60+AO60+AR60 -> 4181 | F60: =L60+O60+R60+U60+X60+AA60+AD60+AG60+AJ60+AM60+AP60+AS60 -> -4603.3 | G60: =E60+F60 -> -422.3 | H60: =ABS(F60)/E60 -> 1.1010045 | J60: Travel | K60: 150 | L60: 0 | M60: 150 | N60: 0 | O60: 0 | P60: 0 | Q60: 1800 | R60: -1756.05 | S60: 43.95 | T60: 0 | U60: 0 | V60: 0 | W60: 500 | X60: -512.25 | Y60: -12.25 | Z60: 100 | AA60: -265 | AB60: -165 | AC60: 100 | AD60: -60 | AE60: 40 | AF60: 826.2 | AG60: -1079 | AH60: -252.8 | AI60: 176.2 | AJ60: -531 | AK60: -354.8 | AL60: 176.2 | AM60: -400 | AN60: -223.8 | AO60: 176.2 | AP60: 0 | AQ60: 176.2 | AR60: 176.2 | AS60: 0 | AT60: 176.2
D61: Parents | E61: =K61+N61+Q61+T61+W61+Z61+AC61+AF61+AI61+AL61+AO61+AR61 -> 3550 | F61: =L61+O61+R61+U61+X61+AA61+AD61+AG61+AJ61+AM61+AP61+AS61 -> -9116 | G61: =E61+F61 -> -5566 | H61: =ABS(F61)/E61 -> 2.5678873 | J61: Parents | K61: 200 | L61: -426 | M61: -226 | N61: 200 | O61: -430 | P61: -230 | Q61: 200 | R61: -200 | S61: 0 | T61: 250 | U61: -250 | V61: 0 | W61: 250 | X61: -200 | Y61: 50 | Z61: 1150 | AA61: -1150 | AB61: 0 | AC61: 250 | AD61: -200 | AE61: 50 | AF61: 250 | AG61: -405 | AH61: -155 | AI61: 200 | AJ61: -1030 | AK61: -830 | AL61: 200 | AM61: -200 | AN61: 0 | AO61: 200 | AP61: -425 | AQ61: -225 | AR61: 200 | AS61: -4200 | AT61: -4000
D62: Car | E62: =K62+N62+Q62+T62+W62+Z62+AC62+AF62+AI62+AL62+AO62+AR62 -> 3073 | F62: =L62+O62+R62+U62+X62+AA62+AD62+AG62+AJ62+AM62+AP62+AS62 -> -2322 | G62: =E62+F62 -> 751 | H62: =ABS(F62)/E62 -> 0.75561341 | J62: Car | K62: 200 | L62: -360 | M62: -160 | N62: 200 | O62: -265 | P62: -65 | Q62: 250 | R62: -130 | S62: 120 | T62: 250 | U62: -135 | V62: 115 | W62: 0 | X62: 0 | Y62: 0 | Z62: 50 | AA62: 0 | AB62: 50 | AC62: 500 | AD62: 0 | AE62: 500 | AF62: 523 | AG62: -294 | AH62: 229 | AI62: 500 | AJ62: -290 | AK62: 210 | AL62: 200 | AM62: -738 | AN62: -538 | AO62: 200 | AP62: -110 | AQ62: 90 | AR62: 200 | AS62: 0 | AT62: 200
D63: House | E63: =K63+N63+Q63+T63+W63+Z63+AC63+AF63+AI63+AL63+AO63+AR63 -> 4000 | F63: =L63+O63+R63+U63+X63+AA63+AD63+AG63+AJ63+AM63+AP63+AS63 -> -3911.1 | G63: =E63+F63 -> 88.9 | H63: =ABS(F63)/E63 -> 0.977775 | J63: House | K63: 200 | L63: -215 | M63: -15 | N63: 200 | O63: -680.1 | P63: -480.1 | Q63: 200 | R63: 0 | S63: 200 | T63: 200 | U63: -447 | V63: -247 | W63: 200 | X63: -325 | Y63: -125 | Z63: 200 | AA63: -325 | AB63: -125 | AC63: 1000 | AD63: -426 | AE63: 574 | AF63: 200 | AG63: -136 | AH63: 64 | AI63: 400 | AJ63: -371 | AK63: 29 | AL63: 400 | AM63: -220 | AN63: 180 | AO63: 400 | AP63: -691 | AQ63: -291 | AR63: 400 | AS63: -75 | AT63: 325
D64: School | E64: =K64+N64+Q64+T64+W64+Z64+AC64+AF64+AI64+AL64+AO64+AR64 -> 920 | F64: =L64+O64+R64+U64+X64+AA64+AD64+AG64+AJ64+AM64+AP64+AS64 -> -3036 | G64: =E64+F64 -> -2116 | H64: =ABS(F64)/E64 -> 3.3 | J64: School | K64: 120 | L64: -309 | M64: -189 | N64: 0 | O64: 0 | P64: 0 | Q64: 0 | R64: 0 | S64: 0 | T64: 200 | U64: -100 | V64: 100 | W64: 0 | X64: 0 | Y64: 0 | Z64: 0 | AA64: -203 | AB64: -203 | AC64: 200 | AD64: -242 | AE64: -42 | AF64: 200 | AG64: -1034 | AH64: -834 | AI64: 200 | AJ64: -1148 | AK64: -948 | AL64: 0 | AM64: 0 | AN64: 0 | AO64: 0 | AP64: 0 | AQ64: 0 | AR64: 0 | AS64: 0 | AT64: 0
D65: Baby Sitter | E65: =K65+N65+Q65+T65+W65+Z65+AC65+AF65+AI65+AL65+AO65+AR65 -> 10106 | F65: =L65+O65+R65+U65+X65+AA65+AD65+AG65+AJ65+AM65+AP65+AS65 -> -7446 | G65: =E65+F65 -> 2660 | H65: =ABS(F65)/E65 -> 0.73679003 | J65: =D65 -> Baby Sitter | K65: 800 | L65: 0 | M65: 800 | N65: 800 | O65: 0 | P65: 800 | Q65: 800 | R65: 0 | S65: 800 | T65: 1006 | U65: -1006 | V65: 0 | W65: 900 | X65: -780 | Y65: 120 | Z65: 900 | AA65: -780 | AB65: 120 | AC65: 800 | AD65: -780 | AE65: 20 | AF65: 900 | AG65: -780 | AH65: 120 | AI65: 800 | AJ65: -780 | AK65: 20 | AL65: 800 | AM65: -780 | AN65: 20 | AO65: 800 | AP65: -880 | AQ65: -80 | AR65: 800 | AS65: -880 | AT65: -80
D66: Total | E66: =SUM(E45:E64) -> 137026 | F66: =SUM(F45:F65) -> -160182.52 | G66: =SUM(G45:G64) -> -15710.52 | J66: Total | K66: 13675 | L66: -13937.8 | M66: -262.8 | N66: 11123 | O66: -10793.27 | P66: 329.73 | Q66: 12540 | R66: -13633.33 | S66: -1093.33 | T66: 11216 | U66: -11287.18 | V66: -71.18 | W66: 11705 | X66: -12070.63 | Y66: -365.63 | Z66: 13488 | AA66: -14038.45 | AB66: -550.45 | AC66: 12975 | AD66: -12592.14 | AE66: 1273.54 | AF66: 13305.2 | AG66: -15387.23 | AH66: -2082.03 | AI66: 11281.2 | AJ66: -14157.7 | AK66: -2876.5 | AL66: 11411.2 | AM66: -13006.79 | AN66: -1595.59 | AO66: 11531.2 | AP66: -13529 | AQ66: -1997.8 | AR66: 12881.2 | AS66: -15749 | AT66: -2867.8
E67: 2024 | J67: 2024 | K67: 45292 | N67: 45323 | Q67: 45352 | T67: 45383 | W67: 45413 | Z67: 45444 | AC67: 45474 | AF67: 45505 | AI67: 45536 | AL67: 45566 | AO67: 45597 | AR67: 45627
D68: Category | E68: Budget | F68: Actual | G68: Variance | H68: % of Total | J68: Category | K68: Budget | L68: Actual | M68: Variance | N68: Budget | O68: Actual | P68: Variance | Q68: Budget | R68: Actual | S68: Variance | T68: Budget | U68: Actual | V68: Variance | W68: Budget | X68: Actual | Y68: Variance | Z68: Budget | AA68: Actual | AB68: Variance | AC68: Budget | AD68: Actual | AE68: Variance | AF68: Budget | AG68: Actual | AH68: Variance | AI68: Budget | AJ68: Actual | AK68: Variance | AL68: Budget | AM68: Actual | AN68: Variance | AO68: Budget | AP68: Actual | AQ68: Variance | AR68: Budget | AS68: Actual | AT68: Variance
D69: Cable | E69: =K69+N69+Q69+T69+W69+Z69+AC69+AF69+AI69+AL69+AO69+AR69 -> 4200 | F69: =L69+O69+R69+U69+X69+AA69+AD69+AG69+AJ69+AM69+AP69+AS69 -> -3993.94 | G69: =E69+F69 -> 206.06 | H69: =ABS(F69)/E69 -> 0.9509381 | J69: Cable | K69: 350 | L69: -311.48 | M69: 38.52 | N69: 350 | O69: -214 | P69: 136 | Q69: 350 | R69: -323 | S69: 27 | T69: 350 | U69: -227.49 | V69: 122.51 | W69: 350 | X69: -335 | Y69: 15 | Z69: 350 | AA69: -471 | AB69: -121 | AC69: 350 | AD69: -337 | AE69: 13 | AF69: 350 | AG69: -262.97 | AH69: 87.03 | AI69: 350 | AJ69: -395 | AK69: -45 | AL69: 350 | AM69: -479 | AN69: 350 | AO69: 350 | AP69: -265 | AQ69: 85 | AR69: 350 | AS69: -373 | AT69: -23
D70: Car Insurance | E70: =K70+N70+Q70+T70+W70+Z70+AC70+AF70+AI70+AL70+AO70+AR70 -> 3240 | F70: =L70+O70+R70+U70+X70+AA70+AD70+AG70+AJ70+AM70+AP70+AS70 -> -4515 | G70: =E70+F70 -> -1275 | H70: =ABS(F70)/E70 -> 1.3935185 | J70: Car Insurance | K70: 270 | L70: -270 | M70: 0 | N70: 270 | O70: -1220 | P70: -950 | Q70: 270 | R70: -270 | S70: 0 | T70: 270 | U70: -270 | V70: 0 | W70: 270 | X70: -270 | Y70: 0 | Z70: 270 | AA70: -269 | AB70: 1 | AC70: 270 | AD70: -269 | AE70: 1 | AF70: 270 | AG70: -352 | AH70: -82 | AI70: 270 | AJ70: -332 | AK70: -62 | AL70: 270 | AM70: -335 | AN70: 270 | AO70: 270 | AP70: -332 | AQ70: -62 | AR70: 270 | AS70: -326 | AT70: -56
D71: Cleaners | E71: =K71+N71+Q71+T71+W71+Z71+AC71+AF71+AI71+AL71+AO71+AR71 -> 160 | F71: =L71+O71+R71+U71+X71+AA71+AD71+AG71+AJ71+AM71+AP71+AS71 -> 0 | G71: =E71+F71 -> 160 | H71: =ABS(F71)/E71 -> 0 | J71: Cleaners | K71: 20 | L71: 0 | M71: 20 | N71: 20 | O71: 0 | P71: 20 | Q71: 20 | R71: 0 | S71: 20 | T71: 20 | U71: 0 | V71: 20 | W71: 20 | X71: 0 | Y71: 20 | Z71: 20 | AA71: 0 | AB71: 20 | AC71: 20 | AD71: 0 | AE71: 20 | AF71: 20 | AG71: 0 | AH71: 20 | AI71: 0 | AJ71: 0 | AK71: 0 | AL71: 0 | AM71: 0 | AN71: 0 | AO71: 0 | AP71: 0 | AQ71: 0 | AR71: 0 | AS71: 0 | AT71: 0
D72: Clothes | E72: =K72+N72+Q72+T72+W72+Z72+AC72+AF72+AI72+AL72+AO72+AR72 -> 1080 | F72: =L72+O72+R72+U72+X72+AA72+AD72+AG72+AJ72+AM72+AP72+AS72 -> -3446.48 | G72: =E72+F72 -> -2366.48 | H72: =ABS(F72)/E72 -> 3.1911852 | J72: Clothes | K72: 300 | L72: -109 | M72: 191 | N72: 300 | O72: -123.71 | P72: 176.29 | Q72: 20 | R72: -349 | S72: -329 | T72: 20 | U72: -163 | V72: -143 | W72: 300 | X72: -150 | Y72: 150 | Z72: 20 | AA72: 0 | AB72: 20 | AC72: 20 | AD72: -895.77 | AE72: -875.77 | AF72: 20 | AG72: -636 | AH72: -616 | AI72: 20 | AJ72: -270 | AK72: -250 | AL72: 20 | AM72: -303 | AN72: 20 | AO72: 20 | AP72: -297 | AQ72: -277 | AR72: 20 | AS72: -150 | AT72: -130
D73: Utilities | E73: =K73+N73+Q73+T73+W73+Z73+AC73+AF73+AI73+AL73+AO73+AR73 -> 7200 | F73: =L73+O73+R73+U73+X73+AA73+AD73+AG73+AJ73+AM73+AP73+AS73 -> -8422.68 | G73: =E73+F73 -> -1222.68 | H73: =ABS(F73)/E73 -> 1.1698167 | J73: Utilities | K73: 600 | L73: -683 | M73: -83 | N73: 600 | O73: -791.49 | P73: -191.49 | Q73: 600 | R73: -639 | S73: -39 | T73: 600 | U73: -638 | V73: -38 | W73: 600 | X73: -610 | Y73: -10 | Z73: 600 | AA73: -863 | AB73: -263 | AC73: 600 | AD73: -831.16 | AE73: -231.16 | AF73: 600 | AG73: -542.03 | AH73: 57.97 | AI73: 600 | AJ73: -866 | AK73: -266 | AL73: 600 | AM73: -426 | AN73: 600 | AO73: 600 | AP73: -885 | AQ73: -285 | AR73: 600 | AS73: -648 | AT73: -48
D74: Dining | E74: =K74+N74+Q74+T74+W74+Z74+AC74+AF74+AI74+AL74+AO74+AR74 -> 10000 | F74: =L74+O74+R74+U74+X74+AA74+AD74+AG74+AJ74+AM74+AP74+AS74 -> -16817.09 | G74: =E74+F74 -> -6817.09 | H74: =ABS(F74)/E74 -> 1.681709 | J74: Dining | K74: 900 | L74: -894 | M74: 6 | N74: 900 | O74: -1148.78 | P74: -248.78 | Q74: 900 | R74: -920.73 | S74: -20.73 | T74: 900 | U74: -1503.43 | V74: -603.43 | W74: 800 | X74: -1431 | Y74: -631 | Z74: 800 | AA74: -1825 | AB74: -1025 | AC74: 800 | AD74: -1605.38 | AE74: -805.38 | AF74: 800 | AG74: -1204 | AH74: -404 | AI74: 800 | AJ74: -2071.36 | AK74: -1271.36 | AL74: 800 | AM74: -2105 | AN74: 800 | AO74: 800 | AP74: -964.41 | AQ74: -164.41 | AR74: 800 | AS74: -1144 | AT74: -344
D75: Entertainment | E75: =K75+N75+Q75+T75+W75+Z75+AC75+AF75+AI75+AL75+AO75+AR75 -> 2100 | F75: =L75+O75+R75+U75+X75+AA75+AD75+AG75+AJ75+AM75+AP75+AS75 -> -4405 | G75: =E75+F75 -> -2305 | H75: =ABS(F75)/E75 -> 2.097619 | J75: Entertainment | K75: 100 | L75: 0 | M75: 100 | N75: 100 | O75: -134 | P75: -34 | Q75: 100 | R75: -1373 | S75: -1273 | T75: 1000 | U75: -1371 | V75: -371 | W75: 100 | X75: -303 | Y75: -203 | Z75: 100 | AA75: -584 | AB75: -484 | AC75: 100 | AD75: 0 | AE75: 100 | AF75: 100 | AG75: -80 | AH75: 20 | AI75: 100 | AJ75: -260 | AK75: -160 | AL75: 100 | AM75: -230 | AN75: 100 | AO75: 100 | AP75: 0 | AQ75: 100 | AR75: 100 | AS75: -70 | AT75: 30
D76: Gas | E76: =K76+N76+Q76+T76+W76+Z76+AC76+AF76+AI76+AL76+AO76+AR76 -> 1800 | F76: =L76+O76+R76+U76+X76+AA76+AD76+AG76+AJ76+AM76+AP76+AS76 -> -2230.68 | G76: =E76+F76 -> -430.68 | H76: =ABS(F76)/E76 -> 1.2392667 | J76: Gas | K76: 150 | L76: -55.5 | M76: 94.5 | N76: 150 | O76: -285.18 | P76: -135.18 | Q76: 150 | R76: -271 | S76: -121 | T76: 150 | U76: -150 | V76: 0 | W76: 150 | X76: -424 | Y76: -274 | Z76: 150 | AA76: -219 | AB76: -69 | AC76: 150 | AD76: -277 | AE76: -127 | AF76: 150 | AG76: -128 | AH76: 22 | AI76: 150 | AJ76: -69 | AK76: 81 | AL76: 150 | AM76: -65 | AN76: 150 | AO76: 150 | AP76: -72 | AQ76: 78 | AR76: 150 | AS76: -215 | AT76: -65
D77: Gifts | E77: =K77+N77+Q77+T77+W77+Z77+AC77+AF77+AI77+AL77+AO77+AR77 -> 3050 | F77: =L77+O77+R77+U77+X77+AA77+AD77+AG77+AJ77+AM77+AP77+AS77 -> -7078.06 | G77: =E77+F77 -> -4028.06 | H77: =ABS(F77)/E77 -> 2.3206754 | J77: Gifts | K77: 1000 | L77: -855 | M77: 145 | N77: 50 | O77: 0 | P77: 50 | Q77: 50 | R77: -323.24 | S77: -273.24 | T77: 200 | U77: 0 | V77: 200 | W77: 300 | X77: -440 | Y77: -140 | Z77: 50 | AA77: -2122 | AB77: -2072 | AC77: 200 | AD77: -117.82 | AE77: 82.18 | AF77: 50 | AG77: 0 | AH77: 50 | AI77: 50 | AJ77: -400 | AK77: -350 | AL77: 50 | AM77: -541 | AN77: 50 | AO77: 50 | AP77: -711 | AQ77: -661 | AR77: 1000 | AS77: -1568 | AT77: -568
D78: Grocery | E78: =K78+N78+Q78+T78+W78+Z78+AC78+AF78+AI78+AL78+AO78+AR78 -> 10800 | F78: =L78+O78+R78+U78+X78+AA78+AD78+AG78+AJ78+AM78+AP78+AS78 -> -14672.91 | G78: =E78+F78 -> -3872.91 | H78: =ABS(F78)/E78 -> 1.3586028 | J78: Grocery | K78: 700 | L78: -843.51 | M78: -143.51 | N78: 700 | O78: -1210.52 | P78: -510.52 | Q78: 700 | R78: -973 | S78: -273 | T78: 1000 | U78: -1077 | V78: -77 | W78: 1000 | X78: -1399 | Y78: -399 | Z78: 700 | AA78: -1018 | AB78: -318 | AC78: 1000 | AD78: -1562 | AE78: -562 | AF78: 1000 | AG78: -1842 | AH78: -842 | AI78: 1000 | AJ78: -916.64 | AK78: 83.36 | AL78: 1000 | AM78: -1104.24 | AN78: 1000 | AO78: 1000 | AP78: -1125 | AQ78: -125 | AR78: 1000 | AS78: -1602 | AT78: -602
D79: Gym | E79: =K79+N79+Q79+T79+W79+Z79+AC79+AF79+AI79+AL79+AO79+AR79 -> 3450 | F79: =L79+O79+R79+U79+X79+AA79+AD79+AG79+AJ79+AM79+AP79+AS79 -> -2664.8 | G79: =E79+F79 -> 785.2 | H79: =ABS(F79)/E79 -> 0.7724058 | J79: Gym | K79: 300 | L79: -312 | M79: -12 | N79: 300 | O79: -310 | P79: -10 | Q79: 300 | R79: -160 | S79: 140 | T79: 300 | U79: -280 | V79: 20 | W79: 300 | X79: -164 | Y79: 136 | Z79: 300 | AA79: -163 | AB79: 137 | AC79: 300 | AD79: -324.8 | AE79: -24.8 | AF79: 300 | AG79: -177 | AH79: 123 | AI79: 150 | AJ79: -170 | AK79: -20 | AL79: 300 | AM79: -160 | AN79: 300 | AO79: 300 | AP79: -160 | AQ79: 140 | AR79: 300 | AS79: -284 | AT79: 16
D80: Loan | E80: =K80+N80+Q80+T80+W80+Z80+AC80+AF80+AI80+AL80+AO80+AR80 -> 0 | F80: =L80+O80+R80+U80+X80+AA80+AD80+AG80+AJ80+AM80+AP80+AS80 -> 0 | G80: =E80+F80 -> 0 | H80: 0 | J80: Loan | K80: 0 | L80: 0 | M80: 0 | N80: 0 | O80: 0 | P80: 0 | Q80: 0 | R80: 0 | S80: 0 | T80: 0 | U80: 0 | V80: 0 | W80: 0 | X80: 0 | Y80: 0 | Z80: 0 | AA80: 0 | AB80: 0 | AC80: 0 | AD80: 0 | AE80: 0 | AF80: 0 | AG80: 0 | AH80: 0 | AI80: 0 | AJ80: 0 | AK80: 0 | AL80: 0 | AM80: 0 | AN80: 0 | AO80: 0 | AP80: 0 | AQ80: 0 | AR80: 0 | AS80: 0 | AT80: 0
D81: Misc | E81: =K81+N81+Q81+T81+W81+Z81+AC81+AF81+AI81+AL81+AO81+AR81 -> 7600 | F81: =L81+O81+R81+U81+X81+AA81+AD81+AG81+AJ81+AM81+AP81+AS81 -> -8684.53 | G81: =E81+F81 -> -1084.53 | H81: =ABS(F81)/E81 -> 1.1427013 | J81: Misc | K81: 2000 | L81: -2760.26 | M81: -760.26 | N81: 500 | O81: -694.27 | P81: -194.27 | Q81: 500 | R81: -539 | S81: -39 | T81: 500 | U81: -347 | V81: 153 | W81: 500 | X81: -366 | Y81: 134 | Z81: 500 | AA81: -601 | AB81: -101 | AC81: 500 | AD81: -318 | AE81: 182 | AF81: 500 | AG81: -380 | AH81: 120 | AI81: 500 | AJ81: -342 | AK81: 158 | AL81: 500 | AM81: -743 | AN81: 500 | AO81: 500 | AP81: -371 | AQ81: 129 | AR81: 600 | AS81: -1223 | AT81: -623
D82: Offering | E82: =K82+N82+Q82+T82+W82+Z82+AC82+AF82+AI82+AL82+AO82+AR82 -> 4800 | F82: =L82+O82+R82+U82+X82+AA82+AD82+AG82+AJ82+AM82+AP82+AS82 -> -5273 | G82: =E82+F82 -> -473 | H82: =ABS(F82)/E82 -> 1.0985417 | J82: Offering | K82: 400 | L82: -393 | M82: 7 | N82: 400 | O82: -350 | P82: 50 | Q82: 400 | R82: -243 | S82: 157 | T82: 400 | U82: -343 | V82: 57 | W82: 400 | X82: -371 | Y82: 29 | Z82: 400 | AA82: -447 | AB82: -47 | AC82: 400 | AD82: -256 | AE82: 144 | AF82: 400 | AG82: -507 | AH82: -107 | AI82: 400 | AJ82: -549 | AK82: -149 | AL82: 400 | AM82: -554 | AN82: 400 | AO82: 400 | AP82: -561 | AQ82: -161 | AR82: 400 | AS82: -699 | AT82: -299
D83: Rent | E83: =K83+N83+Q83+T83+W83+Z83+AC83+AF83+AI83+AL83+AO83+AR83 -> 45255 | F83: =L83+O83+R83+U83+X83+AA83+AD83+AG83+AJ83+AM83+AP83+AS83 -> -50666 | G83: =E83+F83 -> -5411 | H83: =ABS(F83)/E83 -> 1.1195669 | J83: Rent | K83: 3600 | L83: -3611 | M83: -11 | N83: 3600 | O83: -3611 | P83: -11 | Q83: 3600 | R83: -3611 | S83: -11 | T83: 3600 | U83: -3611 | V83: -11 | W83: 3600 | X83: -3611 | Y83: -11 | Z83: 3600 | AA83: -11017 | AB83: -7417 | AC83: 3600 | AD83: -1511 | AE83: 2089 | AF83: 4011 | AG83: -4015 | AH83: -4 | AI83: 4011 | AJ83: -4011 | AK83: 0 | AL83: 4011 | AM83: -4011 | AN83: 4011 | AO83: 4011 | AP83: -4011 | AQ83: 0 | AR83: 4011 | AS83: -4035 | AT83: -24
D84: Travel | E84: =K84+N84+Q84+T84+W84+Z84+AC84+AF84+AI84+AL84+AO84+AR84 -> 11131 | F84: =L84+O84+R84+U84+X84+AA84+AD84+AG84+AJ84+AM84+AP84+AS84 -> -13939 | G84: =E84+F84 -> -2808 | H84: =ABS(F84)/E84 -> 1.2522684 | J84: Travel | K84: 150 | L84: -58 | M84: 92 | N84: 2000 | O84: -2831 | P84: -831 | Q84: 176.2 | R84: 0 | S84: 176.2 | T84: 0 | U84: -736 | V84: -736 | W84: 500 | X84: 0 | Y84: 500 | Z84: 500 | AA84: 0 | AB84: 500 | AC84: 100 | AD84: 0 | AE84: 100 | AF84: 7000 | AG84: -6735 | AH84: 265 | AI84: 176.2 | AJ84: -429 | AK84: -252.8 | AL84: 176.2 | AM84: 0 | AN84: 176.2 | AO84: 176.2 | AP84: -1976 | AQ84: 24 | AR84: 176.2 | AS84: -1174 | AT84: -997.8
D85: Parents | E85: =K85+N85+Q85+T85+W85+Z85+AC85+AF85+AI85+AL85+AO85+AR85 -> 2400 | F85: =L85+O85+R85+U85+X85+AA85+AD85+AG85+AJ85+AM85+AP85+AS85 -> -8401 | G85: =E85+F85 -> -6001 | H85: =ABS(F85)/E85 -> 3.5004167 | J85: Parents | K85: 200 | L85: -150 | M85: 50 | N85: 200 | O85: -1350 | P85: -1150 | Q85: 200 | R85: -200 | S85: 0 | T85: 200 | U85: -200 | V85: 0 | W85: 200 | X85: -200 | Y85: 0 | Z85: 200 | AA85: -746 | AB85: -546 | AC85: 200 | AD85: -1925 | AE85: -1725 | AF85: 200 | AG85: -200 | AH85: 0 | AI85: 200 | AJ85: -200 | AK85: 0 | AL85: 200 | AM85: -200 | AN85: 200 | AO85: 200 | AP85: -200 | AQ85: 0 | AR85: 200 | AS85: -2830 | AT85: -2630
D86: Car | E86: =K86+N86+Q86+T86+W86+Z86+AC86+AF86+AI86+AL86+AO86+AR86 -> 2123 | F86: =L86+O86+R86+U86+X86+AA86+AD86+AG86+AJ86+AM86+AP86+AS86 -> -1793 | G86: =E86+F86 -> 330 | H86: =ABS(F86)/E86 -> 0.84455959 | J86: Car | K86: 500 | L86: 0 | M86: 500 | N86: 500 | O86: 0 | P86: 500 | Q86: 250 | R86: 0 | S86: 250 | T86: 250 | U86: 0 | V86: 250 | W86: 0 | X86: -500 | Y86: -500 | Z86: 0 | AA86: 0 | AB86: 0 | AC86: 0 | AD86: 0 | AE86: 0 | AF86: 523 | AG86: -642 | AH86: -119 | AI86: 100 | AJ86: 0 | AK86: 100 | AL86: 0 | AM86: -651 | AN86: 0 | AO86: 0 | AP86: 0 | AQ86: 0 | AR86: 0 | AS86: 0 | AT86: 0
D87: House | E87: =K87+N87+Q87+T87+W87+Z87+AC87+AF87+AI87+AL87+AO87+AR87 -> 8500 | F87: =L87+O87+R87+U87+X87+AA87+AD87+AG87+AJ87+AM87+AP87+AS87 -> -14326.18 | G87: =E87+F87 -> -5826.18 | H87: =ABS(F87)/E87 -> 1.6854329 | J87: House | K87: 200 | L87: -263.18 | M87: -63.18 | N87: 200 | O87: 0 | P87: 200 | Q87: 200 | R87: -350 | S87: -150 | T87: 200 | U87: 0 | V87: 200 | W87: 200 | X87: -1375 | Y87: -1175 | Z87: 200 | AA87: -508 | AB87: -308 | AC87: 2000 | AD87: -5857 | AE87: -3857 | AF87: 200 | AG87: -210 | AI87: 4500 | AJ87: -4275 | AK87: 225 | AL87: 200 | AM87: -567 | AN87: 200 | AO87: 200 | AP87: -921 | AQ87: -721 | AR87: 200 | AS87: 0 | AT87: 200
D88: School | E88: =K88+N88+Q88+T88+W88+Z88+AC88+AF88+AI88+AL88+AO88+AR88 -> 320 | F88: =L88+O88+R88+U88+X88+AA88+AD88+AG88+AJ88+AM88+AP88+AS88 -> -2421.8 | G88: =E88+F88 -> -2101.8 | H88: =ABS(F88)/E88 -> 7.568125 | J88: School | K88: 120 | L88: -116.23 | M88: 3.77 | N88: 0 | O88: -250 | P88: -250 | Q88: 0 | R88: -1380 | S88: -1380 | T88: 200 | U88: -233.88 | V88: -33.88 | W88: 0 | X88: 0 | Y88: 0 | Z88: 0 | AA88: -175 | AB88: -175 | AC88: 0 | AD88: 0 | AE88: 0 | AF88: 0 | AG88: 0 | AH88: 0 | AI88: 0 | AJ88: 0 | AK88: 0 | AL88: 0 | AM88: 0 | AN88: 0 | AO88: 0 | AP88: -199.69 | AQ88: -199.69 | AR88: 0 | AS88: -67 | AT88: -67
D89: Baby Sitter | E89: =K89+N89+Q89+T89+W89+Z89+AC89+AF89+AI89+AL89+AO89+AR89 -> 10220 | F89: =L89+O89+R89+U89+X89+AA89+AD89+AG89+AJ89+AM89+AP89+AS89 -> -4334 | G89: =E89+F89 -> 5886 | H89: =ABS(F89)/E89 -> 0.42407045 | J89: =D89 -> Baby Sitter | K89: 120 | L89: 0 | M89: 120 | N89: 0 | O89: 0 | P89: 0 | Q89: 1000 | R89: -1380 | S89: -380 | T89: 1000 | U89: -920 | V89: 80 | W89: 900 | X89: -638 | Y89: 262 | Z89: 900 | AA89: -1196 | AB89: -296 | AC89: 200 | AD89: -200 | AE89: 0 | AF89: 900 | AG89: 0 | AH89: 900 | AI89: 800 | AJ89: 0 | AK89: 800 | AL89: 1800 | AM89: 0 | AN89: 1800 | AO89: 1800 | AP89: 0 | AQ89: 800 | AR89: 800 | AS89: 0 | AT89: 800
D90: Total | E90: =SUM(E69:E89) -> 139429 | F90: =SUM(F69:F89) -> -178085.15 | G90: =SUM(G69:G88) -> -44542.15 | J90: Total | K90: 11980 | L90: -11685.16 | M90: 294.84 | N90: 11140 | O90: -14523.95 | P90: -3383.95 | Q90: 9786.2 | R90: -13304.97 | S90: -3518.77 | T90: 11160 | U90: -12070.8 | V90: -910.8 | W90: 10490 | X90: -12587 | Y90: -2097 | Z90: 9660 | AA90: -22224 | AB90: -12564 | AC90: 10810 | AD90: -16286.93 | AE90: -5476.93 | AF90: 17394 | AG90: -17913 | AH90: -509 | AI90: 14177.2 | AJ90: -15556 | AK90: -1378.8 | AL90: 10927.2 | AM90: -12474.24 | AN90: 10927.2 | AO90: 10927.2 | AP90: -13051.1 | AQ90: -1300.1 | AR90: 10977.2 | AS90: -16408 | AT90: -5430.8
E91: 2023 | J91: =E91 -> 2023 | K91: 44927 | N91: 44958 | Q91: 44986 | T91: 45017 | W91: 45047 | Z91: 45078 | AC91: 45108 | AF91: 45139 | AI91: 45170 | AL91: 45200 | AO91: 45231 | AR91: 45261
D92: Category | E92: Budget | F92: Actual | G92: Variance | H92: % of Total | J92: Category | K92: Budget | L92: Actual | M92: Variance | N92: Budget | O92: Actual | P92: Variance | Q92: Budget | R92: Actual | S92: Variance | T92: Budget | U92: Actual | V92: Variance | W92: Budget | X92: Actual | Y92: Variance | Z92: Budget | AA92: Actual | AB92: Variance | AC92: Budget | AD92: Actual | AE92: Variance | AF92: Budget | AG92: Actual | AH92: Variance | AI92: Budget | AJ92: Actual | AK92: Variance | AL92: Budget | AM92: Actual | AN92: Variance | AO92: Budget | AP92: Actual | AQ92: Variance | AR92: Budget | AS92: Actual | AT92: Variance
D93: Cable | E93: 4200 | F93: -2037.2 | G93: =E93+F93 -> 2162.8 | H93: 0.40219048 | J93: Cable | K93: 350 | L93: -236 | M93: 114 | N93: 350 | O93: -148 | P93: 202 | Q93: 350 | R93: -160 | S93: 190 | T93: 350 | U93: -143 | V93: 207 | W93: 350 | X93: -60 | Y93: 290 | Z93: 350 | AA93: -209.27 | AB93: 140.73 | AC93: 350 | AD93: -152.33 | AE93: 197.67 | AF93: 350 | AG93: -120 | AH93: 230 | AI93: 350 | AJ93: -112 | AK93: 238 | AL93: 350 | AM93: -288.6 | AN93: 61.4 | AO93: 350 | AP93: -138 | AQ93: 212 | AR93: 350 | AS93: -270 | AT93: 80
D94: Car Insurance | E94: 2400 | F94: -2349.59 | G94: =E94+F94 -> 50.41 | H94: 0.97899583 | J94: Car Insurance | K94: 200 | L94: 0 | M94: 200 | N94: 200 | O94: -154.92 | P94: 45.08 | Q94: 200 | R94: -154 | S94: 46 | T94: 200 | U94: 0 | V94: 200 | W94: 200 | X94: -322 | Y94: -122 | Z94: 200 | AA94: -322 | AB94: -122 | AC94: 200 | AD94: -321.67 | AE94: -121.67 | AF94: 200 | AG94: -273 | AH94: -73 | AI94: 200 | AJ94: -269 | AK94: -69 | AL94: 200 | AM94: -270 | AN94: -70 | AO94: 200 | AP94: -263 | AQ94: -63 | AR94: 200 | AS94: 0 | AT94: 200
D95: Cleaners | E95: 160 | F95: 0 | G95: =E95+F95 -> 160 | H95: 0 | J95: Cleaners | K95: 20 | L95: 0 | M95: 20 | N95: 20 | O95: 0 | P95: 20 | Q95: 20 | R95: 0 | S95: 20 | T95: 20 | U95: 0 | V95: 20 | W95: 20 | X95: 0 | Y95: 20 | Z95: 20 | AA95: 0 | AB95: 20 | AC95: 20 | AD95: 0 | AE95: 20 | AF95: 20 | AG95: 0 | AH95: 20 | AI95: 0 | AJ95: 0 | AK95: 0 | AL95: 0 | AM95: 0 | AN95: 0 | AO95: 0 | AP95: 0 | AQ95: 0 | AR95: 0 | AS95: 0 | AT95: 0
D96: Clothes | E96: 1080 | F96: -1865.7 | G96: =E96+F96 -> -785.7 | H96: 1.202963 | J96: Clothes | K96: 300 | L96: -282 | M96: 18 | N96: 300 | O96: 0 | P96: 300 | Q96: 20 | R96: 0 | S96: 20 | T96: 20 | U96: 0 | V96: 20 | W96: 300 | X96: -537 | Y96: -237 | Z96: 20 | AA96: -121 | AB96: -101 | AC96: 20 | AD96: -200 | AE96: -180 | AF96: 20 | AG96: 0 | AH96: 20 | AI96: 20 | AJ96: 0 | AK96: 20 | AL96: 20 | AM96: -159.2 | AN96: -139.2 | AO96: 20 | AP96: 0 | AQ96: 20 | AR96: 20 | AS96: -566.5 | AT96: -546.5
D97: Utilities | E97: 4200 | F97: -7082.98 | G97: =E97+F97 -> -2882.98 | H97: 1.507381 | J97: Utilities | K97: 400 | L97: -528 | M97: -128 | N97: 400 | O97: -670.18 | P97: -270.18 | Q97: 400 | R97: -699 | S97: -299 | T97: 400 | U97: -651.07 | V97: -251.07 | W97: 400 | X97: -527.14 | Y97: -127.14 | Z97: 400 | AA97: -701 | AB97: -301 | AC97: 400 | AD97: -571 | AE97: -171 | AF97: 400 | AG97: -643.61 | AH97: -243.61 | AI97: 400 | AJ97: -573 | AK97: -173 | AL97: 400 | AM97: -705 | AN97: -305 | AO97: 100 | AP97: -62 | AQ97: 38 | AR97: 100 | AS97: -751.98 | AT97: -651.98
D98: Dining | E98: 10950 | F98: -15350.63 | G98: =E98+F98 -> -4400.63 | H98: 1.3763132 | J98: Dining | K98: 750 | L98: -1631.26 | M98: -881.26 | N98: 750 | O98: -1266.58 | P98: -516.58 | Q98: 1200 | R98: -1620.33 | S98: -420.33 | T98: 1500 | U98: -2063.94 | V98: -563.94 | W98: 1500 | X98: -1394 | Y98: 106 | Z98: 750 | AA98: -1025.99 | AB98: -275.99 | AC98: 750 | AD98: -1380 | AE98: -630 | AF98: 750 | AG98: -1458.03 | AH98: -708.03 | AI98: 750 | AJ98: -1421.66 | AK98: -671.66 | AL98: 750 | AM98: -1566 | AN98: -816 | AO98: 750 | AP98: -322.84 | AQ98: 427.16 | AR98: 750 | AS98: -200 | AT98: 550
D99: Entertainment | E99: 1200 | F99: -2512 | G99: =E99+F99 -> -1312 | H99: 2.0933333 | J99: Entertainment | K99: 100 | L99: -105 | M99: -5 | N99: 100 | O99: -162 | P99: -62 | Q99: 100 | R99: -344 | S99: -244 | T99: 100 | U99: -186 | V99: -86 | W99: 100 | X99: -80 | Y99: 20 | Z99: 100 | AA99: -150 | AB99: -50 | AC99: 100 | AD99: -120 | AE99: -20 | AF99: 100 | AG99: -216 | AH99: -116 | AI99: 100 | AJ99: -766 | AK99: -666 | AL99: 100 | AM99: -383 | AN99: -283 | AO99: 100 | AP99: 0 | AQ99: 100 | AR99: 100 | AS99: 0 | AT99: 100
D100: Gas | E100: 3600 | F100: -2735.74 | G100: =E100+F100 -> 864.26 | H100: 0.64520556 | J100: Gas | K100: 300 | L100: -438.15 | M100: -138.15 | N100: 300 | O100: -143 | P100: 157 | Q100: 300 | R100: -437.33 | S100: -137.33 | T100: 300 | U100: -150 | V100: 150 | W100: 300 | X100: -217 | Y100: 83 | Z100: 300 | AA100: -210 | AB100: 90 | AC100: 300 | AD100: -200 | AE100: 100 | AF100: 300 | AG100: 0 | AH100: 300 | AI100: 300 | AJ100: -188.26 | AK100: 111.74 | AL100: 300 | AM100: -339 | AN100: -39 | AO100: 300 | AP100: 0 | AQ100: 300 | AR100: 300 | AS100: -413 | AT100: -113
D101: Gifts | E101: 1200 | F101: -4085.81 | G101: =E101+F101 -> -2885.81 | H101: 2.4585583 | J101: Gifts | K101: 150 | L101: -333 | M101: -183 | N101: 50 | O101: -223 | P101: -173 | Q101: 50 | R101: -418 | S101: -368 | T101: 200 | U101: 0 | V101: 200 | W101: 50 | X101: -604 | Y101: -554 | Z101: 50 | AA101: -113.14 | AB101: -63.14 | AC101: 200 | AD101: 0 | AE101: 200 | AF101: 50 | AG101: -210.45 | AH101: -160.45 | AI101: 50 | AJ101: -400 | AK101: -350 | AL101: 50 | AM101: -648.68 | AN101: -598.68 | AO101: 50 | AP101: 0 | AQ101: 50 | AR101: 250 | AS101: -1135.54 | AT101: -885.54
D102: Grocery | E102: 6100 | F102: -11091.32 | G102: =E102+F102 -> -4991.32 | H102: 1.6798885 | J102: Grocery | K102: 400 | L102: -1035.25 | M102: -635.25 | N102: 500 | O102: -1557 | P102: -1057 | Q102: 500 | R102: -643 | S102: -143 | T102: 500 | U102: -425 | V102: 75 | W102: 300 | X102: -951.31 | Y102: -651.31 | Z102: 300 | AA102: -388 | AB102: -88 | AC102: 600 | AD102: -679.15 | AE102: -79.15 | AF102: 600 | AG102: -1100.26 | AH102: -500.26 | AI102: 600 | AJ102: -968 | AK102: -368 | AL102: 600 | AM102: -1462.35 | AN102: -862.35 | AO102: 600 | AP102: -1722 | AQ102: -1122 | AR102: 600 | AS102: -160 | AT102: 440
...

Sheet Children
A2: Riley | F2: Caleb
A3: Date | B3: From | C3: Description | D3: Transaction | F3: Date | G3: From | H3: Description | I3: Transaction
A4: 45603 | B4: Grandparents (Yoons) | C4: Dohl Gift | D4: 500 | F4: 46023 | G4: Granparents (Yoons and Kims) | H4: New Year's | I4: 200
A5: 45603 | B5: Granparents (Kims) | C5: Dohl Gift | D5: =3000-1250 -> 1750 | F5: 46090 | G5: Grandparents (Yoons) | H5: 100 Day | I5: 500
A6: 45603 | B6: Danny and Annie Roh | C6: Dohl Gift | D6: 150 | F6: 46090 | G6: Grandparents (Kims) | H6: 100 Day | I6: 500
A7: 45603 | B7: Stephanie and James | C7: Dohl Gift | D7: 100 | F7: 46090 | G7: Janet (Peony's friend) | H7: 100 Day | I7: 200
A8: 45603 | B8: Chaucer and Sarah | C8: Dohl Gift | D8: 100 | F8: 46143 | G8: Appa and Umma | H8: N/A | I8: 500
A9: 45603 | B9: Rina | C9: Dohl Gift | D9: 100
A10: 45603 | B10: Rinas parents | C10: Dohl Gift | D10: 300
A11: 45992 | B11: Grandparents (Yoons) | C11: 2year BDAY | D11: 400
A12: 46023 | B12: Granparents (Yoons and Kims) | C12: New Year's | D12: 200
A13: 46143 | B13: Appa and Umma | C13: N/A | D13: 500
B17: Total | D17: =SUM(D4:D14) -> 4100 | G17: Total | I17: =SUM(I4:I14) -> 1900
D19: =D17+I17 -> 6000

Sheet Dec
D1: Checking | F1: CC | H1: SAVINGS | P1: INVESTMENT | W1: CC
A2: Date | B2: Name | C2: Categorization | D2: PK | E2: Main | F2: Chase | G2: Chase | H2: School | I2: Buy | J2: House | K2: Car | L2: Travel | M2: Child | N2: Gifts | O2: Emergency | P2: E-Home | Q2: BC | R2: Roth IRA | S2: UTMA | T2: KPMG | U2: USAA | V2: 401K | W2: Chase | Y2: Budget to Actual | AD2: Activity
Y3: Category | Z3: Budget | AA3: Actual | AB3: Variance | AD3: Investment Activity
Y4: Cable | Z4: =Summary!AR21 -> 350 | AA4: =SUMIF($C$2:$C$37,Y4,$F$2:$F$37)+SUMIF($C$2:$C$37,Y4,$G$2:$G$37) -> 0 | AB4: =Z4+AA4 -> 350
Y5: Car Insurance | Z5: =Summary!AR22 -> 335 | AA5: =SUMIF($C$2:$C$37,Y5,$F$2:$F$37)+SUMIF($C$2:$C$37,Y5,$G$2:$G$37) -> 0 | AB5: =Z5+AA5 -> 335 | AD5: Invested Amount for month
Y6: Cleaners | Z6: =Summary!AR23 -> 0 | AA6: =SUMIF($C$2:$C$37,Y6,$F$2:$F$37)+SUMIF($C$2:$C$37,Y6,$G$2:$G$37) -> 0 | AB6: =Z6+AA6 -> 0 | AD6: Etrade
Y7: Clothes | Z7: =Summary!AR24 -> 20 | AA7: =SUMIF($C$2:$C$37,Y7,$F$2:$F$37)+SUMIF($C$2:$C$37,Y7,$G$2:$G$37) -> 0 | AB7: =Z7+AA7 -> 20 | AD7: Ecar
Y8: Utilities | Z8: =Summary!AR25 -> 700 | AA8: =SUMIF($C$2:$C$37,Y8,$F$2:$F$37)+SUMIF($C$2:$C$37,Y8,$G$2:$G$37) -> 0 | AB8: =Z8+AA8 -> 700 | AD8: CC
Y9: Dining | Z9: =Summary!AR26 -> 1300 | AA9: =SUMIF($C$2:$C$37,Y9,$F$2:$F$37)+SUMIF($C$2:$C$37,Y9,$G$2:$G$37) -> 0 | AB9: =Z9+AA9 -> 1300 | AD9: LC
Y10: Entertainment | Z10: =Summary!AR27 -> 150 | AA10: =SUMIF($C$2:$C$37,Y10,$F$2:$F$37)+SUMIF($C$2:$C$37,Y10,$G$2:$G$37) -> 0 | AB10: =Z10+AA10 -> 150 | AD10: Roth
Y11: Gas | Z11: =Summary!AR28 -> 200 | AA11: =SUMIF($C$2:$C$37,Y11,$F$2:$F$37)+SUMIF($C$2:$C$37,Y11,$G$2:$G$37) -> 0 | AB11: =Z11+AA11 -> 200 | AD11: 401K
Y12: Gifts | Z12: =Summary!AR29 -> 1000 | AA12: =SUMIF($C$2:$C$37,Y12,$F$2:$F$37)+SUMIF($C$2:$C$37,Y12,$G$2:$G$37) -> 0 | AB12: =Z12+AA12 -> 1000 | AD12: Total | AE12: =SUM(AE6:AE11) -> 0
Y13: Grocery | Z13: =Summary!AR30 -> 1000 | AA13: =SUMIF($C$2:$C$37,Y13,$F$2:$F$37)+SUMIF($C$2:$C$37,Y13,$G$2:$G$37) -> 0 | AB13: =Z13+AA13 -> 1000
Y14: Gym | Z14: =Summary!AR31 -> 200 | AA14: =SUMIF($C$2:$C$37,Y14,$F$2:$F$37)+SUMIF($C$2:$C$37,Y14,$G$2:$G$37) -> 0 | AB14: =Z14+AA14 -> 200 | AD14: Gain/Loss in Investment
Y15: Loan | Z15: =Summary!AR32 -> 0 | AA15: =SUMIF($C$2:$C$37,Y15,$F$2:$F$37)+SUMIF($C$2:$C$37,Y15,$G$2:$G$37) -> 0 | AB15: =Z15+AA15 -> 0 | AD15: Etrade
Y16: Misc | Z16: =Summary!AR33 -> 600 | AA16: =SUMIF($C$2:$C$37,Y16,$F$2:$F$37)+SUMIF($C$2:$C$37,Y16,$G$2:$G$37) -> 0 | AB16: =Z16+AA16 -> 600 | AD16: Ecar
Y17: Offering | Z17: =Summary!AR34 -> 800 | AA17: =SUMIF($C$2:$C$37,Y17,$F$2:$F$37)+SUMIF($C$2:$C$37,Y17,$G$2:$G$37) -> 0 | AB17: =Z17+AA17 -> 800 | AD17: BC
Y18: Rent | Z18: =Summary!AR35 -> 4100 | AA18: =SUMIF($C$2:$C$37,Y18,$F$2:$F$37)+SUMIF($C$2:$C$37,Y18,$G$2:$G$37) -> 0 | AB18: =Z18+AA18 -> 4100 | AD18: LC
Y19: Travel | Z19: =Summary!AR36 -> 176.2 | AA19: =SUMIF($C$2:$C$37,Y19,$F$2:$F$37)+SUMIF($C$2:$C$37,Y19,$G$2:$G$37) -> 0 | AB19: =Z19+AA19 -> 176.2 | AD19: Roth
Y20: Parents | Z20: =Summary!AR37 -> 500 | AA20: =SUMIF($C$2:$C$37,Y20,$F$2:$F$37)+SUMIF($C$2:$C$37,Y20,$G$2:$G$37) -> 0 | AB20: =Z20+AA20 -> 500 | AD20: 401K
Y21: Car | Z21: =Summary!AR38 -> 200 | AA21: =SUMIF($C$2:$C$37,Y21,$F$2:$F$37)+SUMIF($C$2:$C$37,Y21,$G$2:$G$37) -> 0 | AB21: =Z21+AA21 -> 200 | AD21: Chase & Amex
Y22: House | Z22: =Summary!AR39 -> 200 | AA22: =SUMIF($C$2:$C$37,Y22,$F$2:$F$37)+SUMIF($C$2:$C$37,Y22,$G$2:$G$37) -> 0 | AB22: =Z22+AA22 -> 200 | AD22: Total | AE22: =SUM(AE15:AE21) -> 0
Y23: School | Z23: =Summary!AR40 -> 0 | AA23: =SUMIF($C$2:$C$37,Y23,$F$2:$F$37)+SUMIF($C$2:$C$37,Y23,$G$2:$G$37) -> 0 | AB23: =Z23+AA23 -> 0
A39: Balance | D39: =SUM(D3:D38) -> 0 | E39: =SUM(E3:E38) -> 0 | F39: =SUM(F3:F38) -> 0 | G39: =SUM(G3:G38) -> 0 | H39: =SUM(H3:H38) -> 0 | I39: =SUM(I3:I38) -> 0 | J39: =SUM(J3:J38) -> 0 | K39: =SUM(K3:K38) -> 0 | ... W39: =SUM(W3:W38) -> 0 | Y39: Total | Z39: =SUM(Z4:Z37) -> 11831.2 | AA39: =SUM(AA4:AA37) -> 0 | AB39: =SUM(AB4:AB37) -> 11831.2
W44: =SUM(D39:W39) -> 0
Y46: PERCENTAGE
V47: Total Savings | W47: =SUM(H39:O39) -> 0 | Y47: =W47/W50 -> #DIV/0!
V48: Total Investments | W48: =SUM(P39:W39) -> 0 | Y48: =W48/W50 -> #DIV/0!
V49: Total Checking | W49: =E39+D39 -> 0 | Y49: =W49/W50 -> #DIV/0!
V50: TOTAL | W50: =SUM(W47:W49) -> 0
W52: =W50-W44 -> 0

Sheet Nov
D1: Checking | F1: CC | H1: SAVINGS | P1: INVESTMENT | W1: CC
A2: Date | B2: Name | C2: Categorization | D2: PK | E2: Main | F2: Chase | G2: Chase | H2: School | I2: Buy | J2: House | K2: Car | L2: Travel | M2: Child | N2: Gifts | O2: Emergency | P2: E-Home | Q2: BC | R2: Roth IRA | S2: UTMA | T2: KPMG | U2: USAA | V2: 401K | W2: Chase | Y2: Budget to Actual | AD2: Activity
Y3: Category | Z3: Budget | AA3: Actual | AB3: Variance | AD3: Investment Activity
Y4: Cable | Z4: =Summary!AO21 -> 350 | AA4: =SUMIF($C$2:$C$34,Y4,$F$2:$F$34)+SUMIF($C$2:$C$34,Y4,$G$2:$G$34) -> 0 | AB4: =Z4+AA4 -> 350
Y5: Car Insurance | Z5: =Summary!AO22 -> 335 | AA5: =SUMIF($C$2:$C$34,Y5,$F$2:$F$34)+SUMIF($C$2:$C$34,Y5,$G$2:$G$34) -> 0 | AB5: =Z5+AA5 -> 335 | AD5: Invested Amount for month
Y6: Cleaners | Z6: =Summary!AO23 -> 0 | AA6: =SUMIF($C$2:$C$34,Y6,$F$2:$F$34)+SUMIF($C$2:$C$34,Y6,$G$2:$G$34) -> 0 | AB6: =Z6+AA6 -> 0 | AD6: Etrade
Y7: Clothes | Z7: =Summary!AO24 -> 20 | AA7: =SUMIF($C$2:$C$34,Y7,$F$2:$F$34)+SUMIF($C$2:$C$34,Y7,$G$2:$G$34) -> 0 | AB7: =Z7+AA7 -> 20 | AD7: Ecar
Y8: Utilities | Z8: =Summary!AO25 -> 700 | AA8: =SUMIF($C$2:$C$34,Y8,$F$2:$F$34)+SUMIF($C$2:$C$34,Y8,$G$2:$G$34) -> 0 | AB8: =Z8+AA8 -> 700 | AD8: CC
Y9: Dining | Z9: =Summary!AO26 -> 1300 | AA9: =SUMIF($C$2:$C$34,Y9,$F$2:$F$34)+SUMIF($C$2:$C$34,Y9,$G$2:$G$34) -> 0 | AB9: =Z9+AA9 -> 1300 | AD9: LC
Y10: Entertainment | Z10: =Summary!AO27 -> 150 | AA10: =SUMIF($C$2:$C$34,Y10,$F$2:$F$34)+SUMIF($C$2:$C$34,Y10,$G$2:$G$34) -> 0 | AB10: =Z10+AA10 -> 150 | AD10: Roth
Y11: Gas | Z11: =Summary!AO28 -> 200 | AA11: =SUMIF($C$2:$C$34,Y11,$F$2:$F$34)+SUMIF($C$2:$C$34,Y11,$G$2:$G$34) -> 0 | AB11: =Z11+AA11 -> 200 | AD11: 401K
Y12: Gifts | Z12: =Summary!AO29 -> 500 | AA12: =SUMIF($C$2:$C$34,Y12,$F$2:$F$34)+SUMIF($C$2:$C$34,Y12,$G$2:$G$34) -> 0 | AB12: =Z12+AA12 -> 500 | AD12: Total | AE12: =SUM(AE6:AE11) -> 0
Y13: Grocery | Z13: =Summary!AO30 -> 1000 | AA13: =SUMIF($C$2:$C$34,Y13,$F$2:$F$34)+SUMIF($C$2:$C$34,Y13,$G$2:$G$34) -> 0 | AB13: =Z13+AA13 -> 1000
Y14: Gym | Z14: =Summary!AO31 -> 200 | AA14: =SUMIF($C$2:$C$34,Y14,$F$2:$F$34)+SUMIF($C$2:$C$34,Y14,$G$2:$G$34) -> 0 | AB14: =Z14+AA14 -> 200 | AD14: Gain/Loss in Investment
Y15: Loan | Z15: =Summary!AO32 -> 0 | AA15: =SUMIF($C$2:$C$34,Y15,$F$2:$F$34)+SUMIF($C$2:$C$34,Y15,$G$2:$G$34) -> 0 | AB15: =Z15+AA15 -> 0 | AD15: Etrade
Y16: Misc | Z16: =Summary!AO33 -> 500 | AA16: =SUMIF($C$2:$C$34,Y16,$F$2:$F$34)+SUMIF($C$2:$C$34,Y16,$G$2:$G$34) -> 0 | AB16: =Z16+AA16 -> 500 | AD16: Ecar
Y17: Offering | Z17: =Summary!AO34 -> 800 | AA17: =SUMIF($C$2:$C$34,Y17,$F$2:$F$34)+SUMIF($C$2:$C$34,Y17,$G$2:$G$34) -> 0 | AB17: =Z17+AA17 -> 800 | AD17: BC
Y18: Rent | Z18: =Summary!AO35 -> 4100 | AA18: =SUMIF($C$2:$C$34,Y18,$F$2:$F$34)+SUMIF($C$2:$C$34,Y18,$G$2:$G$34) -> 0 | AB18: =Z18+AA18 -> 4100 | AD18: LC
Y19: Travel | Z19: =Summary!AO36 -> 176.2 | AA19: =SUMIF($C$2:$C$34,Y19,$F$2:$F$34)+SUMIF($C$2:$C$34,Y19,$G$2:$G$34) -> 0 | AB19: =Z19+AA19 -> 176.2 | AD19: Roth
Y20: Parents | Z20: =Summary!AO37 -> 500 | AA20: =SUMIF($C$2:$C$34,Y20,$F$2:$F$34)+SUMIF($C$2:$C$34,Y20,$G$2:$G$34) -> 0 | AB20: =Z20+AA20 -> 500 | AD20: 401K
Y21: Car | Z21: =Summary!AO38 -> 200 | AA21: =SUMIF($C$2:$C$34,Y21,$F$2:$F$34)+SUMIF($C$2:$C$34,Y21,$G$2:$G$34) -> 0 | AB21: =Z21+AA21 -> 200 | AD21: Chase & Amex | AE21: =SUM(W35:W35) -> 0
Y22: House | Z22: =Summary!AO39 -> 200 | AA22: =SUMIF($C$2:$C$34,Y22,$F$2:$F$34)+SUMIF($C$2:$C$34,Y22,$G$2:$G$34) -> 0 | AB22: =Z22+AA22 -> 200 | AD22: Total | AE22: =SUM(AE15:AE21) -> 0
Y23: School | Z23: =Summary!AO40 -> 0 | AA23: =SUMIF($C$2:$C$34,Y23,$F$2:$F$34)+SUMIF($C$2:$C$34,Y23,$G$2:$G$34) -> 0 | AB23: =Z23+AA23 -> 0
Y24: Baby Sitter | Z24: =Summary!AR41 -> 800 | AA24: =SUMIF($C$2:$C$34,Y24,$F$2:$F$34)+SUMIF($C$2:$C$34,Y24,$G$2:$G$34) -> 0 | AB24: =Z24+AA24 -> 800
A36: Balance | D36: =SUM(D3:D35) -> 0 | E36: =SUM(E3:E35) -> 0 | F36: =SUM(F3:F35) -> 0 | G36: =SUM(G3:G35) -> 0 | H36: =SUM(H3:H35) -> 0 | I36: =SUM(I3:I35) -> 0 | J36: =SUM(J3:J35) -> 0 | K36: =SUM(K3:K35) -> 0 | ... W36: =SUM(W3:W35) -> 0 | Y36: Total | Z36: =SUM(Z4:Z34) -> 12031.2 | AA36: =SUM(AA4:AA34) -> 0 | AB36: =SUM(AB4:AB34) -> 12031.2
W41: =SUM(D36:W36) -> 0
Y43: PERCENTAGE
V44: Total Savings | W44: =SUM(H36:O36) -> 0 | Y44: =W44/W47 -> #DIV/0!
V45: Total Investments | W45: =SUM(P36:W36) -> 0 | Y45: =W45/W47 -> #DIV/0!
V46: Total Checking | W46: =E36+D36 -> 0 | Y46: =W46/W47 -> #DIV/0!
V47: TOTAL | W47: =SUM(W44:W46) -> 0
W49: =W47-W41 -> 0

Sheet Oct
D1: Checking | F1: CC | H1: SAVINGS | P1: INVESTMENT | W1: CC
A2: Date | B2: Name | C2: Categorization | D2: PK | E2: Main | F2: Chase | G2: Chase | H2: School | I2: Buy | J2: House | K2: Car | L2: Travel | M2: Child | N2: Gifts | O2: Emergency | P2: E-Home | Q2: BC | R2: Roth IRA | S2: UTMA | T2: KPMG | U2: USAA | V2: 401K | W2: Chase | Y2: Budget to Actual | AD2: Activity
Y3: Category | Z3: Budget | AA3: Actual | AB3: Variance | AD3: Investment Activity
Y4: Cable | Z4: =Summary!AL21 -> 350 | AA4: =SUMIF($C$2:$C$46,Y4,$F$2:$F$46)+SUMIF($C$2:$C$46,Y4,$G$2:$G$46) -> 0 | AB4: =Z4+AA4 -> 350
Y5: Car Insurance | Z5: =Summary!AL22 -> 335 | AA5: =SUMIF($C$2:$C$46,Y5,$F$2:$F$46)+SUMIF($C$2:$C$46,Y5,$G$2:$G$46) -> 0 | AB5: =Z5+AA5 -> 335 | AD5: Invested Amount for month
Y6: Cleaners | Z6: =Summary!AL23 -> 0 | AA6: =SUMIF($C$2:$C$46,Y6,$F$2:$F$46)+SUMIF($C$2:$C$46,Y6,$G$2:$G$46) -> 0 | AB6: =Z6+AA6 -> 0 | AD6: Etrade
Y7: Clothes | Z7: =Summary!AL24 -> 20 | AA7: =SUMIF($C$2:$C$46,Y7,$F$2:$F$46)+SUMIF($C$2:$C$46,Y7,$G$2:$G$46) -> 0 | AB7: =Z7+AA7 -> 20 | AD7: Ecar
Y8: Utilities | Z8: =Summary!AL25 -> 700 | AA8: =SUMIF($C$2:$C$46,Y8,$F$2:$F$46)+SUMIF($C$2:$C$46,Y8,$G$2:$G$46) -> 0 | AB8: =Z8+AA8 -> 700 | AD8: CC
Y9: Dining | Z9: =Summary!AL26 -> 1300 | AA9: =SUMIF($C$2:$C$46,Y9,$F$2:$F$46)+SUMIF($C$2:$C$46,Y9,$G$2:$G$46) -> 0 | AB9: =Z9+AA9 -> 1300 | AD9: LC
Y10: Entertainment | Z10: =Summary!AL27 -> 150 | AA10: =SUMIF($C$2:$C$46,Y10,$F$2:$F$46)+SUMIF($C$2:$C$46,Y10,$G$2:$G$46) -> 0 | AB10: =Z10+AA10 -> 150 | AD10: Roth
Y11: Gas | Z11: =Summary!AL28 -> 200 | AA11: =SUMIF($C$2:$C$46,Y11,$F$2:$F$46)+SUMIF($C$2:$C$46,Y11,$G$2:$G$46) -> 0 | AB11: =Z11+AA11 -> 200 | AD11: 401K
Y12: Gifts | Z12: =Summary!AL29 -> 50 | AA12: =SUMIF($C$2:$C$46,Y12,$F$2:$F$46)+SUMIF($C$2:$C$46,Y12,$G$2:$G$46) -> 0 | AB12: =Z12+AA12 -> 50 | AD12: Total | AE12: =SUM(AE6:AE11) -> 0
Y13: Grocery | Z13: =Summary!AL30 -> 1000 | AA13: =SUMIF($C$2:$C$46,Y13,$F$2:$F$46)+SUMIF($C$2:$C$46,Y13,$G$2:$G$46) -> 0 | AB13: =Z13+AA13 -> 1000
Y14: Gym | Z14: =Summary!AL31 -> 200 | AA14: =SUMIF($C$2:$C$46,Y14,$F$2:$F$46)+SUMIF($C$2:$C$46,Y14,$G$2:$G$46) -> 0 | AB14: =Z14+AA14 -> 200 | AD14: Gain/Loss in Investment
Y15: Loan | Z15: =Summary!AL32 -> 0 | AA15: =SUMIF($C$2:$C$46,Y15,$F$2:$F$46)+SUMIF($C$2:$C$46,Y15,$G$2:$G$46) -> 0 | AB15: =Z15+AA15 -> 0 | AD15: Etrade
Y16: Misc | Z16: =Summary!AL33 -> 500 | AA16: =SUMIF($C$2:$C$46,Y16,$F$2:$F$46)+SUMIF($C$2:$C$46,Y16,$G$2:$G$46) -> 0 | AB16: =Z16+AA16 -> 500 | AD16: Ecar
Y17: Offering | Z17: =Summary!AL34 -> 800 | AA17: =SUMIF($C$2:$C$46,Y17,$F$2:$F$46)+SUMIF($C$2:$C$46,Y17,$G$2:$G$46) -> 0 | AB17: =Z17+AA17 -> 800 | AD17: BC
Y18: Rent | Z18: =Summary!AL35 -> 4100 | AA18: =SUMIF($C$2:$C$46,Y18,$F$2:$F$46)+SUMIF($C$2:$C$46,Y18,$G$2:$G$46) -> 0 | AB18: =Z18+AA18 -> 4100 | AD18: LC
Y19: Travel | Z19: =Summary!AL36 -> 176.2 | AA19: =SUMIF($C$2:$C$46,Y19,$F$2:$F$46)+SUMIF($C$2:$C$46,Y19,$G$2:$G$46) -> 0 | AB19: =Z19+AA19 -> 176.2 | AD19: Roth
Y20: Parents | Z20: =Summary!AL37 -> 500 | AA20: =SUMIF($C$2:$C$46,Y20,$F$2:$F$46)+SUMIF($C$2:$C$46,Y20,$G$2:$G$46) -> 0 | AB20: =Z20+AA20 -> 500 | AD20: 401K
Y21: Car | Z21: =Summary!AL38 -> 0 | AA21: =SUMIF($C$2:$C$46,Y21,$F$2:$F$46)+SUMIF($C$2:$C$46,Y21,$G$2:$G$46) -> 0 | AB21: =Z21+AA21 -> 0 | AD21: Chase & Amex
Y22: House | Z22: =Summary!AL39 -> 200 | AA22: =SUMIF($C$2:$C$46,Y22,$F$2:$F$46)+SUMIF($C$2:$C$46,Y22,$G$2:$G$46) -> 0 | AB22: =Z22+AA22 -> 200 | AD22: Total | AE22: =SUM(AE15:AE21) -> 0
Y23: School | Z23: =Summary!AL40 -> 0 | AA23: =SUMIF($C$2:$C$46,Y23,$F$2:$F$46)+SUMIF($C$2:$C$46,Y23,$G$2:$G$46) -> 0 | AB23: =Z23+AA23 -> 0
A48: Balance | D48: =SUM(D3:D47) -> 0 | E48: =SUM(E3:E47) -> 0 | F48: =SUM(F3:F47) -> 0 | G48: =SUM(G3:G47) -> 0 | H48: =SUM(H3:H47) -> 0 | I48: =SUM(I3:I47) -> 0 | J48: =SUM(J3:J47) -> 0 | K48: =SUM(K3:K47) -> 0 | ... V48: =SUM(V3:V47) -> 0 | Y48: Total | Z48: =SUM(Z4:Z46) -> 10581.2 | AA48: =SUM(AA4:AA46) -> 0 | AB48: =SUM(AB4:AB46) -> 10581.2
W53: =SUM(D48:V48) -> 0
Y55: PERCENTAGE
V56: Total Savings | W56: =SUM(H48:O48) -> 0 | Y56: =W56/W59 -> #DIV/0!
V57: Total Investments | W57: =SUM(P48:V48) -> 0 | Y57: =W57/W59 -> #DIV/0!
V58: Total Checking | W58: =E48+D48 -> 0 | Y58: =W58/W59 -> #DIV/0!
V59: TOTAL | W59: =SUM(W56:W58) -> 0
W61: =W59-W53 -> 0

Sheet Sep
D1: Checking | F1: CC | H1: SAVINGS | P1: INVESTMENT | W1: CC
A2: Date | B2: Name | C2: Categorization | D2: PK | E2: Main | F2: Chase | G2: Chase | H2: School | I2: Buy | J2: House | K2: Car | L2: Travel | M2: Child | N2: Gifts | O2: Emergency | P2: E-Home | Q2: BC | R2: Roth IRA | S2: UTMA | T2: KPMG | U2: USAA | V2: 401K | W2: Chase | Y2: Budget to Actual | AD2: Activity
Y3: Category | Z3: Budget | AA3: Actual | AB3: Variance | AD3: Investment Activity
Y4: Cable | Z4: =Summary!AI21 -> 350 | AA4: =SUMIF($C$2:$C$42,Y4,$F$2:$F$42)+SUMIF($C$2:$C$42,Y4,$G$2:$G$42) -> 0 | AB4: =Z4+AA4 -> 350
Y5: Car Insurance | Z5: =Summary!AI22 -> 335 | AA5: =SUMIF($C$2:$C$42,Y5,$F$2:$F$42)+SUMIF($C$2:$C$42,Y5,$G$2:$G$42) -> 0 | AB5: =Z5+AA5 -> 335 | AD5: Invested Amount for month
Y6: Cleaners | Z6: =Summary!AI23 -> 0 | AA6: =SUMIF($C$2:$C$42,Y6,$F$2:$F$42)+SUMIF($C$2:$C$42,Y6,$G$2:$G$42) -> 0 | AB6: =Z6+AA6 -> 0 | AD6: Etrade
Y7: Clothes | Z7: =Summary!AI24 -> 20 | AA7: =SUMIF($C$2:$C$42,Y7,$F$2:$F$42)+SUMIF($C$2:$C$42,Y7,$G$2:$G$42) -> 0 | AB7: =Z7+AA7 -> 20 | AD7: Ecar
Y8: Utilities | Z8: =Summary!AI25 -> 700 | AA8: =SUMIF($C$2:$C$42,Y8,$F$2:$F$42)+SUMIF($C$2:$C$42,Y8,$G$2:$G$42) -> 0 | AB8: =Z8+AA8 -> 700 | AD8: CC
Y9: Dining | Z9: =Summary!AI26 -> 1300 | AA9: =SUMIF($C$2:$C$42,Y9,$F$2:$F$42)+SUMIF($C$2:$C$42,Y9,$G$2:$G$42) -> 0 | AB9: =Z9+AA9 -> 1300 | AD9: LC
Y10: Entertainment | Z10: =Summary!AI27 -> 150 | AA10: =SUMIF($C$2:$C$42,Y10,$F$2:$F$42)+SUMIF($C$2:$C$42,Y10,$G$2:$G$42) -> 0 | AB10: =Z10+AA10 -> 150 | AD10: Roth
Y11: Gas | Z11: =Summary!AI28 -> 200 | AA11: =SUMIF($C$2:$C$42,Y11,$F$2:$F$42)+SUMIF($C$2:$C$42,Y11,$G$2:$G$42) -> 0 | AB11: =Z11+AA11 -> 200 | AD11: 401K
Y12: Gifts | Z12: =Summary!AI29 -> 50 | AA12: =SUMIF($C$2:$C$42,Y12,$F$2:$F$42)+SUMIF($C$2:$C$42,Y12,$G$2:$G$42) -> 0 | AB12: =Z12+AA12 -> 50 | AD12: Total | AE12: =SUM(AE6:AE11) -> 0
Y13: Grocery | Z13: =Summary!AI30 -> 1000 | AA13: =SUMIF($C$2:$C$42,Y13,$F$2:$F$42)+SUMIF($C$2:$C$42,Y13,$G$2:$G$42) -> 0 | AB13: =Z13+AA13 -> 1000
Y14: Gym | Z14: =Summary!AI31 -> 200 | AA14: =SUMIF($C$2:$C$42,Y14,$F$2:$F$42)+SUMIF($C$2:$C$42,Y14,$G$2:$G$42) -> 0 | AB14: =Z14+AA14 -> 200 | AD14: Gain/Loss in Investment
Y15: Loan | Z15: =Summary!AI32 -> 0 | AA15: =SUMIF($C$2:$C$42,Y15,$F$2:$F$42)+SUMIF($C$2:$C$42,Y15,$G$2:$G$42) -> 0 | AB15: =Z15+AA15 -> 0 | AD15: Etrade
Y16: Misc | Z16: =Summary!AI33 -> 500 | AA16: =SUMIF($C$2:$C$42,Y16,$F$2:$F$42)+SUMIF($C$2:$C$42,Y16,$G$2:$G$42) -> 0 | AB16: =Z16+AA16 -> 500 | AD16: Ecar
Y17: Offering | Z17: =Summary!AI34 -> 800 | AA17: =SUMIF($C$2:$C$42,Y17,$F$2:$F$42)+SUMIF($C$2:$C$42,Y17,$G$2:$G$42) -> 0 | AB17: =Z17+AA17 -> 800 | AD17: BC
Y18: Rent | Z18: =Summary!AI35 -> 4100 | AA18: =SUMIF($C$2:$C$42,Y18,$F$2:$F$42)+SUMIF($C$2:$C$42,Y18,$G$2:$G$42) -> 0 | AB18: =Z18+AA18 -> 4100 | AD18: LC
Y19: Travel | Z19: =Summary!AI36 -> 176.2 | AA19: =SUMIF($C$2:$C$42,Y19,$F$2:$F$42)+SUMIF($C$2:$C$42,Y19,$G$2:$G$42) -> 0 | AB19: =Z19+AA19 -> 176.2 | AD19: Roth
Y20: Parents | Z20: =Summary!AI37 -> 500 | AA20: =SUMIF($C$2:$C$42,Y20,$F$2:$F$42)+SUMIF($C$2:$C$42,Y20,$G$2:$G$42) -> 0 | AB20: =Z20+AA20 -> 500 | AD20: 401K
Y21: Car | Z21: =Summary!AI38 -> 500 | AA21: =SUMIF($C$2:$C$42,Y21,$F$2:$F$42)+SUMIF($C$2:$C$42,Y21,$G$2:$G$42) -> 0 | AB21: =Z21+AA21 -> 500 | AD21: Chase & Amex
Y22: House | Z22: =Summary!AI39 -> 200 | AA22: =SUMIF($C$2:$C$42,Y22,$F$2:$F$42)+SUMIF($C$2:$C$42,Y22,$G$2:$G$42) -> 0 | AB22: =Z22+AA22 -> 200 | AD22: Total | AE22: =SUM(AE15:AE21) -> 0
Y23: School | Z23: =Summary!AI40 -> 0 | AA23: =SUMIF($C$2:$C$42,Y23,$F$2:$F$42)+SUMIF($C$2:$C$42,Y23,$G$2:$G$42) -> 0 | AB23: =Z23+AA23 -> 0
A44: Balance | D44: =SUM(D3:D43) -> 0 | E44: =SUM(E3:E43) -> 0 | F44: =SUM(F3:F43) -> 0 | G44: =SUM(G3:G43) -> 0 | H44: =SUM(H3:H43) -> 0 | I44: =SUM(I3:I43) -> 0 | J44: =SUM(J3:J43) -> 0 | K44: =SUM(K3:K43) -> 0 | ... R44: =SUM(R3:R43) -> 0 | T44: =SUM(T3:T43) -> 0 | U44: =SUM(U3:U43) -> 0 | V44: =SUM(V3:V43) -> 0 | W44: =SUM(W3:W43) -> 0 | Y44: Total | Z44: =SUM(Z4:Z42) -> 11081.2 | AA44: =SUM(AA4:AA42) -> 0 | AB44: =SUM(AB4:AB42) -> 11081.2
W49: =SUM(D44:W44) -> 0
Y51: PERCENTAGE
V52: Total Savings | W52: =SUM(H44:O44) -> 0 | Y52: =W52/W55 -> #DIV/0!
V53: Total Investments | W53: =SUM(P44:W44) -> 0 | Y53: =W53/W55 -> #DIV/0!
V54: Total Checking | W54: =E44+D44 -> 0 | Y54: =W54/W55 -> #DIV/0!
V55: TOTAL | W55: =SUM(W52:W54) -> 0
W57: =W55-W49 -> 0

Sheet Aug
D1: Checking | F1: CC | H1: SAVINGS | P1: INVESTMENT | W1: CC
A2: Date | B2: Name | C2: Categorization | D2: PK | E2: Main | F2: Chase | G2: Chase | H2: School | I2: Buy | J2: House | K2: Car | L2: Travel | M2: Child | N2: Gifts | O2: Emergency | P2: E-Home | Q2: BC | R2: Roth IRA | S2: UTMA | T2: KPMG | U2: USAA | V2: 401K | W2: Chase | Y2: Budget to Actual | AD2: Activity
Y3: Category | Z3: Budget | AA3: Actual | AB3: Variance | AD3: Investment Activity
Y4: Cable | Z4: =Summary!AF21 -> 350 | AA4: =SUMIF($C$2:$C$35,Y4,$F$2:$F$35)+SUMIF($C$2:$C$35,Y4,$G$2:$G$35) -> 0 | AB4: =Z4+AA4 -> 350
Y5: Car Insurance | Z5: =Summary!AF22 -> 335 | AA5: =SUMIF($C$2:$C$35,Y5,$F$2:$F$35)+SUMIF($C$2:$C$35,Y5,$G$2:$G$35) -> 0 | AB5: =Z5+AA5 -> 335 | AD5: Invested Amount for month
Y6: Cleaners | Z6: =Summary!AF23 -> 20 | AA6: =SUMIF($C$2:$C$35,Y6,$F$2:$F$35)+SUMIF($C$2:$C$35,Y6,$G$2:$G$35) -> 0 | AB6: =Z6+AA6 -> 20 | AD6: Etrade
Y7: Clothes | Z7: =Summary!AF24 -> 20 | AA7: =SUMIF($C$2:$C$35,Y7,$F$2:$F$35)+SUMIF($C$2:$C$35,Y7,$G$2:$G$35) -> 0 | AB7: =Z7+AA7 -> 20 | AD7: CC
Y8: Utilities | Z8: =Summary!AF25 -> 700 | AA8: =SUMIF($C$2:$C$35,Y8,$F$2:$F$35)+SUMIF($C$2:$C$35,Y8,$G$2:$G$35) -> 0 | AB8: =Z8+AA8 -> 700 | AD8: Roth
Y9: Dining | Z9: =Summary!AF26 -> 1300 | AA9: =SUMIF($C$2:$C$35,Y9,$F$2:$F$35)+SUMIF($C$2:$C$35,Y9,$G$2:$G$35) -> 0 | AB9: =Z9+AA9 -> 1300 | AD9: 401K
Y10: Entertainment | Z10: =Summary!AF27 -> 150 | AA10: =SUMIF($C$2:$C$35,Y10,$F$2:$F$35)+SUMIF($C$2:$C$35,Y10,$G$2:$G$35) -> 0 | AB10: =Z10+AA10 -> 150 | AD10: Total | AE10: =SUM(AE4:AE9) -> 0
Y11: Gas | Z11: =Summary!AF28 -> 200 | AA11: =SUMIF($C$2:$C$35,Y11,$F$2:$F$35)+SUMIF($C$2:$C$35,Y11,$G$2:$G$35) -> 0 | AB11: =Z11+AA11 -> 200
Y12: Gifts | Z12: =Summary!AF29 -> 50 | AA12: =SUMIF($C$2:$C$35,Y12,$F$2:$F$35)+SUMIF($C$2:$C$35,Y12,$G$2:$G$35) -> 0 | AB12: =Z12+AA12 -> 50
Y13: Grocery | Z13: =Summary!AF30 -> 1000 | AA13: =SUMIF($C$2:$C$35,Y13,$F$2:$F$35)+SUMIF($C$2:$C$35,Y13,$G$2:$G$35) -> 0 | AB13: =Z13+AA13 -> 1000 | AD13: Gain/Loss in Investment
Y14: Gym | Z14: =Summary!AF31 -> 200 | AA14: =SUMIF($C$2:$C$35,Y14,$F$2:$F$35)+SUMIF($C$2:$C$35,Y14,$G$2:$G$35) -> 0 | AB14: =Z14+AA14 -> 200 | AD14: Etrade | AE14: =P35 -> 0
Y15: Loan | Z15: =Summary!AF32 -> 0 | AA15: =SUMIF($C$2:$C$35,Y15,$F$2:$F$35)+SUMIF($C$2:$C$35,Y15,$G$2:$G$35) -> 0 | AB15: =Z15+AA15 -> 0 | AD15: BC | AE15: =Q34 -> 0
Y16: Misc | Z16: =Summary!AF33 -> 500 | AA16: =SUMIF($C$2:$C$35,Y16,$F$2:$F$35)+SUMIF($C$2:$C$35,Y16,$G$2:$G$35) -> 0 | AB16: =Z16+AA16 -> 500 | AD16: Roth | AE16: =R33 -> 0
Y17: Offering | Z17: =Summary!AF34 -> 800 | AA17: =SUMIF($C$2:$C$35,Y17,$F$2:$F$35)+SUMIF($C$2:$C$35,Y17,$G$2:$G$35) -> 0 | AB17: =Z17+AA17 -> 800 | AD17: 401K | AE17: =V33+T33 -> 0
Y18: Rent | Z18: =Summary!AF35 -> 4100 | AA18: =SUMIF($C$2:$C$35,Y18,$F$2:$F$35)+SUMIF($C$2:$C$35,Y18,$G$2:$G$35) -> 0 | AB18: =Z18+AA18 -> 4100 | AD18: Chase & Amex | AE18: =SUM(W33:W33) -> 0
Y19: Travel | Z19: =Summary!AF36 -> 176.2 | AA19: =SUMIF($C$2:$C$35,Y19,$F$2:$F$35)+SUMIF($C$2:$C$35,Y19,$G$2:$G$35) -> 0 | AB19: =Z19+AA19 -> 176.2 | AD19: Total | AE19: =SUM(AE12:AE18) -> 0
Y20: Parents | Z20: =Summary!AF37 -> 500 | AA20: =SUMIF($C$2:$C$35,Y20,$F$2:$F$35)+SUMIF($C$2:$C$35,Y20,$G$2:$G$35) -> 0 | AB20: =Z20+AA20 -> 500
Y21: Car | Z21: =Summary!AF38 -> 523 | AA21: =SUMIF($C$2:$C$35,Y21,$F$2:$F$35)+SUMIF($C$2:$C$35,Y21,$G$2:$G$35) -> 0 | AB21: =Z21+AA21 -> 523
Y22: House | Z22: =Summary!AF39 -> 200 | AA22: =SUMIF($C$2:$C$35,Y22,$F$2:$F$35)+SUMIF($C$2:$C$35,Y22,$G$2:$G$35) -> 0 | AB22: =Z22+AA22 -> 200
Y23: School | Z23: =Summary!AF40 -> 0 | AA23: =SUMIF($C$2:$C$35,Y23,$F$2:$F$35)+SUMIF($C$2:$C$35,Y23,$G$2:$G$35) -> 0 | AB23: =Z23+AA23 -> 0
Y24: Baby Sitter | Z24: =Summary!AF41 -> 900 | AA24: =SUMIF($C$2:$C$35,Y24,$F$2:$F$35)+SUMIF($C$2:$C$35,Y24,$G$2:$G$35) -> 0 | AB24: =Z24+AA24 -> 900
A37: Balance | D37: =SUM(D3:D36) -> 0 | E37: =SUM(E3:E36) -> 0 | F37: =SUM(F3:F36) -> 0 | G37: =SUM(G3:G36) -> 0 | H37: =SUM(H3:H36) -> 0 | I37: =SUM(I3:I36) -> 0 | J37: =SUM(J3:J36) -> 0 | K37: =SUM(K3:K36) -> 0 | ... W37: =SUM(W3:W36) -> 0 | Y37: Total | Z37: =SUM(Z4:Z35) -> 12024.2 | AA37: =SUM(AA4:AA35) -> 0 | AB37: =SUM(AB4:AB35) -> 12024.2
W39: =SUM(D37:W37) -> 0
Y41: PERCENTAGE
V42: Total Savings | W42: =SUM(H37:O37) -> 0 | Y42: =W42/W45 -> #DIV/0!
V43: Total Investments | W43: =SUM(P37:W37) -> 0 | Y43: =W43/W45 -> #DIV/0!
V44: Total Checking | W44: =E37+D37 -> 0 | Y44: =W44/W45 -> #DIV/0!
V45: TOTAL | W45: =SUM(W42:W44) -> 0
W47: =W45-W39 -> 0

Sheet Jul
D1: Checking | F1: CC | H1: SAVINGS | P1: INVESTMENT | W1: CC
A2: Date | B2: Name | C2: Categorization | D2: PK | E2: Main | F2: Chase | G2: Chase | H2: School | I2: Buy | J2: House | K2: Car | L2: Travel | M2: Child | N2: Gifts | O2: Emergency | P2: E-Home | Q2: BC | R2: Roth IRA | S2: UTMA | T2: KPMG | U2: USAA | V2: 401K | W2: Chase | Y2: Budget to Actual | AD2: Activity
Y3: Category | Z3: Budget | AA3: Actual | AB3: Variance | AD3: Investment Activity
Y4: Cable | Z4: =Summary!AC21 -> 350 | AA4: =SUMIF($C$2:$C$43,Y4,$F$2:$F$43)+SUMIF($C$2:$C$43,Y4,$G$2:$G$43) -> 0 | AB4: =Z4+AA4 -> 350
Y5: Car Insurance | Z5: =Summary!AC22 -> 335 | AA5: =SUMIF($C$2:$C$43,Y5,$F$2:$F$43)+SUMIF($C$2:$C$43,Y5,$G$2:$G$43) -> 0 | AB5: =Z5+AA5 -> 335 | AD5: Invested Amount for month
Y6: Cleaners | Z6: =Summary!AC23 -> 20 | AA6: =SUMIF($C$2:$C$43,Y6,$F$2:$F$43)+SUMIF($C$2:$C$43,Y6,$G$2:$G$43) -> 0 | AB6: =Z6+AA6 -> 20 | AD6: Etrade
Y7: Clothes | Z7: =Summary!AC24 -> 20 | AA7: =SUMIF($C$2:$C$43,Y7,$F$2:$F$43)+SUMIF($C$2:$C$43,Y7,$G$2:$G$43) -> 0 | AB7: =Z7+AA7 -> 20 | AD7: CC
Y8: Utilities | Z8: =Summary!AC25 -> 700 | AA8: =SUMIF($C$2:$C$43,Y8,$F$2:$F$43)+SUMIF($C$2:$C$43,Y8,$G$2:$G$43) -> 0 | AB8: =Z8+AA8 -> 700 | AD8: Roth
Y9: Dining | Z9: =Summary!AC26 -> 1300 | AA9: =SUMIF($C$2:$C$43,Y9,$F$2:$F$43)+SUMIF($C$2:$C$43,Y9,$G$2:$G$43) -> 0 | AB9: =Z9+AA9 -> 1300 | AD9: 401K
Y10: Entertainment | Z10: =Summary!AC27 -> 150 | AA10: =SUMIF($C$2:$C$43,Y10,$F$2:$F$43)+SUMIF($C$2:$C$43,Y10,$G$2:$G$43) -> 0 | AB10: =Z10+AA10 -> 150 | AD10: Total | AE10: =SUM(AE4:AE9) -> 0
Y11: Gas | Z11: =Summary!AC28 -> 200 | AA11: =SUMIF($C$2:$C$43,Y11,$F$2:$F$43)+SUMIF($C$2:$C$43,Y11,$G$2:$G$43) -> 0 | AB11: =Z11+AA11 -> 200
Y12: Gifts | Z12: =Summary!AC29 -> 200 | AA12: =SUMIF($C$2:$C$43,Y12,$F$2:$F$43)+SUMIF($C$2:$C$43,Y12,$G$2:$G$43) -> 0 | AB12: =Z12+AA12 -> 200
Y13: Grocery | Z13: =Summary!AC30 -> 1000 | AA13: =SUMIF($C$2:$C$43,Y13,$F$2:$F$43)+SUMIF($C$2:$C$43,Y13,$G$2:$G$43) -> 0 | AB13: =Z13+AA13 -> 1000
Y14: Gym | Z14: =Summary!AC31 -> 200 | AA14: =SUMIF($C$2:$C$43,Y14,$F$2:$F$43)+SUMIF($C$2:$C$43,Y14,$G$2:$G$43) -> 0 | AB14: =Z14+AA14 -> 200 | AD14: Gain/Loss in Investment
Y15: Loan | Z15: =Summary!AC32 -> 0 | AA15: =SUMIF($C$2:$C$43,Y15,$F$2:$F$43)+SUMIF($C$2:$C$43,Y15,$G$2:$G$43) -> 0 | AB15: =Z15+AA15 -> 0 | AD15: Etrade
Y16: Misc | Z16: =Summary!AC33 -> 500 | AA16: =SUMIF($C$2:$C$43,Y16,$F$2:$F$43)+SUMIF($C$2:$C$43,Y16,$G$2:$G$43) -> 0 | AB16: =Z16+AA16 -> 500 | AD16: BC
Y17: Offering | Z17: =Summary!AC34 -> 800 | AA17: =SUMIF($C$2:$C$43,Y17,$F$2:$F$43)+SUMIF($C$2:$C$43,Y17,$G$2:$G$43) -> 0 | AB17: =Z17+AA17 -> 800 | AD17: Roth
Y18: Rent | Z18: =Summary!AC35 -> 4100 | AA18: =SUMIF($C$2:$C$43,Y18,$F$2:$F$43)+SUMIF($C$2:$C$43,Y18,$G$2:$G$43) -> 0 | AB18: =Z18+AA18 -> 4100 | AD18: 401K
Y19: Travel | Z19: =Summary!AC36 -> 2000 | AA19: =SUMIF($C$2:$C$43,Y19,$F$2:$F$43)+SUMIF($C$2:$C$43,Y19,$G$2:$G$43) -> 0 | AB19: =Z19+AA19 -> 2000 | AD19: Chase & Amex
Y20: Parents | Z20: =Summary!AC37 -> 500 | AA20: =SUMIF($C$2:$C$43,Y20,$F$2:$F$43)+SUMIF($C$2:$C$43,Y20,$G$2:$G$43) -> 0 | AB20: =Z20+AA20 -> 500 | AD20: Total | AE20: =SUM(AE13:AE19) -> 0
Y21: Car | Z21: =Summary!AC38 -> 500 | AA21: =SUMIF($C$2:$C$43,Y21,$F$2:$F$43)+SUMIF($C$2:$C$43,Y21,$G$2:$G$43) -> 0 | AB21: =Z21+AA21 -> 500
Y22: House | Z22: =Summary!AC39 -> 1000 | AA22: =SUMIF($C$2:$C$43,Y22,$F$2:$F$43)+SUMIF($C$2:$C$43,Y22,$G$2:$G$43) -> 0 | AB22: =Z22+AA22 -> 1000
Y23: School | Z23: =Summary!AC40 -> 0 | AA23: =SUMIF($C$2:$C$43,Y23,$F$2:$F$43)+SUMIF($C$2:$C$43,Y23,$G$2:$G$43) -> 0 | AB23: =Z23+AA23 -> 0
Y24: Baby Sitter | Z24: =Summary!AC41 -> 800 | AA24: =SUMIF($C$2:$C$43,Y24,$F$2:$F$43)+SUMIF($C$2:$C$43,Y24,$G$2:$G$43) -> 0 | AB24: =Z24+AA24 -> 800
A42: Balance | D42: =SUM(D3:D41) -> 0 | E42: =SUM(E3:E41) -> 0 | F42: =SUM(F3:F41) -> 0 | G42: =SUM(G3:G41) -> 0 | H42: =SUM(H3:H41) -> 0 | I42: =SUM(I3:I41) -> 0 | J42: =SUM(J3:J41) -> 0 | K42: =SUM(K3:K41) -> 0 | ... W42: =SUM(W3:W41) -> 0 | Y42: =SUM(Y3:Y41) -> 0 | Z42: =SUM(Z3:Z41) -> 14675 | AA42: =SUM(AA3:AA41) -> 0 | AB42: =SUM(AB3:AB41) -> 14675
W46: =SUM(D44:W44) -> 0
Y48: PERCENTAGE
V49: Total Savings | W49: =SUM(H44:O44) -> 0 | Y49: =W49/W52 -> #DIV/0!
V50: Total Investments | W50: =SUM(P44:W44) -> 0 | Y50: =W50/W52 -> #DIV/0!
V51: Total Checking | W51: =E44+D44 -> 0 | Y51: =W51/W52 -> #DIV/0!
V52: TOTAL | W52: =SUM(W49:W51) -> 0
W54: =W52-W46 -> 0

Sheet Jun 
D1: Checking | F1: CC | H1: SAVINGS | P1: INVESTMENT | W1: CC
A2: Date | B2: Name | C2: Categorization | D2: PK | E2: Main | F2: Chase | G2: Chase | H2: School | I2: Buy | J2: House | K2: Car | L2: Travel | M2: Child | N2: Gifts | O2: Emergency | P2: E-Home | Q2: BC | R2: Roth IRA | S2: UTMA | T2: KPMG | U2: USAA | V2: 401K | W2: Chase | Y2: Budget to Actual | AD2: Activity
D3: 2000 | E3: 9500 | F3: 0 | G3: 0 | H3: 8939.08 | I3: 52071.91 | J3: 153868 | K3: 60778.68 | L3: 26245.91 | M3: 32000.37 | N3: 4000 | O3: 33572.5 | P3: 213589 | Q3: 132109 | R3: 71894 | S3: 7120 | T3: 33181 | U3: 27298 | V3: 256497 | W3: 4028.92 | Y3: Category | Z3: Budget | AA3: Actual | AB3: Variance | AD3: Investment Activity
A4: 46174 | B4: Mortgage | C4: Rent | E4: -3688 | I4: 473.52 | J4: 1000 | Y4: Cable | Z4: =Summary!Z21 -> 350 | AA4: =SUMIF($C$2:$C$43,Y4,$F$2:$F$43)+SUMIF($C$2:$C$43,Y4,$G$2:$G$43) -> -75 | AB4: =Z4+AA4 -> 275
A5: 46174 | B5: Utilities HOA | C5: Utilities | E5: -275 | Y5: Car Insurance | Z5: =Summary!Z22 -> 335 | AA5: =SUMIF($C$2:$C$43,Y5,$F$2:$F$43)+SUMIF($C$2:$C$43,Y5,$G$2:$G$43) -> 0 | AB5: =Z5+AA5 -> 335 | AD5: Invested Amount for month
A6: 46174 | B6: Parents | C6: Parents | E6: -500 | Y6: Cleaners | Z6: =Summary!Z23 -> 20 | AA6: =SUMIF($C$2:$C$43,Y6,$F$2:$F$43)+SUMIF($C$2:$C$43,Y6,$G$2:$G$43) -> 0 | AB6: =Z6+AA6 -> 20 | AD6: Etrade
A7: 46174 | B7: Rent | C7: Rent | E7: -4250 | Y7: Clothes | Z7: =Summary!Z24 -> 20 | AA7: =SUMIF($C$2:$C$43,Y7,$F$2:$F$43)+SUMIF($C$2:$C$43,Y7,$G$2:$G$43) -> -73.19 | AB7: =Z7+AA7 -> -53.19 | AD7: CC
A8: 46174 | B8: Rent | C8: Rent | E8: 3800 | Y8: Utilities | Z8: =Summary!Z25 -> 700 | AA8: =SUMIF($C$2:$C$43,Y8,$F$2:$F$43)+SUMIF($C$2:$C$43,Y8,$G$2:$G$43)+E5 -> -275 | AB8: =Z8+AA8 -> 425 | AD8: Roth
A9: 46174 | B9: Baby Sitter | C9: Baby SItter | E9: -880 | F9: -36 | Y9: Dining | Z9: =Summary!Z26 -> 1300 | AA9: =SUMIF($C$2:$C$43,Y9,$F$2:$F$43)+SUMIF($C$2:$C$43,Y9,$G$2:$G$43) -> -475 | AB9: =Z9+AA9 -> 825 | AD9: 401K
A10: 46174 | B10: Offering - Radiance | C10: Offering | F10: -50 | Y10: Entertainment | Z10: =Summary!Z27 -> 150 | AA10: =SUMIF($C$2:$C$43,Y10,$F$2:$F$43)+SUMIF($C$2:$C$43,Y10,$G$2:$G$43) -> 0 | AB10: =Z10+AA10 -> 150 | AD10: Total | AE10: =SUM(AE6:AE9) -> 0
A11: 46174 | B11: Offering - Tithly | C11: Offering | F11: -306 | Y11: Gas | Z11: =Summary!Z28 -> 200 | AA11: =SUMIF($C$2:$C$43,Y11,$F$2:$F$43)+SUMIF($C$2:$C$43,Y11,$G$2:$G$43) -> -113 | AB11: =Z11+AA11 -> 87
A12: 46174 | B12: Grocery | C12: Grocery | F12: =-14-4-8-0.47-6.48 -> -32.95 | G12: =-121-62-62 -> -245 | Y12: Gifts | Z12: =Summary!Z29 -> 500 | AA12: =SUMIF($C$2:$C$43,Y12,$F$2:$F$43)+SUMIF($C$2:$C$43,Y12,$G$2:$G$43) -> 0 | AB12: =Z12+AA12 -> 500 | AD12: Gain/Loss in Investment
A13: 46174 | B13: Offering - Serge | C13: Offering | F13: -50 | Y13: Grocery | Z13: =Summary!Z30 -> 1000 | AA13: =SUMIF($C$2:$C$43,Y13,$F$2:$F$43)+SUMIF($C$2:$C$43,Y13,$G$2:$G$43) -> -277.95 | AB13: =Z13+AA13 -> 722.05 | AD13: Etrade | AE13: =P44 -> 0
A14: 46174 | B14: Gas | C14: Gas | G14: -113 | Y14: Gym | Z14: =Summary!Z31 -> 200 | AA14: =SUMIF($C$2:$C$43,Y14,$F$2:$F$43)+SUMIF($C$2:$C$43,Y14,$G$2:$G$43) -> 0 | AB14: =Z14+AA14 -> 200 | AD14: BC | AE14: =Q44 -> 0
A15: 46176 | B15: Dining | C15: Dining | F15: =-34-65-80 -> -179 | G15: =-40-16-14-37-80-61-10-38 -> -296 | Y15: Loan | Z15: =Summary!Z32 -> 0 | AA15: =SUMIF($C$2:$C$43,Y15,$F$2:$F$43)+SUMIF($C$2:$C$43,Y15,$G$2:$G$43) -> 0 | AB15: =Z15+AA15 -> 0 | AD15: Roth | AE15: =R44 -> 0
A16: 46176 | B16: Clothes | C16: Clothes | G16: =-58.19-15 -> -73.19 | Y16: Misc | Z16: =Summary!Z33 -> 500 | AA16: =SUMIF($C$2:$C$43,Y16,$F$2:$F$43)+SUMIF($C$2:$C$43,Y16,$G$2:$G$43) -> -80 | AB16: =Z16+AA16 -> 420 | AD16: 401K | AE16: =V44+T44 -> 0
A17: 46177 | B17: Cable - WSJ | C17: Cable | F17: -8 | Y17: Offering | Z17: =Summary!Z34 -> 800 | AA17: =SUMIF($C$2:$C$43,Y17,$F$2:$F$43)+SUMIF($C$2:$C$43,Y17,$G$2:$G$43)+E19 -> -456 | AB17: =Z17+AA17 -> 344 | AD17: Chase & Amex | AE17: =SUM(W44:W44) -> 0
A18: 46178 | B18: House | C18: House | E18: -100 | F18: -35 | Y18: Rent | Z18: =Summary!Z35 -> 4100 | AA18: =SUMIF($C$2:$C$43,Y18,$F$2:$F$43)+SUMIF($C$2:$C$43,Y18,$G$2:$G$43)+E4+E7+E8 -> -4138 | AB18: =Z18+AA18 -> -38 | AD18: Total | AE18: =SUM(AE13:AE17) -> 0
A19: 46181 | B19: Offering - Crosspoint | C19: Offering | E19: -50 | Y19: Travel | Z19: =Summary!Z36 -> 500 | AA19: =SUMIF($C$2:$C$43,Y19,$F$2:$F$43)+SUMIF($C$2:$C$43,Y19,$G$2:$G$43) -> 0 | AB19: =Z19+AA19 -> 500
A20: 46181 | B20: Misc | C20: Misc | F20: -80 | Y20: Parents | Z20: =Summary!Z37 -> 500 | AA20: =SUMIF($C$2:$C$43,Y20,$F$2:$F$43)+SUMIF($C$2:$C$43,Y20,$G$2:$G$43)+E6 -> -500 | AB20: =Z20+AA20 -> 0
A21: 46181 | B21: Cable - Netflix | C21: Cable | F21: -47 | Y21: Car | Z21: =Summary!Z38 -> 500 | AA21: =SUMIF($C$2:$C$43,Y21,$F$2:$F$43)+SUMIF($C$2:$C$43,Y21,$G$2:$G$43) -> 0 | AB21: =Z21+AA21 -> 500
A22: 46181 | B22: Cable - Claude | C22: Cable | F22: -20 | Y22: House | Z22: =Summary!Z39 -> 200 | AA22: =SUMIF($C$2:$C$43,Y22,$F$2:$F$43)+SUMIF($C$2:$C$43,Y22,$G$2:$G$43) -> -35 | AB22: =Z22+AA22 -> 165
A23: 46181 | Y23: School | Z23: =Summary!Z40 -> 0 | AA23: =SUMIF($C$2:$C$43,Y23,$F$2:$F$43)+SUMIF($C$2:$C$43,Y23,$G$2:$G$43) -> 0 | AB23: =Z23+AA23 -> 0
Y24: Baby Sitter | Z24: =Summary!Z41 -> 900 | AA24: =SUMIF($C$2:$C$43,Y24,$F$2:$F$43)+SUMIF($C$2:$C$43,Y24,$G$2:$G$43) -> -36 | AB24: =Z24+AA24 -> 864
A42: 46203 | B42: Savings | C42: Savings | E42: -25 | I42: 25
A43: 46203 | B43: Payment | C43: Payment | E43: =-SUM(F43:G43) -> -1571.14 | F43: =-SUM(F4:F42) -> 843.95 | G43: =-SUM(G4:G42) -> 727.19
E44: =9600-SUM(E3:E43) -> 7639.14 | I44: =-E44 -> -7639.14
A45: Balance | D45: =SUM(D3:D44) -> 2000 | E45: =SUM(E3:E44) -> 9600 | F45: =SUM(F3:F44) -> 0 | G45: =SUM(G3:G44) -> 0 | H45: =SUM(H3:H44) -> 8939.08 | I45: =SUM(I3:I44) -> 44931.29 | J45: =SUM(J3:J44) -> 154868 | K45: =SUM(K3:K44) -> 60778.68 | ... W45: =SUM(W3:W44) -> 4028.92 | Y45: Total | Z45: =SUM(Z4:Z43) -> 12775 | AA45: =SUM(AA4:AA43) -> -6534.14 | AB45: =SUM(AB4:AB43) -> 6240.86
P46: =SUM(P47:P48) -> -203256 | Q46: -89400 | R46: -71894 | S46: -7120 | V46: =SUM(V47:V48) -> -256497
P47: -192829 | V47: -57802 | W47: =SUM(D45:W45) -> 1122652.8
F48: Reserve | G48: 601 | P48: -10427 | V48: -198695
F49: Pending | G49: 235 | O49: Loss / (Gain) | P49: =SUM(P45:S46)+SUM(V45:V46) -> 53042 | Y49: PERCENTAGE
F50: Total | G50: =SUM(G48:G49) -> 836 | V50: Total Savings | W50: =SUM(H45:O45) -> 365335.83 | Y50: =W50/W53 -> 0.32542193
V51: Total Investments | W51: =SUM(P45:W45) -> 745716.92 | Y51: =W51/W53 -> 0.6642454
F52: Freedom | G52: 633 | V52: Total Checking | W52: =E45+D45 -> 11600 | Y52: =W52/W53 -> 0.01033267
F53: Pending | G53: 108 | V53: TOTAL | W53: =SUM(W50:W52) -> 1122652.8
F54: Total | G54: =SUM(G52:G53) -> 741
W55: =W53-W47 -> 0
V56: Mkt Value | W56: 800000
V57: Liability | W57: -629882.18
V58: Equity | W58: =W56+W57 -> 170117.82
V60: Mkt Value | W60: 400000
V61: Liability | W61: -300000
V62: Equity | W62: =W60+W61 -> 100000
V64: NetWorth | W64: =W58+W53 -> 1292770.6

Sheet May 
D1: Checking | F1: CC | H1: SAVINGS | P1: INVESTMENT | W1: CC
A2: Date | B2: Name | C2: Categorization | D2: PK | E2: Main | F2: Reserve | G2: Freedom | H2: School | I2: Buy | J2: House | K2: Car | L2: Travel | M2: Child | N2: Gifts | O2: Emergency | P2: E-Home | Q2: BC | R2: Roth IRA | S2: UTMA | T2: KPMG Pension | U2: USAA | V2: 401K | W2: Chase | Y2: Budget to Actual | AD2: Activity
D3: 2000 | E3: 9400 | F3: 0 | G3: 0 | H3: 7939.08 | I3: 49090 | J3: 152868 | K3: 60578.68 | L3: 24245.91 | M3: 32000.37 | N3: 4000 | O3: 33572.5 | P3: 213589 | Q3: 132109 | R3: 67829 | S3: 6585 | T3: 33181 | U3: 27298 | V3: 246316 | W3: 3882.48 | Y3: Category | Z3: Budget | AA3: Actual | AB3: Variance | AD3: Investment Activity
A4: 46143 | B4: Mortgage | C4: Rent | E4: -3688 | I4: 456.91 | J4: 1000 | Y4: Cable | Z4: =Summary!W21 -> 350 | AA4: =SUMIF($C$2:$C$60,Y4,$F$2:$F$60)+SUMIF($C$2:$C$60,Y4,$G$2:$G$60) -> -381.99 | AB4: =Z4+AA4 -> -31.99
A5: 46143 | B5: Utilities HOA | C5: Utilities | E5: -275 | Y5: Car Insurance | Z5: =Summary!W22 -> 335 | AA5: =SUMIF($C$2:$C$60,Y5,$F$2:$F$60)+SUMIF($C$2:$C$60,Y5,$G$2:$G$60) -> -358.67 | AB5: =Z5+AA5 -> -23.67 | AD5: Invested Amount for month
A6: 46143 | B6: Parents | C6: Parents | E6: -500 | Y6: Cleaners | Z6: =Summary!W23 -> 20 | AA6: =SUMIF($C$2:$C$60,Y6,$F$2:$F$60)+SUMIF($C$2:$C$60,Y6,$G$2:$G$60) -> 0 | AB6: =Z6+AA6 -> 20 | AD6: Etrade
A7: 46143 | B7: Rent | C7: Rent | E7: -4250 | Y7: Clothes | Z7: =Summary!W24 -> 300 | AA7: =SUMIF($C$2:$C$60,Y7,$F$2:$F$60)+SUMIF($C$2:$C$60,Y7,$G$2:$G$60) -> -262 | AB7: =Z7+AA7 -> 38 | AD7: CC
A8: 46143 | B8: Rent | C8: Rent | E8: 3800 | Y8: Utilities | Z8: =Summary!W25 -> 700 | AA8: =SUMIF($C$2:$C$60,Y8,$F$2:$F$60)+SUMIF($C$2:$C$60,Y8,$G$2:$G$60)+E5+E45+E50 -> -642.06 | AB8: =Z8+AA8 -> 57.94 | AD8: Roth | AE8: =R39 -> 300
A9: 46145 | B9: Grocery | C9: Grocery | F9: =-400+120 -> -280 | G9: -277 | Y9: Dining | Z9: =Summary!W26 -> 1300 | AA9: =SUMIF($C$2:$C$60,Y9,$F$2:$F$60)+SUMIF($C$2:$C$60,Y9,$G$2:$G$60) -> -1470.7 | AB9: =Z9+AA9 -> -170.7 | AD9: 401K
A10: 46145 | B10: Offering - GRC | C10: Offering | F10: -306 | Y10: Entertainment | Z10: =Summary!W27 -> 150 | AA10: =SUMIF($C$2:$C$60,Y10,$F$2:$F$60)+SUMIF($C$2:$C$60,Y10,$G$2:$G$60) -> -180 | AB10: =Z10+AA10 -> -30 | AD10: Total | AE10: =SUM(AE6:AE9) -> 300
A11: 46145 | B11: Offernig - Serge | C11: Offering | F11: -50 | Y11: Gas | Z11: =Summary!W28 -> 200 | AA11: =SUMIF($C$2:$C$60,Y11,$F$2:$F$60)+SUMIF($C$2:$C$60,Y11,$G$2:$G$60) -> -481 | AB11: =Z11+AA11 -> -281
A12: 46145 | B12: Offering - Radiance | C12: Offering | F12: -50 | Y12: Gifts | Z12: =Summary!W29 -> 500 | AA12: =SUMIF($C$2:$C$60,Y12,$F$2:$F$60)+SUMIF($C$2:$C$60,Y12,$G$2:$G$60) -> -590.84 | AB12: =Z12+AA12 -> -90.84
A13: 46145 | B13: Gas | C13: Gas | F13: -119 | Y13: Grocery | Z13: =Summary!W30 -> 1000 | AA13: =SUMIF($C$2:$C$60,Y13,$F$2:$F$60)+SUMIF($C$2:$C$60,Y13,$G$2:$G$60) -> -1171.31 | AB13: =Z13+AA13 -> -171.31
A14: 46145 | B14: Entertainment | C14: Entertainment | E14: 130 | F14: =-130-50 -> -180 | Y14: Gym | Z14: =Summary!W31 -> 200 | AA14: =SUMIF($C$2:$C$60,Y14,$F$2:$F$60)+SUMIF($C$2:$C$60,Y14,$G$2:$G$60) -> -259 | AB14: =Z14+AA14 -> -59 | AD14: Gain/Loss in Investment
A15: 46145 | B15: Grocery | C15: Grocery | F15: -120 | Y15: Loan | Z15: =Summary!W32 -> 0 | AA15: =SUMIF($C$2:$C$60,Y15,$F$2:$F$60)+SUMIF($C$2:$C$60,Y15,$G$2:$G$60) -> 0 | AB15: =Z15+AA15 -> 0 | AD15: Etrade | AE15: =P61 -> 0
A16: 46145 | B16: Dining | C16: Dining | F16: -300 | G16: =-40-7-62-20 -> -129 | Y16: Misc | Z16: =Summary!W33 -> 500 | AA16: =SUMIF($C$2:$C$60,Y16,$F$2:$F$60)+SUMIF($C$2:$C$60,Y16,$G$2:$G$60) -> -50 | AB16: =Z16+AA16 -> 450 | AD16: BC | AE16: =Q61 -> 0
A17: 46145 | B17: House | C17: House | F17: =-100-75-36-32.3-13 -> -256.3 | Y17: Offering | Z17: =Summary!W34 -> 800 | AA17: =SUMIF($C$2:$C$60,Y17,$F$2:$F$60)+SUMIF($C$2:$C$60,Y17,$G$2:$G$60)+E18 -> -909.27 | AB17: =Z17+AA17 -> -109.27 | AD17: Roth | AE17: =R61 -> 3765
A18: 46147 | B18: Offering- Crosspoint | C18: Offering | E18: -50 | Y18: Rent | Z18: =Summary!W35 -> 4100 | AA18: =SUMIF($C$2:$C$60,Y18,$F$2:$F$60)+SUMIF($C$2:$C$60,Y18,$G$2:$G$60)+E4+E7+E8 -> -4138 | AB18: =Z18+AA18 -> -38 | AD18: UTMA | AE18: =S61 -> 535
A19: 46147 | B19: Grocery | C19: Grocery | F19: -45 | G19: =-23-40-90-50-50-73.21-48-75.1 -> -449.31 | Y19: Travel | Z19: =Summary!W36 -> 500 | AA19: =SUMIF($C$2:$C$60,Y19,$F$2:$F$60)+SUMIF($C$2:$C$60,Y19,$G$2:$G$60) -> -142 | AB19: =Z19+AA19 -> 358 | AD19: 401K | AE19: =V61 -> 10181
A20: 46147 | B20: Gifts | C20: Gifts | F20: =-220-45 -> -265 | G20: =-122.84-33-170 -> -325.84 | Y20: Parents | Z20: =Summary!W37 -> 500 | AA20: =SUMIF($C$2:$C$60,Y20,$F$2:$F$60)+SUMIF($C$2:$C$60,Y20,$G$2:$G$60)+E6+E27 -> -845 | AB20: =Z20+AA20 -> -345 | AD20: Chase & Amex | AE20: =SUM(W61:W61) -> 146.44
A21: 46149 | B21: Chair | C21: Chair | E21: 519 | F21: -520 | Y21: Car | Z21: =Summary!W38 -> 0 | AA21: =SUMIF($C$2:$C$60,Y21,$F$2:$F$60)+SUMIF($C$2:$C$60,Y21,$G$2:$G$60) -> 0 | AB21: =Z21+AA21 -> 0 | AD21: Total | AE21: =SUM(AE15:AE20) -> 14627.44
A22: 46148 | B22: Gym - LA Fitness | C22: Gym | F22: =-27-27 -> -54 | Y22: House | Z22: =Summary!W39 -> 500 | AA22: =SUMIF($C$2:$C$60,Y22,$F$2:$F$60)+SUMIF($C$2:$C$60,Y22,$G$2:$G$60) -> -508.3 | AB22: =Z22+AA22 -> -8.3
A23: 46148 | B23: Baby Sitter | C23: Baby SItter | E23: -880 | Y23: School | Z23: =Summary!W40 -> 0 | AA23: =SUMIF($C$2:$C$60,Y23,$F$2:$F$60)+SUMIF($C$2:$C$60,Y23,$G$2:$G$60) -> -65 | AB23: =Z23+AA23 -> -65
A24: 46148 | B24: Cable - Netflix | C24: Cable | F24: -47 | Y24: Baby Sitter | Z24: =Summary!W41 -> 900 | AA24: =SUMIF($C$2:$C$60,Y24,$F$2:$F$60)+SUMIF($C$2:$C$60,Y24,$G$2:$G$60)+E23+E44 -> -1245 | AB24: =Z24+AA24 -> -345
A25: 46150 | B25: Gas | C25: Gas | F25: =-115-5-10-4-113-7 -> -254
A26: 46150 | B26: Cable - Claude | C26: Cable | F26: -20
A27: 46152 | B27: Parents | C27: Parents | E27: 500 | F27: -500 | G27: -80
A28: 46152 | B28: Dining | C28: Dining | F28: =-45-50 -> -95 | G28: =-20-103-28.04-47.42-100 -> -298.46
A29: 46152 | B29: Offering - Compassion | C29: Offering | F29: -93
A30: 46152 | B30: Offering - Ethnos | C30: Offering | F30: -51
A31: 46152 | B31: Cable - Fubo | C31: Cable | F31: -55.99
A32: 46152 | B32: Haircut | C32: Misc | F32: -50
A33: 46153 | B33: Dining - Shakeshack | C33: Dining | F33: =-106-61-20 -> -187 | G33: =-15-32.24-25-39 -> -111.24
A34: 46153 | B34: Gym - GLF | C34: Gym | F34: =-75-22-50 -> -147
A35: 46154 | B35: School | C35: School | G35: -65
A36: 46154 | B36: Paycheck | C36: Paycheck | E36: 5000
A37: 46155 | B37: Cable - ESPN | C37: Cable | F37: =-30-5 -> -35
A38: 46157 | B38: Paycheck | C38: Paycheck | E38: 4665
A39: 46157 | B39: Investment | C39: Investment | E39: -300 | R39: 300
A40: 46157 | B40: Offering | C40: Offering | F40: -309.27
A41: 46157 | B41: Car Insurance | C41: Car Insurance | F41: =-342.67-16 -> -358.67
A42: 46157 | B42: AM Home Warranty | C42: Utilities | F42: -66
A43: 46157 | B43: Clothes - Riley | C43: Clothes | F43: -37 | G43: -150
A44: 46160 | B44: Growing Room | C44: Baby Sitter | E44: -365
A45: 46160 | B45: IRWD | C45: Utilities | E45: -68
A46: 46160 | B46: Travel - Legoland | C46: Travel | F46: =-9-30 -> -39 | G46: -103
A47: 46162 | B47: Cable - Netflix | C47: Cable | F47: -30
A48: 46163 | B48: Payment | C48: Payment | E48: -2716 | F48: 2716
A49: 46164 | B49: Clothes - Riley | C49: Clothes | G49: -75
A50: 46168 | B50: Utilities - Edison | C50: Utilities | E50: =-193.06-8 -> -201.06 | F50: -32
A51: 46168 | B51: Parents - Hotel - Travel | C51: Parents | F51: -30 | G51: -235
A52: 46168 | B52: Cable - ATT | C52: Cable | F52: =-85-70 -> -155
A53: 46168 | B53: Gas | C53: Gas | F53: -108
A54: 46168 | B54: Cable - Burry | C54: Cable | F54: -39
A55: 46168 | B55: House - Dishes | C55: House | F55: =-103-40-42-67 -> -252
A56: 46170 | B56: Golf | C56: Gym | F56: -58
A57: 46172 | B57: Paycheck | C57: Paycheck | E57: =5031.33+5000 -> 10031.33
A58: 46173 | B58: Dining | C58: Dining | F58: -250 | G58: -100
A59: 46173 | B59: Savings | C59: Savings | E59: -25 | I59: 25
A60: 46173 | B60: Payment | C60: Payment | E60: =-SUM(F60:G60) -> -5527.08 | F60: =-SUM(F3:F59) -> 3128.23 | G60: =-SUM(G3:G59) -> 2398.85
E61: =9500-SUM(E3:E60) -> -5700.19 | H61: 1000 | I61: 2500 | K61: 200 | L61: 2000 | R61: 3765 | S61: 535 | V61: 10181 | W61: =75.47+70.97 -> 146.44
A62: Balance | D62: =SUM(D3:D61) -> 2000 | E62: =SUM(E3:E61) -> 9500 | F62: =SUM(F3:F61) -> 0 | G62: =SUM(G3:G61) -> 0 | H62: =SUM(H3:H61) -> 8939.08 | I62: =SUM(I3:I61) -> 52071.91 | J62: =SUM(J3:J61) -> 153868 | K62: =SUM(K3:K61) -> 60778.68 | ... W62: =SUM(W3:W61) -> 4028.92 | Y62: Total | Z62: =SUM(Z4:Z60) -> 12855 | AA62: =SUM(AA4:AA60) -> -13700.14 | AB62: =SUM(AB4:AB60) -> -845.14
W64: =SUM(D62:W62) -> 1128693.4
Y66: PERCENTAGE
V67: Total Savings | W67: =SUM(H62:O62) -> 371476.45 | Y67: =W67/W70 -> 0.32912079
V68: Total Investments | W68: =SUM(P62:W62) -> 745716.92 | Y68: =W68/W70 -> 0.66069044
V69: Total Checking | W69: =E62+D62 -> 11500 | Y69: =W69/W70 -> 0.010188773
V70: TOTAL | W70: =SUM(W67:W69) -> 1128693.4
W72: =W70-W64 -> 0

Sheet Apr 
D1: Checking | F1: CC | H1: SAVINGS | P1: INVESTMENT | W1: CC
A2: Date | B2: Name | C2: Categorization | D2: PK | E2: Main | F2: Chase | G2: Chase | H2: School | I2: Buy | J2: House | K2: Car | L2: Travel | M2: Child | N2: Gifts | O2: Emergency | P2: E-Home | Q2: BC | R2: Roth IRA | S2: UTMA | T2: KPMG Pension | U2: USAA | V2: 401K | W2: Chase | Y2: Budget to Actual | AD2: Activity
D3: 2000 | E3: 9300 | F3: 0 | G3: 0 | H3: 14845.08 | I3: 47065 | J3: 154796 | K3: 59712.68 | L3: 21245.91 | M3: 32000.37 | N3: 4000 | O3: 26572.5 | P3: 213589 | Q3: 130109 | R3: 65471 | S3: 4185 | T3: 33181 | U3: 27298 | V3: 231983 | W3: 3721.58 | Y3: Category | Z3: Budget | AA3: Actual | AB3: Variance | AD3: Investment Activity
A4: 46113 | B4: Mortgage | C4: Rent | E4: -3688 | J4: -1928 | K4: 580 | Y4: Cable | Z4: =Summary!T21 -> 350 | AA4: =SUMIF($C$2:$C$58,Y4,$F$2:$F$58)+SUMIF($C$2:$C$58,Y4,$G$2:$G$58) -> -277 | AB4: =Z4+AA4 -> 73
A5: 46113 | B5: Utilities HOA | C5: Utilities | E5: -275 | Y5: Car Insurance | Z5: =Summary!T22 -> 335 | AA5: =SUMIF($C$2:$C$58,Y5,$F$2:$F$58)+SUMIF($C$2:$C$58,Y5,$G$2:$G$58) -> -342 | AB5: =Z5+AA5 -> -7 | AD5: Invested Amount for month
A6: 46113 | B6: Parents | C6: Parents | E6: -500 | Y6: Cleaners | Z6: =Summary!T23 -> 20 | AA6: =SUMIF($C$2:$C$58,Y6,$F$2:$F$58)+SUMIF($C$2:$C$58,Y6,$G$2:$G$58) -> 0 | AB6: =Z6+AA6 -> 20 | AD6: Etrade | AE6: =+P4+P5 -> 0
A7: 46113 | B7: Rent | C7: Rent | E7: -4250 | Y7: Clothes | Z7: =Summary!T24 -> 20 | AA7: =SUMIF($C$2:$C$58,Y7,$F$2:$F$58)+SUMIF($C$2:$C$58,Y7,$G$2:$G$58) -> -539 | AB7: =Z7+AA7 -> -519 | AD7: CC | AE7: =Q7+Q4+Q9+Q11+Q15+Q55 -> 2000
A8: 46113 | B8: Rent | C8: Rent | E8: 3320 | Y8: Utilities | Z8: =Summary!T25 -> 700 | AA8: =SUMIF($C$2:$C$58,Y8,$F$2:$F$58)+SUMIF($C$2:$C$58,Y8,$G$2:$G$58)+E5+E40+E48 -> -751.29 | AB8: =Z8+AA8 -> -51.29 | AD8: Roth | AE8: =R34 -> 300
A9: 46113 | B9: Baby Sitter | C9: Baby SItter | E9: -880 | Y9: Dining | Z9: =Summary!T26 -> 1300 | AA9: =SUMIF($C$2:$C$58,Y9,$F$2:$F$58)+SUMIF($C$2:$C$58,Y9,$G$2:$G$58) -> -1631.13 | AB9: =Z9+AA9 -> -331.13 | AD9: UTMA | AE9: =S27+S56 -> 2400
A10: 46113 | B10: Misc | C10: Misc | E10: 61 | Y10: Entertainment | Z10: =Summary!T27 -> 150 | AA10: =SUMIF($C$2:$C$58,Y10,$F$2:$F$58)+SUMIF($C$2:$C$58,Y10,$G$2:$G$58) -> -347.38 | AB10: =Z10+AA10 -> -197.38 | AD10: 401K | AE10: =V28+V58 -> 0
A11: 46113 | B11: Paycheck | C11: Paycheck | E11: =5000+5060 -> 10060 | Y11: Gas | Z11: =Summary!T28 -> 200 | AA11: =SUMIF($C$2:$C$58,Y11,$F$2:$F$58)+SUMIF($C$2:$C$58,Y11,$G$2:$G$58) -> -293 | AB11: =Z11+AA11 -> -93 | AD11: Total | AE11: =SUM(AE6:AE10) -> 4700
A12: 46113 | B12: Dining | C12: Dining | G12: =-115.13-15-6-65 -> -201.13 | Y12: Gifts | Z12: =Summary!T29 -> 200 | AA12: =SUMIF($C$2:$C$58,Y12,$F$2:$F$58)+SUMIF($C$2:$C$58,Y12,$G$2:$G$58) -> -496 | AB12: =Z12+AA12 -> -296
A13: 46113 | B13: Offering - Serge | C13: Offering | F13: -50 | Y13: Grocery | Z13: =Summary!T30 -> 1000 | AA13: =SUMIF($C$2:$C$58,Y13,$F$2:$F$58)+SUMIF($C$2:$C$58,Y13,$G$2:$G$58) -> -630 | AB13: =Z13+AA13 -> 370 | AD13: Gain/Loss in Investment
A14: 46113 | B14: Offering - Tithly | C14: Offering | F14: -309.27 | Y14: Gym | Z14: =Summary!T31 -> 100 | AA14: =SUMIF($C$2:$C$58,Y14,$F$2:$F$58)+SUMIF($C$2:$C$58,Y14,$G$2:$G$58) -> -100 | AB14: =Z14+AA14 -> 0 | AD14: Etrade | AE14: =P59 -> 0
A15: 46113 | B15: Offering - Radiance | C15: Offering | F15: -50 | Y15: Loan | Z15: =Summary!T32 -> 0 | AA15: =SUMIF($C$2:$C$58,Y15,$F$2:$F$58)+SUMIF($C$2:$C$58,Y15,$G$2:$G$58) -> 0 | AB15: =Z15+AA15 -> 0 | AD15: CC | AE15: =Q59 -> 0
A16: 46113 | B16: Entertainment | C16: Entertainment | F16: =-7.19-12.16-17.53-24.5-70-150-26 -> -307.38 | Y16: Misc | Z16: =Summary!T33 -> 500 | AA16: =SUMIF($C$2:$C$58,Y16,$F$2:$F$58)+SUMIF($C$2:$C$58,Y16,$G$2:$G$58)+E17 -> -906 | AB16: =Z16+AA16 -> -406 | AD16: Roth | AE16: 0
A17: 46113 | B17: Misc | C17: Misc | E17: -265 | F17: =-137-42-250-160-52 -> -641 | Y17: Offering | Z17: =Summary!T34 -> 800 | AA17: =SUMIF($C$2:$C$58,Y17,$F$2:$F$58)+SUMIF($C$2:$C$58,Y17,$G$2:$G$58)+E22 -> -910.27 | AB17: =Z17+AA17 -> -110.27 | AD17: UTMA | AE17: =R59 -> 2058
A18: 46113 | B18: School | C18: School | H18: -9906 | Y18: Rent | Z18: =Summary!T35 -> 4100 | AA18: =SUMIF($C$2:$C$58,Y18,$F$2:$F$58)+SUMIF($C$2:$C$58,Y18,$G$2:$G$58)+E4+E7+E8 -> -4618 | AB18: =Z18+AA18 -> -518 | AD18: 401K | AE18: =V59+T59 -> 14333
A19: 46115 | B19: House | C19: House | F19: =-150-100-40 -> -290 | Y19: Travel | Z19: =Summary!T36 -> 0 | AA19: =SUMIF($C$2:$C$58,Y19,$F$2:$F$58)+SUMIF($C$2:$C$58,Y19,$G$2:$G$58) -> -1508 | AB19: =Z19+AA19 -> -1508 | AD19: Chase & Amex | AE19: =SUM(W59:W59) -> 160.9
A20: 46116 | B20: Dining | C20: Dining | F20: =-50-30-10 -> -90 | G20: =-128-150-14-60-20-15-25-36-140-19-5-19-220 -> -851 | Y20: Parents | Z20: =Summary!T37 -> 500 | AA20: =SUMIF($C$2:$C$58,Y20,$F$2:$F$58)+SUMIF($C$2:$C$58,Y20,$G$2:$G$58)+E6 -> -500 | AB20: =Z20+AA20 -> 0 | AD20: Total | AE20: =SUM(AE14:AE19) -> 16551.9
A21: 46116 | B21: Tax | C21: Tax | E21: 3491 | F21: -1984 | G21: -500 | Y21: Car | Z21: =Summary!T38 -> 250 | AA21: =SUMIF($C$2:$C$58,Y21,$F$2:$F$58)+SUMIF($C$2:$C$58,Y21,$G$2:$G$58)+E25 -> -830 | AB21: =Z21+AA21 -> -580
A22: 46118 | B22: Offering - Crosspoint | C22: Offering | E22: -50 | G22: -93 | Y22: House | Z22: =Summary!T39 -> 400 | AA22: =SUMIF($C$2:$C$58,Y22,$F$2:$F$58)+SUMIF($C$2:$C$58,Y22,$G$2:$G$58)+E49 -> -290 | AB22: =Z22+AA22 -> 110
A23: 46118 | B23: Gas | C23: Gas | F23: =-100-100 -> -200 | Y23: School | Z23: =Summary!T40 -> 10000 | AA23: =SUMIF($C$2:$C$58,Y23,$F$2:$F$58)+SUMIF($C$2:$C$58,Y23,$G$2:$G$58)+H18 -> -9906 | AB23: =Z23+AA23 -> 94
A24: 46118 | B24: Gym | C24: Gym | F24: -100 | Y24: Baby Sitter | Z24: =Summary!T41 -> 900 | AA24: =SUMIF($C$2:$C$58,Y24,$F$2:$F$58)+SUMIF($C$2:$C$58,Y24,$G$2:$G$58)+E9 -> -880 | AB24: =Z24+AA24 -> 20
A25: 46118 | B25: Cable - Netflix | C25: Cable | F25: -44
A26: 46120 | B26: Clothes | C26: Clothes | F26: -80 | G26: -115
A27: 46120 | B27: Investment | C27: Investment | E27: -1400 | S27: 1400
A28: 46122 | B28: Paycheck | C28: Paycheck | E28: 4987
A29: 46122 | B29: Clothes | C29: Clothes | G29: =-174-170 -> -344
A30: 46122 | B30: Offering - Ethnos | C30: Offering | F30: =-50-3 -> -53
A31: 46122 | B31: Grocery | C31: Grocery | F31: =-300-100 -> -400 | G31: =-100-130 -> -230
A32: 46124 | B32: Travel | C32: Travel | F32: =-500-320-71-32 -> -923 | G32: =-200+13+50 -> -137
A33: 46125 | B33: Cable - ESPN and Microsoft | C33: Cable | F33: -35
A34: 46127 | B34: Investment | C34: Investment | E34: -300 | R34: 300
A35: 46127 | B35: Utilities - AM Warranty | C35: Utilities | F35: -65
A36: 46127 | B36: Offering - Tithly | C36: Offering | F36: -305
A37: 46127 | B37: Car Insurance | C37: Car Insurance | F37: -342
A38: 46129 | B38: Car Oil Change | C38: Car | F38: -830
A39: 46131 | B39: Gifts | C39: Gifts | F39: -300 | G39: -120
A40: 46132 | B40: IRWD Utilities | C40: Utilities | E40: =-72.39-74 -> -146.39 | F40: -20
A41: 46132 | B41: Cable - Netflix | C41: Cable | F41: -28
A42: 46132 | B42: Cable - ChatGPT | C42: Cable | F42: -20
A43: 46132 | B43: Dining | C43: Dining | F43: =-100-43-13 -> -156
A44: 46135 | B44: Entertainment | C44: Entertainment | F44: -40
A45: 46136 | B45: Paycheck | C45: Paycheck | E45: =4940+5000 -> 9940
A46: 46136 | B46: Gifts | C46: Gifts | G46: -76
A47: 46136 | B47: Payment | C47: Payment | E47: =-F47-G47 -> -3427.7 | F47: 2006 | G47: 1421.7
A48: 46139 | B48: Utilities - Edison | C48: Utilities | E48: -244.9
A49: 46139 | B49: Cable - COX | C49: Cable | F49: -70
A50: 46139 | B50: Gas | C50: Gas | F50: -93
A51: 46139 | B51: Utilities - ATT | C51: Cable | F51: -80
A52: 46139 | B52: Dining | C52: Dining | F52: =-27-23-77-156 -> -283 | G52: -50
A53: 46141 | B53: Paycheck | C53: Paycheck | E53: 9906
A54: 46141 | B54: Travel | C54: Travel | F54: =-100-18-60 -> -178 | G54: -270
A55: 46142 | B55: INvestment | C55: Investment | E55: -2000 | Q55: 2000
A56: 46142 | B56: INvestment | C56: Investment | E56: -1000 | S56: 1000
A57: 46142 | B57: Savings | C57: Savings | E57: -25 | I57: 25
A58: 46142 | B58: Payment | C58: Payment | E58: =-SUM(F58:G58) -> -7926.08 | F58: =-SUM(F4:F57) -> 6360.65 | G58: =-SUM(G4:G57) -> 1565.43
E59: =9400-SUM(E3:E58) -> -15286.93 | H59: 3000 | I59: 2000 | K59: 286 | L59: 3000 | O59: 7000 | R59: 2058 | V59: 14333 | W59: =97.7+34.5+28.7 -> 160.9
A60: Balance | D60: =SUM(D3:D59) -> 2000 | E60: =SUM(E3:E59) -> 9400 | F60: =SUM(F3:F59) -> 0 | G60: =SUM(G3:G59) -> 0 | H60: =SUM(H3:H59) -> 7939.08 | I60: =SUM(I3:I59) -> 49090 | J60: =SUM(J3:J59) -> 152868 | K60: =SUM(K3:K59) -> 60578.68 | ... W60: =SUM(W3:W59) -> 3882.48 | Y60: Total | Z60: =SUM(Z4:Z58) -> 21825 | AA60: =SUM(AA4:AA58) -> -25755.07 | AB60: =SUM(AB4:AB58) -> -3930.07
W62: =SUM(D60:W60) -> 1106484
Y64: PERCENTAGE
V65: Total Savings | W65: =SUM(H60:O60) -> 364294.54 | Y65: =W65/W68 -> 0.32923615
V66: Total Investments | W66: =SUM(P60:W60) -> 730789.48 | Y66: =W66/W68 -> 0.66046094
V67: Total Checking | W67: =E60+D60 -> 11400 | Y67: =W67/W68 -> 0.010302905
V68: TOTAL | W68: =SUM(W65:W67) -> 1106484
W69: =W68-W62 -> 0

Sheet Mar
D1: Checking | F1: CC | H1: SAVINGS | P1: INVESTMENT | W1: CC
A2: Date | B2: Name | C2: Categorization | D2: PK | E2: Main | F2: Reserve | G2: Freedom | H2: School | I2: Buy | J2: House | K2: Car | L2: Travel | M2: Child | N2: Gifts | O2: Emergency | P2: E-Home | Q2: BC | R2: Roth IRA | S2: UTMA | T2: KPMG | U2: USAA | V2: 401K | W2: Chase | Y2: Budget to Actual | AD2: Activity
D3: 2000 | E3: 9200 | F3: 0 | G3: 0 | H3: 14645.08 | I3: 57040 | J3: 153796 | K3: 69712.68 | L3: 20985.75 | M3: 32000.37 | N3: 4000 | O3: 26572.5 | P3: 213589 | Q3: 130109 | R3: 65171 | S3: 4185 | T3: 33181 | U3: 27298 | V3: 231983 | W3: 3246.86 | Y3: Category | Z3: Budget | AA3: Actual | AB3: Variance | AD3: Investment Activity
A4: 46082 | B4: Mortgage | C4: Rent | E4: -3688 | H4: 200 | J4: 1000 | L4: 260.16 | Y4: Cable | Z4: =Summary!Q21 -> 480 | AA4: =SUMIF($C$2:$C$67,Y4,$F$2:$F$67)+SUMIF($C$2:$C$67,Y4,$G$2:$G$67) -> -452 | AB4: =Z4+AA4 -> 28
A5: 46082 | B5: Utilities HOA | C5: Utilities | E5: -265 | Y5: Car Insurance | Z5: =Summary!Q22 -> 335 | AA5: =SUMIF($C$2:$C$67,Y5,$F$2:$F$67)+SUMIF($C$2:$C$67,Y5,$G$2:$G$67) -> -342 | AB5: =Z5+AA5 -> -7 | AD5: Invested Amount for month
A6: 46082 | B6: Parents | C6: Parents | E6: -500 | Y6: Cleaners | Z6: =Summary!Q23 -> 20 | AA6: =SUMIF($C$2:$C$67,Y6,$F$2:$F$67)+SUMIF($C$2:$C$67,Y6,$G$2:$G$67) -> 0 | AB6: =Z6+AA6 -> 20 | AD6: Etrade
A7: 46082 | B7: Rent | C7: Rent | E7: -4250 | Y7: Clothes | Z7: =Summary!Q24 -> 20 | AA7: =SUMIF($C$2:$C$67,Y7,$F$2:$F$67)+SUMIF($C$2:$C$67,Y7,$G$2:$G$67) -> -450 | AB7: =Z7+AA7 -> -430 | AD7: CC
A8: 46082 | B8: Rent | C8: Rent | E8: 3800 | Y8: Utilities | Z8: =Summary!Q25 -> 700 | AA8: =SUMIF($C$2:$C$67,Y8,$F$2:$F$67)+SUMIF($C$2:$C$67,Y8,$G$2:$G$67)+E5+E47+E59+E60 -> -694.97 | AB8: =Z8+AA8 -> 5.03 | AD8: Roth IRA | AE8: =R39 -> 300
A9: 46082 | B9: Baby Sitter | C9: Baby SItter | E9: -880 | Y9: Dining | Z9: =Summary!Q26 -> 1300 | AA9: =SUMIF($C$2:$C$67,Y9,$F$2:$F$67)+SUMIF($C$2:$C$67,Y9,$G$2:$G$67) -> -1959 | AB9: =Z9+AA9 -> -659 | AD9: UTMA
A10: 46082 | B10: Misc | C10: Misc | E10: -160 | Y10: Entertainment | Z10: =Summary!Q27 -> 150 | AA10: =SUMIF($C$2:$C$67,Y10,$F$2:$F$67)+SUMIF($C$2:$C$67,Y10,$G$2:$G$67) -> -853 | AB10: =Z10+AA10 -> -703 | AD10: 401K
A11: 46083 | B11: Grocery | C11: Grocery | F11: -100 | G11: =-100-60 -> -160 | Y11: Gas | Z11: =Summary!Q28 -> 200 | AA11: =SUMIF($C$2:$C$67,Y11,$F$2:$F$67)+SUMIF($C$2:$C$67,Y11,$G$2:$G$67) -> -247 | AB11: =Z11+AA11 -> -47 | AD11: Total | AE11: =SUM(AE6:AE10) -> 300
A12: 46083 | B12: Dining | C12: Dining | G12: =-60-200 -> -260 | Y12: Gifts | Z12: =Summary!Q29 -> 200 | AA12: =SUMIF($C$2:$C$67,Y12,$F$2:$F$67)+SUMIF($C$2:$C$67,Y12,$G$2:$G$67)+E20 -> -915 | AB12: =Z12+AA12 -> -715
A13: 46083 | B13: Offering - GRC | C13: Offering | F13: -306 | Y13: Grocery | Z13: =Summary!Q30 -> 1000 | AA13: =SUMIF($C$2:$C$67,Y13,$F$2:$F$67)+SUMIF($C$2:$C$67,Y13,$G$2:$G$67) -> -700 | AB13: =Z13+AA13 -> 300
A14: 46083 | B14: Offering - Serge | C14: Offering | F14: -50 | Y14: Gym | Z14: =Summary!Q31 -> 100 | AA14: =SUMIF($C$2:$C$67,Y14,$F$2:$F$67)+SUMIF($C$2:$C$67,Y14,$G$2:$G$67) -> 0 | AB14: =Z14+AA14 -> 100 | AD14: Gain/Loss in Investment
A15: 46083 | B15: Entertainment | C15: Entertainment | F15: =-20-204 -> -224 | Y15: Loan | Z15: =Summary!Q32 -> 0 | AA15: =SUMIF($C$2:$C$67,Y15,$F$2:$F$67)+SUMIF($C$2:$C$67,Y15,$G$2:$G$67) -> 0 | AB15: =Z15+AA15 -> 0 | AD15: Etrade
A16: 46083 | B16: Offering - Radiance | C16: Offering | F16: -50 | Y16: Misc | Z16: =Summary!Q33 -> 500 | AA16: =SUMIF($C$2:$C$67,Y16,$F$2:$F$67)+SUMIF($C$2:$C$67,Y16,$G$2:$G$67)+E10 -> -457 | AB16: =Z16+AA16 -> 43 | AD16: CC
A17: 46083 | B17: Offering - Crosspoint | C17: Offering | E17: =-50-11 -> -61 | Y17: Offering | Z17: =Summary!Q34 -> 800 | AA17: =SUMIF($C$2:$C$67,Y17,$F$2:$F$67)+SUMIF($C$2:$C$67,Y17,$G$2:$G$67)+E17 -> -917 | AB17: =Z17+AA17 -> -117 | AD17: Roth IRA
A18: 46083 | B18: Dining | C18: Dining | F18: =-30-17-160 -> -207 | G18: =-26-49-11-56 -> -142 | Y18: Rent | Z18: =Summary!Q35 -> 4100 | AA18: =SUMIF($C$2:$C$67,Y18,$F$2:$F$67)+SUMIF($C$2:$C$67,Y18,$G$2:$G$67)+E4+E7+E8 -> -4138 | AB18: =Z18+AA18 -> -38 | AD18: UTMA
A19: 46084 | B19: House | C19: House | F19: -24 | Y19: Travel | Z19: =Summary!Q36 -> 1800 | AA19: =SUMIF($C$2:$C$67,Y19,$F$2:$F$67)+SUMIF($C$2:$C$67,Y19,$G$2:$G$67) -> -2709 | AB19: =Z19+AA19 -> -909 | AD19: 401K
A20: 46085 | B20: Gifts | C20: Gifts | E20: -175 | F20: -200 | Y20: Parents | Z20: =Summary!Q37 -> 500 | AA20: =SUMIF($C$2:$C$67,Y20,$F$2:$F$67)+SUMIF($C$2:$C$67,Y20,$G$2:$G$67)+E6 -> -500 | AB20: =Z20+AA20 -> 0 | AD20: Chase & Amex | AE20: =W68 -> 474.72
A21: 46086 | B21: Grocery | C21: Grocery | F21: -40 | G21: -44 | Y21: Car | Z21: =Summary!Q38 -> 250 | AA21: =SUMIF($C$2:$C$67,Y21,$F$2:$F$67)+SUMIF($C$2:$C$67,Y21,$G$2:$G$67) -> 0 | AB21: =Z21+AA21 -> 250 | AD21: Total | AE21: =SUM(AE15:AE20) -> 474.72
A22: 46086 | B22: Clothes | C22: Clothes | F22: -100 | G22: -150 | Y22: House | Z22: =Summary!Q39 -> 200 | AA22: =SUMIF($C$2:$C$67,Y22,$F$2:$F$67)+SUMIF($C$2:$C$67,Y22,$G$2:$G$67) -> -24 | AB22: =Z22+AA22 -> 176
A23: 46090 | B23: Paycheck | C23: Paycheck | E23: 5000 | Y23: School | Z23: =Summary!Q40 -> 0 | AA23: =SUMIF($C$2:$C$67,Y23,$F$2:$F$67)+SUMIF($C$2:$C$67,Y23,$G$2:$G$67) -> -400 | AB23: =Z23+AA23 -> -400
A24: 46090 | B24: Cable - Netflix | C24: Cable | F24: -43 | Y24: Baby Sitter | Z24: =Summary!Q41 -> 900 | AA24: =SUMIF($C$2:$C$67,Y24,$F$2:$F$67)+SUMIF($C$2:$C$67,Y24,$G$2:$G$67)+E9 -> -880 | AB24: =Z24+AA24 -> 20
A25: 46091 | B25: Offering - Ethnos | C25: Offering | F25: -51
A26: 46092 | B26: Grocery | C26: Grocery | G26: -56
A27: 46092 | B27: Offering - Compassion | C27: Offering | F27: -93
A28: 46092 | B28: Cable - Fubo TV | C28: Cable | F28: -65
A29: 46093 | B29: Gas | C29: Gas | F29: -125
A30: 46093 | B30: School | C30: School | G30: -400
A31: 46093 | B31: Dining | C31: Dining | G31: =-38-82 -> -120
A32: 46093 | B32: Cable - Paramount | C32: Cable | F32: -14
A33: 46093 | B33: Cable - WSJ | C33: Cable | F33: -5
A34: 46094 | B34: Gifts | C34: Gifts | G34: -150
A35: 46094 | B35: Cable - ESPN | C35: Cable | F35: -30
A36: 46094 | B36: Grocery | C36: Grocery | F36: =-17-38 -> -55
A37: 46094 | B37: Dining | C37: Dining | F37: =-50-404-40-50 -> -544 | G37: -300
A38: 46097 | B38: Paycheck | C38: Paycheck | E38: 4838
A39: 46097 | B39: Investment | C39: Investment | E39: -300 | R39: 300
A40: 46097 | B40: Grocery | C40: Grocery | G40: =-65-3-34-65-13-65 -> -245
A41: 46097 | B41: Offering | C41: Offering | F41: -306
A42: 46097 | B42: Car Insurance | C42: Car Insurance | F42: -342
A43: 46097 | B43: UAM Warranty | C43: Utilities | F43: -64
A44: 46097 | B44: Haircut | C44: Misc | F44: -167
A45: 46097 | B45: Dining | C45: DIning | F45: =-135-20-49-27 -> -231 | G45: -125
A46: 46097 | B46: Misc | C46: Misc | F46: -130
A47: 46100 | B47: IRWD | C47: Utilities | E47: -70.85
A48: 46101 | B48: Cable - Netflix | C48: Cable | F48: =-50-40 -> -90
A49: 46101 | B49: Gifts | C49: Gifts | G49: -300
A50: 46101 | B50: Clothes | C50: Clothes | G50: -200
A51: 46104 | B51: Payment | C51: Payment | E51: -2000 | F51: 2000
A52: 46104 | B52: Entertainment | C52: Entertainment | F52: =-150-20 -> -170
A53: 46104 | B53: Gas | C53: Gas | F53: =-50-72 -> -122
A54: 46105 | B54: Cable - ATT | C54: Cable | F54: -85
A55: 46105 | B55: Cable - Michael Burry | C55: Cable | F55: -40
A56: 46107 | B56: Dining | C56: Dining | F56: -30
A57: 46107 | B57: Cable - COX | C57: Cable | F57: -80
A58: 46107 | B58: Gifts | C58: Gifts | F58: -90
A59: 46108 | B59: Utilities - Edison | C59: Utilities | E59: -276
A60: 46108 | B60: Utilities - Socal Gas | C60: Utilities | E60: -19.12
A61: 46108 | B61: Paycheck | C61: Paycheck | E61: 4794
A62: 46108 | B62: Paycheck | C62: Paycheck | E62: 5000
A63: 46108 | B63: Travel | C63: Travel | F63: -49 | G63: -2660
A64: 46108 | B64: Tax | C64: Tax | F64: =-14-2-2500 -> -2516 | I64: =-15000+5000 -> -10000 | K64: -10000
A65: 46110 | B65: Entertainment | C65: Entertainment | F65: =-50-100-28-76 -> -254 | G65: =-150-100+50-5 -> -205
A66: 46112 | B66: Savings | C66: Savings | E66: -25 | I66: 25
A67: 46112 | B67: Payment | C67: Payment | E67: =-SUM(F67:G67) -> -10609 | F67: =-SUM(F4:F66) -> 5092 | G67: =-SUM(G4:G66) -> 5517
E68: =9300-SUM(E3:E67) -> -53.03 | W68: 474.72
A69: Balance | D69: =SUM(D3:D68) -> 2000 | E69: =SUM(E3:E68) -> 9300 | F69: =SUM(F4:F68) -> 0 | G69: =SUM(G3:G68) -> 0 | H69: =SUM(H3:H68) -> 14845.08 | I69: =SUM(I3:I68) -> 47065 | J69: =SUM(J3:J68) -> 154796 | K69: =SUM(K3:K68) -> 59712.68 | L69: =SUM(L3:L68) -> 21245.91 | M69: =SUM(M3:M68) -> 32000.37 | N69: =SUM(N3:N68) -> 4000 | ... W69: =SUM(W3:W68) -> 3721.58 | Y69: Total | Z69: =SUM(Z4:Z67) -> 13555 | AA69: =SUM(AA4:AA67) -> -16637.97 | AB69: =SUM(AB4:AB67) -> -3082.97
W71: =SUM(D69:W69) -> 1081075.1
Y73: PERCENTAGE
V74: Total Savings | W74: =SUM(H69:O69) -> 360237.54 | Y74: =W74/W77 -> 0.33322156
V75: Total Investments | W75: =SUM(P69:W69) -> 709537.58 | Y75: =W75/W78 -> #DIV/0!
V76: Total Checking | W76: =SUM(D69:E69) -> 11300 | Y76: =W76/W79 -> #DIV/0!
V77: TOTAL | W77: =SUM(W74:W76) -> 1081075.1
W79: =W77-W71 -> 0

Sheet Feb
D1: Checking | F1: CC | H1: SAVINGS | P1: INVESTMENT | W1: CC
A2: Date | B2: Name | C2: Categorization | D2: Peony | E2: Main | F2: Chase | G2: Chase | H2: School | I2: Buy | J2: House | K2: Car | L2: Travel | M2: Child | N2: Gifts | O2: Emergency | P2: E-Home | Q2: BC | R2: Roth IRA | S2: UTMA | T2: KPMG | U2: USAA | V2: 401K | W2: Chase | Y2: Budget to Actual | AD2: Activity
D3: 2000 | E3: 9100 | F3: 0 | G3: 0 | H3: 14645.08 | I3: 55015 | J3: 152796 | K3: 67208.71 | L3: 20985.75 | M3: 30000.37 | N3: 4000 | O3: 25572.5 | P3: 210453 | Q3: 130109 | R3: 64871 | S3: 4185 | T3: 33181 | U3: 27298 | V3: 229377 | W3: 3126.9 | Y3: Category | Z3: Budget | AA3: Actual | AB3: Variance | AD3: Investment Activity
A4: 46054 | B4: Mortgage | C4: Rent | E4: -3688 | J4: 1000 | K4: 503.97 | Y4: Cable | Z4: =Summary!N21 -> 480 | AA4: =SUMIF($C$2:$C$51,Y4,$F$2:$F$51)+SUMIF($C$2:$C$51,Y4,$G$2:$G$51) -> -271 | AB4: =Z4+AA4 -> 209
A5: 46054 | B5: Utilities HOA | C5: Utilities | E5: -265 | Y5: Car Insurance | Z5: =Summary!N22 -> 335 | AA5: =SUMIF($C$2:$C$51,Y5,$F$2:$F$51)+SUMIF($C$2:$C$51,Y5,$G$2:$G$51) -> -342 | AB5: =Z5+AA5 -> -7 | AD5: Invested Amount for month
A6: 46054 | B6: Parents | C6: Parents | E6: -500 | Y6: Cleaners | Z6: =Summary!N23 -> 20 | AA6: =SUMIF($C$2:$C$51,Y6,$F$2:$F$51)+SUMIF($C$2:$C$51,Y6,$G$2:$G$51) -> 0 | AB6: =Z6+AA6 -> 20 | AD6: Etrade
A7: 46054 | B7: Rent | C7: Rent | E7: -4250 | Y7: Clothes | Z7: =Summary!N24 -> 300 | AA7: =SUMIF($C$2:$C$51,Y7,$F$2:$F$51)+SUMIF($C$2:$C$51,Y7,$G$2:$G$51) -> -150 | AB7: =Z7+AA7 -> 150 | AD7: BC
A8: 46054 | B8: Rent | C8: Rent | E8: 3800 | Y8: Utilities | Z8: =Summary!N25 -> 700 | AA8: =SUMIF($C$2:$C$51,Y8,$F$2:$F$51)+SUMIF($C$2:$C$51,Y8,$G$2:$G$51)+E5+E33+E39 -> -687.74 | AB8: =Z8+AA8 -> 12.26 | AD8: Roth | AE8: =R32 -> 300
A9: 46054 | B9: Paycheck | C9: Paycheck | E9: 5000 | Y9: Dining | Z9: =Summary!N26 -> 1300 | AA9: =SUMIF($C$2:$C$51,Y9,$F$2:$F$51)+SUMIF($C$2:$C$51,Y9,$G$2:$G$51) -> -1495 | AB9: =Z9+AA9 -> -195 | AD9: UTMA
A10: 46054 | B10: Baby Sitter | C10: Baby Sitter | E10: -880 | Y10: Entertainment | Z10: =Summary!N27 -> 150 | AA10: =SUMIF($C$2:$C$51,Y10,$F$2:$F$51)+SUMIF($C$2:$C$51,Y10,$G$2:$G$51)+E24 -> -435 | AB10: =Z10+AA10 -> -285 | AD10: 401K
A11: 46056 | B11: Paycheck | C11: Paycheck | E11: 378 | Y11: Gas | Z11: =Summary!N28 -> 200 | AA11: =SUMIF($C$2:$C$51,Y11,$F$2:$F$51)+SUMIF($C$2:$C$51,Y11,$G$2:$G$51) -> -197.94 | AB11: =Z11+AA11 -> 2.06 | AD11: Chase & Amex
A12: 46056 | B12: Offering - Radiance | C12: Offering | F12: -50 | Y12: Gifts | Z12: =Summary!N29 -> 200 | AA12: =SUMIF($C$2:$C$51,Y12,$F$2:$F$51)+SUMIF($C$2:$C$51,Y12,$G$2:$G$51) -> -423 | AB12: =Z12+AA12 -> -223 | AD12: Total | AE12: =SUM(AE6:AE11) -> 300
A13: 46056 | B13: Gas | C13: Gas | F13: -47.94 | Y13: Grocery | Z13: =Summary!N30 -> 1000 | AA13: =SUMIF($C$2:$C$51,Y13,$F$2:$F$51)+SUMIF($C$2:$C$51,Y13,$G$2:$G$51) -> -777 | AB13: =Z13+AA13 -> 223
A14: 46059 | B14: Dininig | C14: Dining | F14: =-65-150-100 -> -315 | G14: =-150-55-62-83-42-42 -> -434 | Y14: Gym | Z14: =Summary!N31 -> 100 | AA14: =SUMIF($C$2:$C$51,Y14,$F$2:$F$51)+SUMIF($C$2:$C$51,Y14,$G$2:$G$51) -> 0 | AB14: =Z14+AA14 -> 100 | AD14: Gain/Loss in Investment
A15: 46059 | B15: Gofl | C15: Entertainment | F15: =-20-20-20-20 -> -80 | Y15: Loan | Z15: =Summary!N32 -> 0 | AA15: =SUMIF($C$2:$C$51,Y15,$F$2:$F$51)+SUMIF($C$2:$C$51,Y15,$G$2:$G$51) -> 0 | AB15: =Z15+AA15 -> 0 | AD15: Etrade | AE15: =P52 -> 3136
A16: 46059 | B16: House Stuff | C16: Grocery | F16: =-30-40-80 -> -150 | Y16: Misc | Z16: =Summary!N33 -> 500 | AA16: =SUMIF($C$2:$C$51,Y16,$F$2:$F$51)+SUMIF($C$2:$C$51,Y16,$G$2:$G$51)+E37 -> -300 | AB16: =Z16+AA16 -> 200 | AD16: BC | AE16: 0
A17: 46063 | B17: Clothes | C17: Clothes | G17: -150 | Y17: Offering | Z17: =Summary!N34 -> 800 | AA17: =SUMIF($C$2:$C$51,Y17,$F$2:$F$51)+SUMIF($C$2:$C$51,Y17,$G$2:$G$51) -> -499 | AB17: =Z17+AA17 -> 301 | AD17: Roth | AE17: =Q52 -> 0
A18: 46063 | B18: Offering - Ethnos | C18: Offering | F18: -50 | Y18: Rent | Z18: =Summary!N35 -> 4100 | AA18: =SUMIF($C$2:$C$51,Y18,$F$2:$F$51)+SUMIF($C$2:$C$51,Y18,$G$2:$G$51)+E4+E8+E7 -> -4138 | AB18: =Z18+AA18 -> -38 | AD18: UTMA | AE18: =Q52 -> 0
A19: 46063 | B19: Offering - Compassion | C19: Offering | F19: -93 | Y19: Travel | Z19: =Summary!N36 -> 0 | AA19: =SUMIF($C$2:$C$51,Y19,$F$2:$F$51)+SUMIF($C$2:$C$51,Y19,$G$2:$G$51) -> -1318 | AB19: =Z19+AA19 -> -1318 | AD19: 401K | AE19: =V52 -> 2606
A20: 46065 | B20: Cable - Paramount | C20: Cable | F20: -13 | Y20: Parents | Z20: =Summary!N37 -> 500 | AA20: =SUMIF($C$2:$C$51,Y20,$F$2:$F$51)+SUMIF($C$2:$C$51,Y20,$G$2:$G$51)+E6 -> -500 | AB20: =Z20+AA20 -> 0 | AD20: Chase & Amex | AE20: =+W52 -> 119.96
A21: 46065 | B21: School | C21: School | F21: -260 | Y21: Car | Z21: =Summary!N38 -> 200 | AA21: =SUMIF($C$2:$C$51,Y21,$F$2:$F$51)+SUMIF($C$2:$C$51,Y21,$G$2:$G$51) -> 0 | AB21: =Z21+AA21 -> 200 | AD21: Total | AE21: =SUM(AE15:AE20) -> 5861.96
A22: 46066 | B22: Haircut | C22: Misc | F22: -50 | Y22: House | Z22: =Summary!N39 -> 200 | AA22: =SUMIF($C$2:$C$51,Y22,$F$2:$F$51)+SUMIF($C$2:$C$51,Y22,$G$2:$G$51) -> -157 | AB22: =Z22+AA22 -> 43
A23: 46069 | B23: Paycheck | C23: Paycheck | E23: =5000+5178 -> 10178 | Y23: School | Z23: =Summary!N40 -> 0 | AA23: =SUMIF($C$2:$C$51,Y23,$F$2:$F$51)+SUMIF($C$2:$C$51,Y23,$G$2:$G$51) -> -260 | AB23: =Z23+AA23 -> -260
A24: 46069 | B24: Bruno Mars | C24: Entertainment | E24: -355 | Y24: Baby Sitter | Z24: =Summary!N41 -> 900 | AA24: =SUMIF($C$2:$C$51,Y24,$F$2:$F$51)+SUMIF($C$2:$C$51,Y24,$G$2:$G$51)+E10 -> -880 | AB24: =Z24+AA24 -> 20
A25: 46069 | B25: Dining | C25: Dining | F25: =-100-40-30 -> -170 | G25: =-120-136 -> -256
A26: 46069 | B26: Grocery | C26: Grocery | G26: =-60-33 -> -93
A27: 46069 | B27: Offering - GRC | C27: Offering | F27: -306
A28: 46069 | B28: Car Insurance | C28: Car Insurance | F28: -342
A29: 46069 | B29: AM Warranty | C29: Utilities | F29: -65
A30: 46069 | B30: House Stuff | C30: House | F30: =-79-78 -> -157
A31: 46069 | B31: Travel | C31: Travel | F31: -320
A32: 46071 | B32: Investmnet | C32: Investment | E32: -300 | R32: 300
A33: 46071 | B33: IRWD | C33: Utilities | E33: -79
A34: 46072 | B34: Gifts | C34: Gifts | F34: -6 | G34: -317
A35: 46073 | B35: Cable - ChatGPT | C35: Cable | F35: -30
A36: 46073 | B36: Cable - Netflix | C36: Cable | F36: -28
A37: 46074 | B37: Misc-Cleaning | C37: Misc | E37: -250
A38: 46076 | B38: Travel | C38: Travel | F38: -800 | G38: =-140-45-13 -> -198
A39: 46076 | B39: Utilities - Edison | C39: Utilities | E39: =-256.52-22.22 -> -278.74
A40: 46076 | B40: Grocery | C40: Grocery | G40: =-52-38 -> -90
A41: 46076 | B41: Cable - ATT | C41: Cable | F41: -85
A42: 46076 | B42: Gas | C42: Gas | F42: -150
A43: 46076 | B43: Cable - Substack | C43: Cable | F43: -40
A44: 46079 | B44: Crocery | C44: Grocery | G44: -165
A45: 46076 | B45: Cable - COX | C45: Cable | F45: -75
A46: 46080 | B46: Gifts | C46: Gifts | F46: -100
A47: 46080 | B47: Dining | C47: Dining | F47: =-150-100 -> -250 | G47: -70
A48: 46081 | B48: Grocery | C48: Grocery | F48: -279
A49: 46081 | B49: Paycheck | C49: Paycheck | E49: 4784
A50: 46080 | B50: Savings | C50: Savings | E50: -25 | I50: 25
A51: 46080 | B51: Payment | C51: Payment | E51: =-SUM(F51:G51) -> -6084.94 | F51: =-SUM(F4:F50) -> 4311.94 | G51: =-SUM(G4:G50) -> 1773
E52: =9200-SUM(E3:E51) -> -7084.32 | I52: 2000 | K52: 2000 | M52: 2000 | O52: 1000 | P52: 3136 | V52: 2606 | W52: =74+45.96 -> 119.96
A53: Balance | D53: =SUM(D3:D52) -> 2000 | E53: =SUM(E3:E52) -> 9200 | F53: =SUM(F3:F52) -> 0 | G53: =SUM(G3:G52) -> 0 | H53: =SUM(H3:H52) -> 14645.08 | I53: =SUM(I3:I52) -> 57040 | J53: =SUM(J3:J52) -> 153796 | K53: =SUM(K3:K52) -> 69712.68 | ... W53: =SUM(W3:W52) -> 3246.86 | Y53: Total | Z53: =SUM(Z4:Z51) -> 11985 | AA53: =SUM(AA4:AA51) -> -12830.68 | AB53: =SUM(AB4:AB51) -> -845.68
W55: =SUM(D53:W53) -> 1098715.2
Y57: PERCENTAGE
V58: Total Savings | W58: =SUM(H53:O53) -> 378752.38 | Y58: =W58/W61 -> 0.34472297
H59: . | V59: Total Investments | W59: =SUM(P53:W53) -> 708762.86 | Y59: =W59/W61 -> 0.64508331
V60: Total Checking | W60: =E53+D53 -> 11200 | Y60: =W60/W61 -> 0.010193724
V61: TOTAL | W61: =SUM(W58:W60) -> 1098715.2
W63: =W61-W55 -> 0

Sheet Jan
D1: CHECKING | F1: CC | H1: SAVINGS | P1: INVESTMENT | W1: CC
A2: Date | B2: Name | C2: Categorization | D2: PK | E2: Main | F2: Chase | G2: Chase | H2: School | I2: Buy | J2: House | K2: Car | L2: Travel | M2: Child | N2: Gifts | O2: Emergency | P2: E-Home | Q2: BC | R2: Roth IRA | S2: UTMA | T2: KPMG | U2: USAA | V2: 401K | W2: Chase | Y2: Budget to Actual | AD2: Activity
D3: 2000 | E3: 9000 | F3: 0 | G3: 0 | H3: 14645.08 | I3: 50990 | J3: 151796 | K3: 66708.71 | L3: 20000.39 | M3: 30000.37 | N3: 3500 | O3: 25152.5 | P3: 206508 | Q3: 127109 | R3: 62955 | S3: 3879 | T3: 33181 | U3: 27298 | V3: 213880 | W3: 2944.3 | Y3: Category | Z3: Budget | AA3: Actual | AB3: Variance | AD3: Investment Activity
A4: 46023 | B4: Mortgage | C4: Rent | E4: -3688 | J4: 1000 | L4: 485.36 | Y4: Cable | Z4: =Summary!K21 -> 350 | AA4: =SUMIF($C$2:$C$63,Y4,$F$2:$F$63)+SUMIF($C$2:$C$63,Y4,$G$2:$G$63) -> -326 | AB4: =Z4+AA4 -> 24
A5: 46023 | B5: Utilities HOA | C5: Utilities | E5: =612-285 -> 327 | Y5: Car Insurance | Z5: =Summary!K22 -> 335 | AA5: =SUMIF($C$2:$C$63,Y5,$F$2:$F$63)+SUMIF($C$2:$C$63,Y5,$G$2:$G$63) -> -342 | AB5: =Z5+AA5 -> -7 | AD5: Invested Amount for month
A6: 46023 | B6: Parents | C6: Parents | E6: -200 | Y6: Cleaners | Z6: =Summary!K23 -> 20 | AA6: =SUMIF($C$2:$C$63,Y6,$F$2:$F$63)+SUMIF($C$2:$C$63,Y6,$G$2:$G$63) -> 0 | AB6: =Z6+AA6 -> 20 | AD6: Etrade
A7: 46023 | B7: Rent | C7: Rent | E7: -4250 | Y7: Clothes | Z7: =Summary!K24 -> 300 | AA7: =SUMIF($C$2:$C$63,Y7,$F$2:$F$63)+SUMIF($C$2:$C$63,Y7,$G$2:$G$63) -> -353 | AB7: =Z7+AA7 -> -53 | AD7: CC | AE7: =Q45 -> 3000
A8: 46023 | B8: Rent | C8: Rent | E8: 3804 | Y8: Utilities | Z8: =Summary!K25 -> 700 | AA8: =SUMIF($C$2:$C$63,Y8,$F$2:$F$63)+SUMIF($C$2:$C$63,Y8,$G$2:$G$63)+E33+E47 -> -492 | AB8: =Z8+AA8 -> 208 | AD8: UTMA | AE8: =S22 -> 200
A9: 46023 | B9: Paycheck | C9: Paycheck | E9: 4874 | Y9: Dining | Z9: =Summary!K26 -> 1300 | AA9: =SUMIF($C$2:$C$63,Y9,$F$2:$F$63)+SUMIF($C$2:$C$63,Y9,$G$2:$G$63) -> -1652 | AB9: =Z9+AA9 -> -352 | AD9: Roth | AE9: =R34 -> 300
A10: 46023 | B10: Cable -ChatGPT | C10: Cable | G10: -20 | Y10: Entertainment | Z10: =Summary!K27 -> 150 | AA10: =SUMIF($C$2:$C$63,Y10,$F$2:$F$63)+SUMIF($C$2:$C$63,Y10,$G$2:$G$63)+E42 -> -733 | AB10: =Z10+AA10 -> -583 | AD10: 401K
A11: 46023 | B11: Grocery | C11: Grocery | F11: =-62-89-250 -> -401 | G11: -150 | Y11: Gas | Z11: =Summary!K28 -> 200 | AA11: =SUMIF($C$2:$C$63,Y11,$F$2:$F$63)+SUMIF($C$2:$C$63,Y11,$G$2:$G$63) -> -160 | AB11: =Z11+AA11 -> 40 | AD11: Total | AE11: =SUM(AE6:AE10) -> 3500
A12: 46023 | B12: Offering - Serge | C12: Offering | F12: -50 | Y12: Gifts | Z12: =Summary!K29 -> 200 | AA12: =SUMIF($C$2:$C$63,Y12,$F$2:$F$63)+SUMIF($C$2:$C$63,Y12,$G$2:$G$63)+E22 -> -275 | AB12: =Z12+AA12 -> -75
A13: 46023 | B13: Offering - GRC | C13: Offering | F13: -306 | Y13: Grocery | Z13: =Summary!K30 -> 1000 | AA13: =SUMIF($C$2:$C$63,Y13,$F$2:$F$63)+SUMIF($C$2:$C$63,Y13,$G$2:$G$63) -> -1314 | AB13: =Z13+AA13 -> -314
A14: 46023 | B14: Offering - Radiance | C14: Offering | F14: -50 | Y14: Gym | Z14: =Summary!K31 -> 100 | AA14: =SUMIF($C$2:$C$63,Y14,$F$2:$F$63)+SUMIF($C$2:$C$63,Y14,$G$2:$G$63) -> 0 | AB14: =Z14+AA14 -> 100 | AD14: Gain/Loss in Investment
A15: 46023 | B15: House | C15: House | F15: -144 | Y15: Loan | Z15: =Summary!K32 -> 0 | AA15: =SUMIF($C$2:$C$63,Y15,$F$2:$F$63)+SUMIF($C$2:$C$63,Y15,$G$2:$G$63) -> 0 | AB15: =Z15+AA15 -> 0 | AD15: Etrade | AE15: =P64 -> 3945
A16: 46027 | B16: Dining | C16: Dining | F16: =-80-39-29-16-22-4-33 -> -223 | G16: =-30-30-41 -> -101 | Y16: Misc | Z16: =Summary!K33 -> 2000 | AA16: =SUMIF($C$2:$C$63,Y16,$F$2:$F$63)+SUMIF($C$2:$C$63,Y16,$G$2:$G$63)+E23 -> -287 | AB16: =Z16+AA16 -> 1713 | AD16: BC
A17: 46027 | B17: Offering - Crosspoint | C17: Offering | E17: -50 | Y17: Offering | Z17: =Summary!K34 -> 800 | AA17: =SUMIF($C$2:$C$63,Y17,$F$2:$F$63)+SUMIF($C$2:$C$63,Y17,$G$2:$G$63)+E17 -> -1264 | AB17: =Z17+AA17 -> -464 | AD17: UTMA | AE17: =S64 -> 106
A18: 46027 | B18: Baby Sitter | C18: Baby Sitter | E18: -880 | Y18: Rent | Z18: =Summary!K35 -> 4100 | AA18: =SUMIF($C$2:$C$63,Y18,$F$2:$F$63)+SUMIF($C$2:$C$63,Y18,$G$2:$G$63)+E4+E7+E8 -> -4134 | AB18: =Z18+AA18 -> -34 | AD18: Roth | AE18: =R64 -> 1616
A19: 46028 | B19: Grocery | C19: Grocery | F19: =-63-12-22-35-150 -> -282 | G19: =-120-30-60 -> -210 | Y19: Travel | Z19: =Summary!K36 -> 150 | AA19: =SUMIF($C$2:$C$63,Y19,$F$2:$F$63)+SUMIF($C$2:$C$63,Y19,$G$2:$G$63)+E44 -> 0 | AB19: =Z19+AA19 -> 150 | AD19: 401K | AE19: =V64 -> 15497
A20: 46029 | B20: Cable - Netflix | C20: Cable | F20: -43 | Y20: Parents | Z20: =Summary!K37 -> 200 | AA20: =SUMIF($C$2:$C$63,Y20,$F$2:$F$63)+SUMIF($C$2:$C$63,Y20,$G$2:$G$63)+E6 -> -200 | AB20: =Z20+AA20 -> 0 | AD20: Chase & Amex | AE20: =W64 -> 182.6
A21: 46029 | B21: Dining | C21: Dining | E21: 10 | F21: =-25-20-58-44-75-14-64-92-70-38-45 -> -545 | G21: =-15-190-80+50-70-100-15-11 -> -431 | Y21: Car | Z21: =Summary!K38 -> 200 | AA21: =SUMIF($C$2:$C$63,Y21,$F$2:$F$63)+SUMIF($C$2:$C$63,Y21,$G$2:$G$63) -> 0 | AB21: =Z21+AA21 -> 200 | AD21: Total | AE21: =SUM(AE15:AE20) -> 21346.6
A22: 46029 | B22: Gifts - Riley | C22: Gifts | E22: -200 | F22: -75 | S22: 200 | Y22: House | Z22: =Summary!K39 -> 200 | AA22: =SUMIF($C$2:$C$63,Y22,$F$2:$F$63)+SUMIF($C$2:$C$63,Y22,$G$2:$G$63) -> -425 | AB22: =Z22+AA22 -> -225
A23: 46031 | B23: Misc | C23: Misc | E23: 250 | F23: =-65-75-37-30-125 -> -332 | G23: -60 | Y23: School | Z23: =Summary!K40 -> 120 | AA23: =SUMIF($C$2:$C$63,Y23,$F$2:$F$63)+SUMIF($C$2:$C$63,Y23,$G$2:$G$63) -> -570 | AB23: =Z23+AA23 -> -450
A24: 46032 | B24: Entertainment | C24: Entertainment | F24: =-20-85-30 -> -135 | Y24: Baby Sitter | Z24: =Summary!K41 -> 900 | AA24: =SUMIF($C$2:$C$63,Y24,$F$2:$F$63)+SUMIF($C$2:$C$63,Y24,$G$2:$G$63)+E18 -> -880 | AB24: =Z24+AA24 -> 20
A25: 46034 | B25: Gas | C25: Gas | F25: -80
A26: 46034 | B26: Offering - Ethnos | C26: Offering | F26: -50
A27: 46034 | B27: Offering - Compassion | C27: Offering | F27: -93
A28: 46034 | B28: Cable - Paramount | C28: Cable | F28: -14
A29: 46035 | B29: Cable - ESPN | C29: Cable | F29: -30
A30: 46035 | B30: House - Camping Gear | C30: House | F30: -80 | G30: =-14-12 -> -26
A31: 46035 | B31: Cable - Microsoft | C31: Cable | F31: -4
A32: 46035 | B32: House - Baby Stuff | C32: House | F32: -75
A33: 46036 | B33: Utilities - IRWD + Warranty | C33: Utilities | E33: =-90-75 -> -165 | F33: -66
A34: 46037 | B34: Investment | C34: Investment | E34: -300 | R34: 300
A35: 46037 | B35: Paycheck | C35: Paycheck | E35: 5000
A36: 46037 | B36: Offering - GRC | C36: Offering | F36: -309
A37: 46037 | B37: Car Insurance | C37: Car Insurance | F37: -342
A38: 46037 | B38: Paycheck | C38: Paycheck | E38: 4794
A39: 46041 | B39: Cable - Peacock | C39: Cable | F39: -20
A40: 46042 | B40: Cable - Netflix ChatGPT | C40: Cable | F40: =-27-20 -> -47
A41: 46043 | B41: Clothes | C41: Clothes | F41: =-90-150 -> -240 | G41: -113
A42: 46043 | B42: Entertainment | C42: Entertainment | E42: =-210-200 -> -410 | F42: =-86-45-7-50 -> -188
A43: 46045 | B43: House | C43: House | F43: -100
A44: 46045 | B44: Cable - ATT | C44: Cable | F44: -80
A45: 46045 | B45: Investment | C45: BC | E45: -4000 | Q45: 3000
A46: 46048 | B46: Paycheck | C46: Paycheck | E46: 5000
A47: 46048 | B47: Utilities - Edison | C47: Utilities | E47: =-206-25 -> -231 | G47: -30
A48: 46048 | B48: Cable - Michael Burry | C48: Cable | F48: -36
A49: 46048 | B49: Cable - Ring | C49: Cable | F49: -5
A50: 46048 | B50: Payment | C50: Payment | E50: =-2196-4 -> -2200 | F50: 2196
A51: 46048 | B51: Cable - COX | C51: Cable | F51: -70
A52: 45684 | B52: Grocery | C52: Grocery | F52: =-1-38 -> -39 | G52: =-102-30-20 -> -152
A53: 45684 | B53: Misc- CPE | C53: School | F53: =-200-340-30 -> -570
A54: 45687 | B54: Paycheck | C54: Paycheck | E54: 4794.41
A55: 111795 | B55: Dining | C55: Dining | F55: -200 | G55: -77
A56: 46053 | B56: Misc- CPE | C56: Misc | F56: -70 | G56: -75
A57: 46053 | B57: Offering - GRC | C57: Offering | F57: -306
A58: 46053 | B58: Offering - Serge | C58: Offering | F58: -50
A59: 46053 | B59: Grocery | C59: Grocery | G59: =-80 -> -80
A60: 46053 | B60: Dining | C60: Dining | G60: -75
A61: 46053 | B61: Gas | C61: Gas | F61: -80
A62: 46053 | B62: Savings | C62: Savings | E62: -25 | I62: 25
A63: 46053 | B63: Payment | C63: Payment | E63: =-SUM(F63:G63) -> -5234 | F63: =-SUM(F4:F62) -> 3634 | G63: =-SUM(G4:G62) -> 1600
E64: =9100-SUM(E3:E63) -> -6920.41 | I64: 4000 | K64: 500 | L64: 500 | N64: 500 | O64: 420 | P64: 3945 | R64: 1616 | S64: 106 | V64: 15497 | W64: =87.5+66.69+28.41 -> 182.6
A65: Balance | D65: =SUM(D3:D64) -> 2000 | E65: =SUM(E3:E64) -> 9100 | F65: =SUM(F3:F64) -> 0 | G65: =SUM(G3:G64) -> 0 | H65: =SUM(H3:H64) -> 14645.08 | I65: =SUM(I3:I64) -> 55015 | J65: =SUM(J3:J64) -> 152796 | K65: =SUM(K3:K64) -> 67208.71 | ... W65: =SUM(W3:W64) -> 3126.9 | Y65: Total | Z65: =SUM(Z4:Z63) -> 13325 | AA65: =SUM(AA4:AA63) -> -13407 | AB65: =SUM(AB4:AB63) -> -82
W67: =SUM(D65:W65) -> 1083924.3
Y69: PERCENTAGE
V70: Total Savings | W70: =SUM(H65:O65) -> 370223.41 | Y70: =W70/W73 -> 0.34155836
V71: Total Investments | W71: =SUM(P65:W65) -> 702600.9 | Y71: =W71/W73 -> 0.64820107
V72: Total Checking | W72: =E65+D65 -> 11100 | Y72: =W72/W73 -> 0.010240567
V73: TOTAL | W73: =SUM(W70:W72) -> 1083924.3
W74: =W73-W67 -> 0
